Workbook
Name _age2: 資料輸入區!$L$39
Name _Sex2: 資料輸入區!$K$70
Name Age: 資料輸入區!$I$10
Name Corridor: 險種基本資料!$A$36:$D$146
Name CSWD: 險種基本資料!$G$14
Name CurrList: 險種基本資料!$A$30:$A$33
Name CYPremium: 資料輸入區!$N$23
Name dangerRate: 險種基本資料!$D$2
Name DecareRate: 資料輸入區!$E$20
Name DVAC: 險種基本資料!$G$15
Name factor_key: 險種基本資料!$C$23:$E$24
Name factor_key_3: #REF!
Name firstpay: 資料輸入區!$N$20
Name FYPremium: 資料輸入區!$N$22
Name GP: 險種基本資料!$F$24
Name GP_3: #REF!
Name isRec: 資料輸入區!$M$51
Name ListDIVOPT01: 險種基本資料!$F$13:$F$14
Name ListDIVOPT02: 險種基本資料!$G$14:$G$16
Name ListDIVOPT02_: 險種基本資料!$G$13:$G$16
Name ListSex: 資料輸入區!$B$41:$B$42
Name LoanP: 資料輸入區!$E$28
Name MinSA: 險種基本資料!$F$28
Name PayYear: 資料輸入區!$D$12
Name PDRate: 資料輸入區!$E$21
Name PMST: 險種基本資料!$G$13
Name Premium: 險種基本資料!$AO$4
Name PremMuti: 險種基本資料!$B$18
Name PUAD: 險種基本資料!$G$16
Name PUAYear: 險種基本資料!$B$16
Name RoundNo: 險種基本資料!$B$15
Name SA: 資料輸入區!$N$12
Name SA_3: 資料輸入區!$O$12
Name SA_3C: 資料輸入區!$U$12
Name SameOwner: 資料輸入區!$G$5
Name Sex: 資料輸入區!$G$10
Name UNIT: 險種基本資料!$B$13
Name UNIT3: #REF!
Name UVUNIT: 險種基本資料!$B$14
Name UVUNIT3: #REF!
Name ZDIVOPT01: 資料輸入區!$E$18
Name ZDIVOPT02: 資料輸入區!$E$19
Name 期繳: 資料輸入區!$B$36:$B$39
Name 躉繳: 資料輸入區!$B$40

Sheet 資料輸入區
Q1: EBKD6UD411501380 115.01版
B2: 凱基人壽美利成臻美元利率變動型終身壽險－定期給付型
B4: ◎請於"反白"儲存格填入相關基本資料
B5: 要保人／被保險人／實際繳交保費之人相同 | G5: 是 | I5: =IF(AND(PayYear=1,LoanP="是"),IF(SameOwner="是","",IF(AND(Sex=G32,E11=E33,G11=G33,I11=I33),"","※要保人與被保險人須為同一人。")),"")
I6: =IF(M51,IF(H53,"※"&G53,"")&I53&IF(H54,G54,"")&I54&IF(H55,G55,"")&"保險年齡達六十五歲(含)以上，需配合進行銷售過程錄音，並請填寫下方『高齡錄音相關資料』。","") -> ※要保人、被保人、實際繳交保費之人保險年齡達六十五歲(含)以上，需配合進行銷售過程錄音，並請填寫下方『高齡錄音相關資料』。
A7: =IF(M48,IF(L30<20,"要保人未滿二十足歲，被保險人或實際繳交保費之人保險年齡達七十歲(含)以上，要保人、被保險人及要保人之『所有』法定代理人(父及母)需配合進行銷售過程錄音。","要保人或被保險人或實際繳交保費之人保險年齡若達七十歲(含)以上，要保人需配合進行銷售過程錄音。"),"")
B8: 被保險人基本資料與壽險購買條件設定 | M8: 訊息反應區
B9: ◎請於"反白"儲存格填入相關基本資料 | I9: 單位：美元 | P9: 單位：美元
B10: 1.姓名 | D10: AAA | F10: 性別 | G10: 男性 | H10: 保險年齡 | I10: =IF(OR(H37<0,H39<VLOOKUP(PayYear,險種基本資料!B2:I11,5,FALSE),H39>VLOOKUP(PayYear,險種基本資料!B2:I11,6,FALSE)),"NA",H39) -> 71 | J10: 歲 | N10: 美利成臻 | O10: 美好加在 | R10: 合計保費
B11: 2.生日 | D11: 民國 | E11: 44 | F11: 年 | G11: 1 | H11: 月 | I11: 23 | J11: 日出生 | M11: 保險年齡 | N11: =I10 -> 71 | O11: =IF(E25="不附加","-",IF(G25<>"","NA",_age2)) -> 71 | P11: 歲 | U11: SA_3C
B12: 3.繳費年期 | D12: =VLOOKUP(E12,險種基本資料!A2:B11,2,FALSE) -> 1 | E12: 躉 | F12: =IF(PayYear=1,"繳","年") -> 繳 | G12: =IF(F43<=10,"※假設試算日為生效日之年齡，再過"&F43&"天保險年齡加1歲。","") | M12: 投保金額 | N12: =IF(N11="NA","-",IF(M37,險種基本資料!AO3,"-")) -> 3701867 | O12: =IF(OR(SA="-",E25="不附加"),"-",IF(F25,"-",T12)) -> 0 | P12: 元 | S12: 豁免 保額 | T12: =IF(E25="附加",ROUND(ROUND(N14*(1-N15-N18-IF(N16>=1%,N16-1%,N16)),3),0),0) -> 0 | U12: =ROUND(SA_3/VLOOKUP(E13,B36:D39,3,FALSE),0) -> #N/A
B13: 4.繳別 | E13: 躉 | F13: 繳 | G13: =IF(OR(E11<>G48,G11<>H48,I11<>I48),"輸入生日有誤，請重新輸入",IF(OR(H37<0,H39<險種基本資料!D28,H39>險種基本資料!E28),"◎投保年齡限制為"&險種基本資料!D28&"~"&險種基本資料!E28&"歲，請重新輸入！",IF(NOT(M38),"請選擇正確繳別",""))) | M13: =IF(PayYear=1,"(1)每單位(1萬)躉繳表訂費率","(1)每單位(1萬)年繳表訂費率") -> (1)每單位(1萬)躉繳表訂費率 | N13: =IF(M37,GP,"-") -> 7714 | O13: =IF(OR(SA="-",E25="不附加"),"-",IF(F25,"-",GP_3/10)) -> #REF! | P13: 元 | S13: 費率 | T13: =IF(_age2="NA","-",GP_3/10) -> #REF!
B14: 5.計算方式 | E14: 保額 | G14: =IF(E14="保費","此欄位為試算保費金額，實際繳交保費應以試算表上所載首期保險費金額為準。","") | M14: (2)原始總保費=(1)*(保額÷單位)*繳別率(四捨五入) | N14: =IF(M37,ROUND(ROUND(ROUNDDOWN(ROUND(SA*UNIT/UVUNIT*GP,3),2)*VLOOKUP(E13,B36:D40,3,FALSE),3),0),"-") -> 2855620 | O14: =IF(OR(SA="-",E25="不附加"),"-",IF(F25,"-",T14)) -> #REF! | P14: 元 | R14: =SUM(N14:O14) -> #REF! | S14: 豁免 原始保費 | T14: =ROUND(ROUND(ROUNDDOWN(ROUND(T12*UNIT3/UVUNIT3*T13,3),2),3),0) -> #REF!
B15: =IF(E14="保額","6.保險金額","6."& "預計"&IF(PayYear=1,E13,"年")&"繳保費") -> 6.保險金額 | E15: 3701867 | F15: 元 | G15: =IF(險種基本資料!AO3<險種基本資料!F28,"最低投保金額為"&TEXT(險種基本資料!F28,"###,###,##0")&"元，請重新輸入！",IF(險種基本資料!AO3>險種基本資料!G28,"最高投保金額為"&TEXT(險種基本資料!G28,"###,###,##0")&"元，請重新輸入！",IF(AND(H37<15,險種基本資料!G24>險種基本資料!F19),"※未滿十五足歲其個人累計壽險危險保額最高限新台幣1,000萬元。",""))) | M15: (3)高保費費率折減 | N15: =IF(N11="NA","-",險種基本資料!C28) -> 0.07 | O15: -
B16: 7.首期繳費方式 | E16: 金融機構轉帳 | G16: =IF(AND($D$12=6,$E$15="集彙"),"六年期不適用集體彙繳折減優惠，請重新選擇繳費方式!",IF(PayYear = 1,"躉繳不提供保費折減",IF(E16="-","請選擇繳費方式",""))) -> 躉繳不提供保費折減 | M16: =IF(PayYear=1,"(4)躉繳保險費(2)*【1-(3)】","(4)首期"&E16&"費率折減") -> (4)躉繳保險費(2)*【1-(3)】 | N16: =IF(PayYear=1,TEXT(ROUND(ROUND(N14*(1-N15),3),0),"#,##0"),VLOOKUP(E16,E44:H47,2,FALSE)) -> 2,655,727 | P16: =IF(PayYear=1,"元","") -> 元 | S16: =VLOOKUP(E17,G44:H46,2,FALSE) -> 0
B17: 8.續期繳費方式 | E17: 金融機構轉帳 | G17: =IF(PayYear = 1,"躉繳不適用此選項",IF(E17="-","請選擇繳費方式","")) -> 躉繳不適用此選項 | M17: =IF(PayYear = 1,"實際繳交保費","(5)續期"&E17&"費率折減") -> 實際繳交保費 | N17: =IF(PayYear = 1,TEXT(IF(M37,IF(VLOOKUP(E13,B36:C40,2,FALSE)=12,2,1)*ROUND(ROUND(N14*(1-N18),3),0),"-"),"#,##0"),VLOOKUP(E17,G44:H46,2,FALSE)) -> 2,655,727 | S17: =IF(N11="NA","-",N15+IF(PayYear=1,0,N16)) -> 0.07
B18: 9.第一保單年度至第六保單年度增值回饋分享金給付方式 | E18: 以繳清保險方式增加保險金額 | G18: =IF($E$18=PMST,"繳費期間抵繳應繳保險費，繳費期滿以繳清保險方式增加保險金額","") | M18: (6)首期合計費率折減=(3)+(4) | N18: =IF(N11="NA","-",N15+IF(PayYear=1,0,N16)) -> 0.07 | O18: =IF(E25="不附加","-",N16) -> 2,655,727 | S18: =IF(N11="NA","-",N15+S16) -> 0.07
B19: =IF(PayYear=1,"7.增值回饋分享金給付方式","10.第七保單年度起增值回饋分享金給付方式") -> 7.增值回饋分享金給付方式 | E19: 以繳清保險方式增加保險金額 | G19: =IF(資料輸入區!I10<16,"※被保險人保險年齡到達十六歲之保單週年日時，其增值回饋分享金請參照保單條款。"," ") | M19: =IF(PayYear=1,"(4)躉繳保險費(2)*【1-(3)】","(7)續期合計費率折減=(3)+(5)") -> (4)躉繳保險費(2)*【1-(3)】 | N19: =IF(N11="NA","-",IF(PayYear=1,TEXT(ROUND(ROUND(N14*(1-N15),3),0),"#,##0"),N15+N17)) -> 2,655,727 | O19: =IF(E25="不附加","-",N17) -> 2,655,727 | P19: =IF(PayYear=1,"元","") -> 元
B20: 宣告利率(假設值) | E20: 4.35 | F20: % | G20: ※使用本試算表請確認宣告利率 | M20: =IF(PayYear=1,"實際繳交保費","(8)"&IF(N16>0,"扣除"&E16&"費率折減後，","")&"首期"&E13&"繳保險費=(2)*【1-"&IF(PayYear=1,"(5)","(6)")&"】(四捨五入)"&IF(E13="月","*2","")) -> 實際繳交保費 | N20: =IF(M37,IF(VLOOKUP(E13,B36:C40,2,FALSE)=12,2,1)*ROUND(ROUND(N14*(1-N18),3),0),"-") -> 2655727 | O20: =IF(OR(SA="-",E25="不附加"),"-",IF(F25,"-",T20)) -> #N/A | P20: 元 | R20: =SUM(N20:O20) -> #N/A | S20: 首期保費 | T20: =IF(VLOOKUP(E13,B36:C39,2,FALSE)=12,2,1)*ROUND(ROUND(T13*(1-P18),3),0) -> #N/A
B21: 預定利率 | E21: =險種基本資料!A28 -> 1.75 | F21: % | M21: =IF(PayYear=1,"","(9)"&IF(N17>0,"扣除"&E17&"費率折減後，","")&"續期"&E13&"繳保險費=(2)*【1-(7)】(四捨五入)") | N21: =IF(M37,ROUND(ROUND(N14*(1-N19),3),0),"-") -> -7583744280120 | O21: =IF(OR(SA="-",E25="不附加"),"-",IF(F25,"-",T21)) -> #REF! | P21: 元 | R21: =SUM(N21:O21) -> #REF! | S21: 續期保費 | T21: =ROUND(ROUND(T13*(1-P19),3),0) -> #REF!
B22: 是否超過體檢額度 | E22: =IF(SA="-","-",IF(SA<=險種基本資料!I24,"免體檢 （詳警語）","需體檢")) -> 需體檢 | F22: =IF(SA="-","","※【主約保險金額】若超過上限"&TEXT(險種基本資料!I24,"#,##0")&"元則需體檢") -> ※【主約保險金額】若超過上限500,000元則需體檢 | M22: ="(10)首年實繳保險費=(8)*1+(9)*"&(VLOOKUP(E13,B36:C40,2,FALSE)-IF(E13="月",2,1)) -> (10)首年實繳保險費=(8)*1+(9)*0 | N22: =IF(M37,N20+(VLOOKUP(E13,B36:C40,2,FALSE)-IF(VLOOKUP(E13,B36:C40,2,FALSE)=12,2,1))*N21,"-") -> 2655727 | O22: =IF(OR(SA="-",E25="不附加"),"-",IF(F25,"-",O20+O21*(VLOOKUP(E13,B36:C39,2,FALSE)-IF(VLOOKUP(E13,B36:C39,2,FALSE)=12,2,1)))) -> #N/A | P22: 元
M23: (11)續年實繳保險費=(9)*繳費次數 | N23: =IF(M37,VLOOKUP(E13,B36:C40,2,FALSE)*N21,"-") -> -7583744280120 | O23: =IF(OR(SA="-",E25="不附加"),"-",IF(F25,"-",O21*VLOOKUP(E13,B36:C39,2,FALSE))) -> #REF! | P23: 元
M24: =PayYear&"年總保費" -> 1年總保費 | N24: =IF(M37,FYPremium+(PayYear-1)*CYPremium,"-") -> 2655727 | O24: =IF(OR(SA="-",E25="不附加"),"-",IF(F25,"-",O22+O23*(PayYear-1))) -> #N/A | P24: 元
M25: 註：本試算表內容數值僅供參考，容有四捨五入之些微誤差，各期實繳保費及實際給付內容仍應以保單面頁數值為準。
K26: ※要被保險人須為同一人，方能執行豁免保費貼現試算頁之試算功能。
B28: 審閱期間確認聲明書標示 「凱基人壽保費融資批註條款」 | E28: 否 | F28: =IF(LoanP="是",IF(OR(SameOwner="是",AND(E33=E11,G33=G11,I33=I11,G32=Sex)),"","※要保人與被保險人須為同一人"),"")
B29: ※投保本商品可申請辦理「保費融資批註條款」，若申請「保費融資批註條款」時，當件保單限制要保人與被保險人須為同一人且必須檢附「辦理保費融資批註條款重要事項告知暨聲明書」。
B30: ※本Excel試算表檔案，需於PC/NB之MS Windows系統及合法授權的MS Office Excel軟體中執行。其他作業系統或非MS Office Excel軟體將可能發生無法預期之錯誤或無法順利運行。
B31: 要保人／實際繳交保費之人資料輸入區
B32: 要保人姓名 | D32: AAA | F32: 性別 | G32: 男性
B33: 要保人生日 | D33: 民國 | E33: 44 | F33: 年 | G33: 1 | H33: 月 | I33: 1 | J33: 日出生 | K33: =IF(DATE(E33+1911,G33,I33)>TODAY(),"請重新輸入生日",IF(ISERROR(DATEVALUE((E33+1911)&"/"&G33&"/"&I33)),"請重新輸入生日","保險年齡："&L39&"歲")) -> 保險年齡：71歲 | N33: =IF(K33="請重新輸入生日","",IF(J46<=10,"※假設試算日為生效日之年齡，再過"&J46&"天保險年齡加1歲。",""))
B34: 實際繳交保費之人姓名 | D34: CCC | F34: 性別 | G34: 男性
B35: 實際繳交保費之人生日 | D35: 民國 | E35: 44 | F35: 年 | G35: 5 | H35: 月 | I35: 16 | J35: 日出生 | K35: =IF(DATE(E35+1911,G35,I35)>TODAY(),"請重新輸入生日",IF(ISERROR(DATEVALUE((E35+1911)&"/"&G35&"/"&I35)),"請重新輸入生日","保險年齡："&L42&"歲")) -> 保險年齡：71歲 | N35: =IF(K35="請重新輸入生日","",IF(J49<=10,"※假設試算日為生效日之年齡，再過"&J49&"天保險年齡加1歲。",""))
B36: 年 | C36: 1 | D36: 1 | E36: ="險種基本資料!"&險種基本資料!B25 -> 險種基本資料!A2:A2 | F36: today | J36: today
B37: 半年 | C37: 2 | D37: 0.52 | E37: 以繳清保險方式增加保險金額 | F37: =YEAR(TODAY()) -> 2026 | G37: =F37-(E11+1911) -> 71 | H37: =IF(OR(AND(G38=0,G39<0),AND(G38<0)),G37-1,G37) -> 71 | J37: =YEAR(TODAY()) -> 2026 | K37: =J37-(IF(SameOwner="是",E11,E33)+1911) -> 71 | L37: =IF(OR(AND(K38=0,K39<0),AND(K38<0)),K37-1,K37) -> 71 | M37: =AND(NOT(OR(OR(E11<>G48,G11<>H48,I11<>I48),OR(H37<0,H39<險種基本資料!D28,H39>險種基本資料!E28),險種基本資料!AO3<MinSA,險種基本資料!AO3>險種基本資料!G28,AND(E18=B45,E19=C44))),M38,M39) -> TRUE
B38: 季 | C38: 4 | D38: 0.262 | F38: =MONTH(TODAY()) -> 2 | G38: =F38-G11 -> 1 | H38: =IF(G39<0,IF(OR(G38<0,AND(G38=0,G39<0)),G38+12-1,G38-1),IF(G38<0,G38+12,G38)) -> 1 | I38: =IF(G11+6>12,G11-6,G11+6) -> 7 | J38: =MONTH(TODAY()) -> 2 | K38: =J38-IF(SameOwner="是",G11,G33) -> 1 | L38: =IF(K39<0,IF(OR(K38<0,AND(K38=0,K39<0)),K38+12-1,K38-1),IF(K38<0,K38+12,K38)) -> 1 | M38: =IF(E12="躉",E13="躉",E13<>"躉") -> TRUE | N38: 判斷繳費年期期繳別是否對應(躉繳應為躉繳，年繳不應躉繳)
A39: =IF(E12="躉","躉繳","期繳") -> 躉繳 | B39: 月 | C39: 12 | D39: 0.088 | F39: =DAY(TODAY()) -> 25 | G39: =F39-I11 -> 2 | H39: =H37+ROUND(H38/12,0)-IF(AND(ABS(G38)=6,G39=0),1,0) -> 71 | J39: =DAY(TODAY()) -> 25 | K39: =J39-IF(SameOwner="是",I11,I33) -> 2 | L39: =L37+ROUND(L38/12,0)-IF(AND(ABS(K38)=6,K39=0),1,0) -> 71 | M39: =IF(AND(PayYear=1,LoanP="是"),IF(SameOwner="是","",IF(AND(Sex=G32,E11=E33,G11=G33,I11=I33),TRUE,FALSE)),TRUE) -> TRUE
A40: 2 | B40: 躉 | C40: 1 | D40: 1 | J40: =YEAR(TODAY()) -> 2026 | K40: =J40-(IF(SameOwner="是",E11,E35)+1911) -> 71 | L40: =IF(OR(AND(K41=0,K42<0),AND(K41<0)),K40-1,K40) -> 71
B41: 男性 | C41: 1 | D41: 先生 | F41: =F37 -> 2026 | G41: =IF(G11+6>12,G11-6,G11+6) -> 7 | H41: =MIN(DAY(DATE(YEAR(TODAY()),IF(G11+6>12,G11-6,G11+6)+1,1)-1),I11) -> 23 | J41: =MONTH(TODAY()) -> 2 | K41: =J41-IF(SameOwner="是",G11,G35) -> 1 | L41: =IF(K42<0,IF(OR(K41<0,AND(K41=0,K42<0)),K41+12-1,K41-1),IF(K41<0,K41+12,K41)) -> 1
B42: 女性 | C42: 2 | D42: 女士 | F42: =IF(DATE(F41,G41,H41)<TODAY(),F41+1,F41) -> 2026 | G42: =G41 -> 7 | H42: =MIN(DAY(DATE(F42,G42+1,1)-1),I11) -> 23 | J42: =DAY(TODAY()) -> 25 | K42: =J42-IF(SameOwner="是",I11,I35) -> 2 | L42: =L40+ROUND(L41/12,0)-IF(AND(ABS(K41)=6,K42=0),1,0) -> 71
B43: =IF(PayYear<=PUAYear+1,"") | F43: =DATE(F42,G42,H42+1)-TODAY() -> 149
B44: =PMST -> 抵繳應繳保險費 | C44: 抵繳應繳保險費 | E44: 金融機構轉帳 | F44: =IF(PayYear=1,0,1%) -> 0 | G44: 金融機構轉帳 | H44: =IF(PayYear=1,0%,1%) -> 0 | J44: =J37 -> 2026 | K44: =IF(G33+6>12,G33-6,G33+6) -> 7 | L44: =MIN(DAY(DATE(YEAR(TODAY()),IF(G33+6>12,G33-6,G33+6)+1,1)-1),I33) -> 1
B45: =PUAD -> 以繳清保險方式增加保險金額 | C45: 現金給付 | E45: 匯款 | F45: =IF(PayYear=1,0%,IF(E17=G44,1%,0%)) -> 0 | G45: 其他 | H45: 0 | J45: =IF(DATE(J44,K44,L44)<TODAY(),J44+1,J44) -> 2026 | K45: =K44 -> 7 | L45: =MIN(DAY(DATE(J45,K45+1,1)-1),I33) -> 1
C46: 儲存生息 | E46: 信用卡 | F46: =IF(PayYear=1,0%,0%) -> 0 | G46: 信用卡 | H46: =IF(PayYear=1,0%,0%) -> 0 | J46: =DATE(J45,K45,L45+1)-TODAY() -> 127
C47: 以繳清保險方式增加保險金額 | E47: 其他 | F47: 0 | J47: =J40 -> 2026 | K47: =IF(G35+6>12,G35-6,G35+6) -> 11 | L47: =MIN(DAY(DATE(YEAR(TODAY()),IF(G35+6>12,G35-6,G35+6)+1,1)-1),I35) -> 16
F48: =DATE(E11+1911,G11,I11) -> 20112 | G48: =YEAR(F48)-1911 -> 44 | H48: =MONTH(F48) -> 1 | I48: =DAY(F48) -> 23 | J48: =IF(DATE(J47,K47,L47)<TODAY(),J47+1,J47) -> 2026 | K48: =K47 -> 11 | L48: =MIN(DAY(DATE(J48,K48+1,1)-1),I35) -> 16
A49: 是 | J49: =DATE(J48,K48,L48+1)-TODAY() -> 265 | M49: =OR(G15="",G15="※未滿十五足歲其個人累計壽險危險保額最高限新台幣1,000萬元。") -> TRUE
A50: 否 | M50: =OR(H39>=65,L39>=65,L42>=65) -> TRUE
A51: ="險種基本資料!A2:A"&險種基本資料!B24+1 -> 險種基本資料!A2:A2 | M51: =AND(M49,M50) -> TRUE
M52: =AND(isRec,L37<20) -> FALSE
C53: 提醒：因未滿七足歲，須由法定代理人代為簽名及法定代理人簽名。 | G53: 要保人 | H53: =AND(L39>=65,isRec) -> TRUE | I53: =IF(AND(H54,H53),"、",IF(AND(H55,H53),"、","")) -> 、
C54: ※ 未滿十五足歲之被保險人所投保之喪葬費用保險金額，不得超過遺產及贈與稅法第十七條有關遺產稅喪葬費扣除額之半數。 | G54: 被保人 | H54: =AND(H39>=65,isRec) -> TRUE | I54: =IF(AND(H55,H54,H53),"、",IF((AND(H55,H54)),"、","")) -> 、
C55: 提醒：因未滿二十足歲，須由本人及法定代理人簽名。 | G55: 實際繳交保費之人 | H55: =AND(L42>=65,isRec) -> TRUE
G56: =K69 -> AAA | H56: =IF(K70="男性","先生","女士") -> 先生 | I56: =G53&G56&H56 -> 要保人AAA先生
G57: =K71 -> AAA | H57: =IF(K72="男性","先生","女士") -> 先生 | I57: =G54&G57&H57 -> 被保人AAA先生
G58: =K73 -> AAA | H58: =IF(K74="男性","先生","女士") -> 先生 | I58: =G55&G58&H58 -> 實際繳交保費之人AAA先生
G59: 112.07版 | I59: =B2 -> 凱基人壽美利成臻美元利率變動型終身壽險－定期給付型
B63: =IF(AND(isRec,OR(K69="",K70="",K71="",K79="",K80="",K81="",K73="",K74="")),"【錄音範本資料輸入區輸入有誤，請重新輸入】","")
B64: 錄音範本資料輸入區
B65: 項次 | D65: 問項問題 | K65: 業務人員輸入欄位
B66: 1 | D66: 要保人投保保險年齡 | H66: 自動 | K66: =IF(K33="請重新輸入生日","請重新輸入生日",L39&"歲") -> 71歲
B67: 2 | D67: 被保人投保保險年齡 | H67: 自動 | K67: =Age&"歲" -> 71歲
B68: 3 | D68: 實際繳交保費之人年齡 | H68: 自動 | K68: =L42&"歲" -> 71歲
B69: 4 | D69: 要保人姓名 | H69: 自動 | K69: =IF(SameOwner="是",D10,D32) -> AAA
B70: 5 | D70: 要保人性別 | H70: 自動 | K70: =IF(SameOwner="是",Sex,G32) -> 男性
B71: 6 | D71: 被保險人姓名 | H71: 自動 | K71: =D10 -> AAA
B72: 7 | D72: 被保險人性別 | H72: 自動 | K72: =Sex -> 男性
B73: 8 | D73: 實際繳交保費之人姓名 | H73: 自動 | K73: =IF(SameOwner="是",D10,D34) -> AAA
B74: 9 | D74: 實際繳交保費之人性別 | H74: 自動 | K74: =IF(SameOwner="是",Sex,G34) -> 男性
B75: 10 | D75: 投保險種(全名) | H75: 自動 | K75: =B2 -> 凱基人壽美利成臻美元利率變動型終身壽險－定期給付型
B76: 11 | D76: 繳別 | H76: 自動 | K76: =E13&"繳" -> 躉繳
B77: 12 | D77: 繳費年期 | H77: 自動 | K77: =E12&"年期" -> 躉年期
B78: 13 | D78: 首期實繳保險費 | H78: 自動 | K78: =N20 -> 2655727
B79: 14 | D79: 公司名稱 | H79: 請自行輸入名稱 | K79: 凱基人壽
B80: 15 | D80: 業務人員姓名 | H80: 請自行輸入姓名 | K80: ○○○
B81: 16 | D81: 業務人員登錄證號 | H81: 請自行輸入 | K81: 00123789556

Sheet 險種基本資料
B1: 年期清單 | C1: 預定利率 | D1: 危額係數 | E1: 高保費費率折減 | F1: 投保年齡下限 | G1: 投保年齡上限 | H1: 保額下限 | I1: 保額上限 | J1: offset | L1: 解約金表 | M1: 年期 | X1: 2年期 | AI1: 銀保 | AJ1: 面額計算額度則危險係數放1
A2: 躉 | B2: 1 | C2: 1.85 | D2: =IF(Age>=71,0.2,IF(Age>=61,0.2,IF(Age>=51,0.3,IF(Age>=41,0.4,IF(Age>=31,0.4,IF(Age>=16,0.45,0.45)))))) -> 0.2 | E2: =IF(Premium>=1500000,7%,IF(Premium>=1200000,5.5%,IF(Premium>=800000,4%,IF(Premium>=500000,3%,IF(Premium>=200000,2%,IF(Premium>=100000,1%,0%)))))) -> 0.07 | F2: 18 | G2: 75 | H2: 3000 | I2: 10000000 | J2: 0 | L2: 年度 | M2: =OFFSET($B$2,0,0) -> 1 | N2: =OFFSET($B$2,1,0) -> 0 | O2: =OFFSET($B$2,2,0) -> 0 | P2: =OFFSET($B$2,3,0) -> 0 | Q2: =OFFSET($B$2,4,0) -> 0 | R2: =OFFSET($B$2,5,0) -> 0 | S2: =OFFSET($B$2,6,0) -> 0 | T2: =OFFSET($B$2,7,0) -> 0 | U2: =OFFSET($B$2,8,0) -> 0 | V2: =OFFSET($B$2,9,0) -> 0 | X2: 性別 | Z2: 男性 | AC2: 女性 | AG2: 年期 | AH2: 年齡下限 | AI2: 危險係數 | AK2: 年齡下限 | AL2: 主約免體檢額度 | AM2: 有附約 | AO2: =MAX(AR:AR) -> 5160101 | AP2: =ROUNDDOWN(資料輸入區!E15/(1-G45)/UNIT*UVUNIT/GP,0) -> 5160101 | AQ2: =ROUND(ROUND(ROUND(ROUNDDOWN(ROUND(AP2*UNIT/UVUNIT*GP,3),2),3),0)*(1-$G$45),0) -> 3701867 | AR2: =IF(AQ2>資料輸入區!$E$15,0,AP2) -> 5160101
J3: 1 | L3: 1 | M3: 0.08 | X3: 年齡 | Z3: 18 | AA3: 35 | AB3: 65 | AC3: 18 | AD3: 35 | AE3: 65 | AG3: 6 | AH3: 0 | AI3: 1 | AK3: 0 | AL3: 500 | AM3: 1000 | AO3: =IF(資料輸入區!E14="保費",險種基本資料!AO2,資料輸入區!E15) -> 3701867 | AP3: =AP2+1 -> 5160102 | AQ3: =ROUND(ROUND(ROUND(ROUNDDOWN(ROUND(AP3*UNIT/UVUNIT*GP,3),2),3),0)*(1-$G$45),0) -> 3701868 | AR3: =IF(AQ3>資料輸入區!$E$15,0,AP3) -> 0
J4: 2 | L4: 2 | M4: 0.08 | X4: 保單 年度 | Y4: 1 | Z4: 0.79 | AA4: 0.8 | AB4: 0.8 | AC4: 0.79 | AD4: 0.79 | AE4: 0.8 | AG4: 6 | AH4: 16 | AI4: 1 | AK4: 16 | AL4: 500 | AM4: 900 | AO4: =VLOOKUP(資料輸入區!E13,資料輸入區!B36:C40,2,0)*資料輸入區!N14 -> 2855620 | AP4: =AP3+1 -> 5160103 | AQ4: =ROUND(ROUND(ROUND(ROUNDDOWN(ROUND(AP4*UNIT/UVUNIT*GP,3),2),3),0)*(1-$G$45),0) -> 3701868 | AR4: =IF(AQ4>資料輸入區!$E$15,0,AP4) -> 0
J5: 3 | L5: 3 | M5: 0.01 | Y5: 2 | Z5: 0.79 | AA5: 0.8 | AB5: 0.8 | AC5: 0.79 | AD5: 0.79 | AE5: 0.79 | AG5: 6 | AH5: 31 | AI5: 1 | AK5: 46 | AL5: 500 | AM5: 800 | AP5: =AP4+1 -> 5160104 | AQ5: =ROUND(ROUND(ROUND(ROUNDDOWN(ROUND(AP5*UNIT/UVUNIT*GP,3),2),3),0)*(1-$G$45),0) -> 3701869 | AR5: =IF(AQ5>資料輸入區!$E$15,0,AP5) -> 0
J6: 4 | L6: 4 | M6: 0.01 | Y6: 3 | Z6: 0.85 | AA6: 0.86 | AB6: 0.85 | AC6: 0.85 | AD6: 0.85 | AE6: 0.85 | AG6: 6 | AH6: 41 | AI6: 1 | AK6: 51 | AL6: 500 | AM6: 550 | AP6: =AP5+1 -> 5160105 | AQ6: =ROUND(ROUND(ROUND(ROUNDDOWN(ROUND(AP6*UNIT/UVUNIT*GP,3),2),3),0)*(1-$G$45),0) -> 3701870 | AR6: =IF(AQ6>資料輸入區!$E$15,0,AP6) -> 0
J7: 5 | L7: 5 | M7: 0.01 | Y7: 4 | Z7: 0.85 | AA7: 0.86 | AB7: 0.85 | AC7: 0.85 | AD7: 0.85 | AE7: 0.85 | AG7: 6 | AH7: 51 | AI7: 1 | AK7: 56 | AL7: 500 | AM7: 250 | AP7: =AP6+1 -> 5160106 | AQ7: =ROUND(ROUND(ROUND(ROUNDDOWN(ROUND(AP7*UNIT/UVUNIT*GP,3),2),3),0)*(1-$G$45),0) -> 3701871 | AR7: =IF(AQ7>資料輸入區!$E$15,0,AP7) -> 0
J8: 6 | L8: 6 | M8: 0.01 | Y8: 5 | Z8: 0.85 | AA8: 0.85 | AB8: 0.84 | AC8: 0.85 | AD8: 0.85 | AE8: 0.85 | AG8: 6 | AH8: 61 | AI8: 1 | AK8: 61 | AL8: 500 | AM8: 100 | AP8: =AP7+1 -> 5160107 | AQ8: =ROUND(ROUND(ROUND(ROUNDDOWN(ROUND(AP8*UNIT/UVUNIT*GP,3),2),3),0)*(1-$G$45),0) -> 3701872 | AR8: =IF(AQ8>資料輸入區!$E$15,0,AP8) -> 0
J9: 7 | L9: 7 | M9: 0 | Y9: 10 | Z9: 0.85 | AA9: 0.84 | AB9: 0.8 | AC9: 0.85 | AD9: 0.85 | AE9: 0.82 | AG9: 6 | AH9: 71 | AI9: 1 | AK9: 66 | AL9: 500 | AM9: 0 | AP9: =AP8+1 -> 5160108 | AQ9: =ROUND(ROUND(ROUND(ROUNDDOWN(ROUND(AP9*UNIT/UVUNIT*GP,3),2),3),0)*(1-$G$45),0) -> 3701872 | AR9: =IF(AQ9>資料輸入區!$E$15,0,AP9) -> 0
J10: 8 | L10: 8 | M10: 0 | Y10: 15 | Z10: 0.83 | AA10: 0.81 | AB10: 0.73 | AC10: 0.84 | AD10: 0.83 | AE10: 0.77 | AK10: 71 | AL10: 50 | AP10: =AP9+1 -> 5160109 | AQ10: =ROUND(ROUND(ROUND(ROUNDDOWN(ROUND(AP10*UNIT/UVUNIT*GP,3),2),3),0)*(1-$G$45),0) -> 3701872 | AR10: =IF(AQ10>資料輸入區!$E$15,0,AP10) -> 0
J11: 9 | L11: 9 | M11: 0 | Y11: 20 | Z11: 0.82 | AA11: 0.78 | AB11: 0.67 | AC11: 0.83 | AD11: 0.82 | AE11: 0.71 | AP11: =AP10+1 -> 5160110 | AQ11: =ROUND(ROUND(ROUND(ROUNDDOWN(ROUND(AP11*UNIT/UVUNIT*GP,3),2),3),0)*(1-$G$45),0) -> 3701873 | AR11: =IF(AQ11>資料輸入區!$E$15,0,AP11) -> 0
L12: 10 | M12: 0 | AP12: =AP11+1 -> 5160111 | AQ12: =ROUND(ROUND(ROUND(ROUNDDOWN(ROUND(AP12*UNIT/UVUNIT*GP,3),2),3),0)*(1-$G$45),0) -> 3701874 | AR12: =IF(AQ12>資料輸入區!$E$15,0,AP12) -> 0
A13: 保額單位 | B13: 1 | F13: =PMST -> 抵繳應繳保險費 | G13: 抵繳應繳保險費 | L13: 11 | M13: 0 | X13: 6年期 | AI13: 經代 | AJ13: 面額計算額度則危險係數放1 | AP13: =AP12+1 -> 5160112 | AQ13: =ROUND(ROUND(ROUND(ROUNDDOWN(ROUND(AP13*UNIT/UVUNIT*GP,3),2),3),0)*(1-$G$45),0) -> 3701874 | AR13: =IF(AQ13>資料輸入區!$E$15,0,AP13) -> 0
A14: 精算單位 | B14: 10000 | F14: =PUAD -> 以繳清保險方式增加保險金額 | G14: 現金給付 | L14: 12 | M14: 0 | X14: 性別 | Z14: 男性 | AC14: 女性 | AG14: 年期 | AH14: 年齡下限 | AI14: 危險係數 | AK14: 年齡下限 | AL14: 主約免體檢額度 | AM14: 有附約 | AP14: =AP13+1 -> 5160113 | AQ14: =ROUND(ROUND(ROUND(ROUNDDOWN(ROUND(AP14*UNIT/UVUNIT*GP,3),2),3),0)*(1-$G$45),0) -> 3701875 | AR14: =IF(AQ14>資料輸入區!$E$15,0,AP14) -> 0
A15: 四捨五入 | B15: 2 | G15: 儲存生息 | L15: 13 | M15: 0 | X15: 年齡 | AG15: 6 | AH15: 0 | AI15: 1 | AK15: 0 | AL15: 115 | AM15: 600 | AP15: =AP14+1 -> 5160114 | AQ15: =ROUND(ROUND(ROUND(ROUNDDOWN(ROUND(AP15*UNIT/UVUNIT*GP,3),2),3),0)*(1-$G$45),0) -> 3701876 | AR15: =IF(AQ15>資料輸入區!$E$15,0,AP15) -> 0
A16: 增額繳清年度 | B16: 5 | G16: 以繳清保險方式增加保險金額 | L16: 14 | M16: 0 | X16: 保單 年度 | Y16: 1 | AG16: 6 | AH16: 16 | AI16: 1 | AK16: 41 | AL16: 115 | AM16: 500 | AP16: =AP15+1 -> 5160115 | AQ16: =ROUND(ROUND(ROUND(ROUNDDOWN(ROUND(AP16*UNIT/UVUNIT*GP,3),2),3),0)*(1-$G$45),0) -> 3701877 | AR16: =IF(AQ16>資料輸入區!$E$15,0,AP16) -> 0
A17: 生存險 | B17: FALSE | L17: 15 | M17: 0 | Y17: 2 | AG17: 6 | AH17: 31 | AI17: 1 | AK17: 46 | AL17: 115 | AM17: 500 | AP17: =AP16+1 -> 5160116 | AQ17: =ROUND(ROUND(ROUND(ROUNDDOWN(ROUND(AP17*UNIT/UVUNIT*GP,3),2),3),0)*(1-$G$45),0) -> 3701877 | AR17: =IF(AQ17>資料輸入區!$E$15,0,AP17) -> 0
A18: 三者取其大保費倍數 | B18: 1 | E18: 15歲以下危額上限 | L18: 16 | M18: 0 | Y18: 3 | AG18: 6 | AH18: 41 | AI18: 1 | AK18: 51 | AL18: 90 | AM18: 200 | AP18: =AP17+1 -> 5160117 | AQ18: =ROUND(ROUND(ROUND(ROUNDDOWN(ROUND(AP18*UNIT/UVUNIT*GP,3),2),3),0)*(1-$G$45),0) -> 3701878 | AR18: =IF(AQ18>資料輸入區!$E$15,0,AP18) -> 0
A19: 幣別 | B19: USD | C19: 分期定期給付門檻BY匯率 | F19: 10000000 | L19: 17 | M19: 0 | Y19: 4 | AG19: 6 | AH19: 51 | AI19: 1 | AK19: 56 | AL19: 90 | AM19: 100 | AP19: =AP18+1 -> 5160118 | AQ19: =ROUND(ROUND(ROUND(ROUNDDOWN(ROUND(AP19*UNIT/UVUNIT*GP,3),2),3),0)*(1-$G$45),0) -> 3701879 | AR19: =IF(AQ19>資料輸入區!$E$15,0,AP19) -> 0
A20: 核保匯率 | B20: =VLOOKUP(B19,A30:B33,2,FALSE) -> 31.5 | C20: =VLOOKUP(B19,A30:D33,3,FALSE) -> 1000 | D20: =VLOOKUP(B19,A30:D33,4,FALSE) -> 5000 | L20: 18 | M20: 0 | Y20: 5 | AG20: 6 | AH20: 61 | AI20: 1 | AK20: 61 | AL20: 75 | AM20: 0 | AP20: =AP19+1 -> 5160119 | AQ20: =ROUND(ROUND(ROUND(ROUNDDOWN(ROUND(AP20*UNIT/UVUNIT*GP,3),2),3),0)*(1-$G$45),0) -> 3701880 | AR20: =IF(AQ20>資料輸入區!$E$15,0,AP20) -> 0
A21: 保障至 | B21: 109 | C21: 歲 | I21: 適用通路 | J21: 危額係數體檢額度位置 | L21: 19 | M21: 0 | Y21: 10 | AG21: 6 | AH21: 66 | AI21: 1 | AK21: 66 | AL21: 15 | AM21: 0 | AP21: =AP20+1 -> 5160120 | AQ21: =ROUND(ROUND(ROUND(ROUNDDOWN(ROUND(AP21*UNIT/UVUNIT*GP,3),2),3),0)*(1-$G$45),0) -> 3701881 | AR21: =IF(AQ21>資料輸入區!$E$15,0,AP21) -> 0
A22: 門檻 | B22: Corridor210 | C22: =MATCH(B22,A36:E36,0) -> 4 | G22: 體檢匯率 | H22: 1 | I22: 銀保 | J22: ="AH"&MATCH(I22,AI:AI,0)&":AI"&(MATCH(I22,AI:AI,0)+11) -> AH1:AI12 | K22: ="AK"&MATCH(I22,AI:AI,0)&":AM"&(MATCH(I22,AI:AI,0)+11) -> AK1:AM12 | L22: 20 | M22: 0 | Y22: 15 | AK22: 71 | AL22: 10 | AP22: =AP21+1 -> 5160121 | AQ22: =ROUND(ROUND(ROUND(ROUNDDOWN(ROUND(AP22*UNIT/UVUNIT*GP,3),2),3),0)*(1-$G$45),0) -> 3701881 | AR22: =IF(AQ22>資料輸入區!$E$15,0,AP22) -> 0
B23: 年期數 | C23: PAY_YEAR | D23: SEX | E23: AGE | F23: 費率 | G23: 危險保額 | H23: 體檢危額 | I23: 免體檢額度 | J23: 體檢與否 | L23: 21 | M23: 0 | Y23: 20 | AP23: =AP22+1 -> 5160122 | AQ23: =ROUND(ROUND(ROUND(ROUNDDOWN(ROUND(AP23*UNIT/UVUNIT*GP,3),2),3),0)*(1-$G$45),0) -> 3701882 | AR23: =IF(AQ23>資料輸入區!$E$15,0,AP23) -> 0
B24: =COUNT(B2:B11) -> 1 | C24: =TEXT(PayYear,"00") -> 01 | D24: =TEXT(VLOOKUP(Sex,資料輸入區!B41:C42,2,FALSE),"0") -> 1 | E24: =TEXT(Age,"00") -> 71 | F24: =DGET(Premium!A:D,"GP",險種基本資料!$C$23:$E$24) -> 7714 | G24: =險種基本資料!AO3*VLOOKUP(PayYear,B2:D9,3,FALSE)*B20 -> 23321762 | H24: =VLOOKUP(E24*1,INDIRECT(J22),2)*1*SA -> 3701867 | I24: =VLOOKUP(E24*1,INDIRECT(K22),2)*10000 -> 500000 | J24: =IF(SA="-",0,IF(H24>I24,1,0)) -> 1 | K24: 主約 | L24: 22 | M24: 0 | AP24: =AP23+1 -> 5160123 | AQ24: =ROUND(ROUND(ROUND(ROUNDDOWN(ROUND(AP24*UNIT/UVUNIT*GP,3),2),3),0)*(1-$G$45),0) -> 3701883 | AR24: =IF(AQ24>資料輸入區!$E$15,0,AP24) -> 0
B25: ="A2:A"&B24+1 -> A2:A2 | I25: =VLOOKUP(E24*1,INDIRECT(K22),3)*10000 -> 0 | J25: 0 | K25: 附約 | L25: 23 | M25: 0 | X25: 8年期 | AI25: 業務 | AJ25: 面額計算額度則危險係數放1 | AP25: =AP24+1 -> 5160124 | AQ25: =ROUND(ROUND(ROUND(ROUNDDOWN(ROUND(AP25*UNIT/UVUNIT*GP,3),2),3),0)*(1-$G$45),0) -> 3701884 | AR25: =IF(AQ25>資料輸入區!$E$15,0,AP25) -> 0
J26: =SUM(J24:J25) -> 1 | K26: 主附約 | L26: 24 | M26: 0 | X26: 性別 | Z26: 男性 | AC26: 女性 | AG26: 年期 | AH26: 年齡下限 | AI26: 危險係數 | AK26: 年齡下限 | AL26: 主約免體檢額度 | AM26: 有附約 | AP26: =AP25+1 -> 5160125 | AQ26: =ROUND(ROUND(ROUND(ROUNDDOWN(ROUND(AP26*UNIT/UVUNIT*GP,3),2),3),0)*(1-$G$45),0) -> 3701884 | AR26: =IF(AQ26>資料輸入區!$E$15,0,AP26) -> 0
A27: 預定利率 | B27: 危額係數 | C27: 高保額費率折減 | D27: 投保年齡下限 | E27: 投保年齡上限 | F27: 保額下限 | G27: 保額上限 | H27: offset | I27: 是否有PVA | L27: 25 | M27: 0 | X27: 年齡 | AG27: 6 | AH27: 0 | AI27: 1 | AK27: 0 | AL27: 115 | AM27: 600 | AP27: =AP26+1 -> 5160126 | AQ27: =ROUND(ROUND(ROUND(ROUNDDOWN(ROUND(AP27*UNIT/UVUNIT*GP,3),2),3),0)*(1-$G$45),0) -> 3701885 | AR27: =IF(AQ27>資料輸入區!$E$15,0,AP27) -> 0
A28: 1.75 | B28: =VLOOKUP(PayYear,B2:J11,3,FALSE) -> 0.2 | C28: =VLOOKUP(PayYear,B2:J11,4,FALSE) -> 0.07 | D28: =VLOOKUP(PayYear,B2:J11,5,FALSE) -> 18 | E28: =VLOOKUP(PayYear,B2:J11,6,FALSE) -> 75 | F28: =VLOOKUP(PayYear,B2:J11,7,FALSE) -> 3000 | G28: =VLOOKUP(PayYear,B2:J11,8,FALSE) -> 10000000 | H28: =VLOOKUP(PayYear,B2:J11,9,FALSE) -> 0 | I28: N | L28: 26 | M28: 0 | N28: 0 | O28: 0 | X28: 保單 年度 | Y28: 1 | AG28: 6 | AH28: 16 | AI28: 1 | AK28: 41 | AL28: 115 | AM28: 500 | AP28: =AP27+1 -> 5160127 | AQ28: =ROUND(ROUND(ROUND(ROUNDDOWN(ROUND(AP28*UNIT/UVUNIT*GP,3),2),3),0)*(1-$G$45),0) -> 3701885 | AR28: =IF(AQ28>資料輸入區!$E$15,0,AP28) -> 0
L29: 27 | M29: 0 | N29: 0 | O29: 0 | Y29: 2 | AG29: 6 | AH29: 31 | AI29: 1 | AK29: 46 | AL29: 115 | AM29: 500 | AP29: =AP28+1 -> 5160128 | AQ29: =ROUND(ROUND(ROUND(ROUNDDOWN(ROUND(AP29*UNIT/UVUNIT*GP,3),2),3),0)*(1-$G$45),0) -> 3701886 | AR29: =IF(AQ29>資料輸入區!$E$15,0,AP29) -> 0
A30: NTD | B30: 1 | C30: 20000 | D30: 100000 | L30: 28 | M30: 0 | N30: 0 | O30: 0 | Y30: 3 | AG30: 6 | AH30: 41 | AI30: 1 | AK30: 51 | AL30: 90 | AM30: 200 | AP30: =AP29+1 -> 5160129 | AQ30: =ROUND(ROUND(ROUND(ROUNDDOWN(ROUND(AP30*UNIT/UVUNIT*GP,3),2),3),0)*(1-$G$45),0) -> 3701887 | AR30: =IF(AQ30>資料輸入區!$E$15,0,AP30) -> 0
A31: USD | B31: 31.5 | C31: 1000 | D31: 5000 | L31: 29 | M31: 0 | N31: 0 | O31: 0 | Y31: 4 | AG31: 6 | AH31: 51 | AI31: 1 | AK31: 56 | AL31: 90 | AM31: 100 | AP31: =AP30+1 -> 5160130 | AQ31: =ROUND(ROUND(ROUND(ROUNDDOWN(ROUND(AP31*UNIT/UVUNIT*GP,3),2),3),0)*(1-$G$45),0) -> 3701887 | AR31: =IF(AQ31>資料輸入區!$E$15,0,AP31) -> 0
A32: CNY | B32: 4.5 | L32: 30 | M32: 0 | N32: 0 | O32: 0 | Y32: 5 | AG32: 6 | AH32: 61 | AI32: 1 | AK32: 61 | AL32: 75 | AM32: 0 | AP32: =AP31+1 -> 5160131 | AQ32: =ROUND(ROUND(ROUND(ROUNDDOWN(ROUND(AP32*UNIT/UVUNIT*GP,3),2),3),0)*(1-$G$45),0) -> 3701888 | AR32: =IF(AQ32>資料輸入區!$E$15,0,AP32) -> 0
A33: AUD | B33: 21 | L33: 31 | M33: 0 | N33: 0 | O33: 0 | Y33: 10 | AG33: 6 | AH33: 66 | AI33: 1 | AK33: 66 | AL33: 15 | AM33: 0 | AP33: =AP32+1 -> 5160132 | AQ33: =ROUND(ROUND(ROUND(ROUNDDOWN(ROUND(AP33*UNIT/UVUNIT*GP,3),2),3),0)*(1-$G$45),0) -> 3701889 | AR33: =IF(AQ33>資料輸入區!$E$15,0,AP33) -> 0
L34: 32 | M34: 0 | N34: 0 | O34: 0 | Y34: 15 | AK34: 71 | AL34: 10 | AP34: =AP33+1 -> 5160133 | AQ34: =ROUND(ROUND(ROUND(ROUNDDOWN(ROUND(AP34*UNIT/UVUNIT*GP,3),2),3),0)*(1-$G$45),0) -> 3701890 | AR34: =IF(AQ34>資料輸入區!$E$15,0,AP34) -> 0
H35: 躉繳保費達高保額折扣金額 | L35: 33 | M35: 0 | N35: 0 | O35: 0 | Y35: 20 | AP35: =AP34+1 -> 5160134 | AQ35: =ROUND(ROUND(ROUND(ROUNDDOWN(ROUND(AP35*UNIT/UVUNIT*GP,3),2),3),0)*(1-$G$45),0) -> 3701890 | AR35: =IF(AQ35>資料輸入區!$E$15,0,AP35) -> 0
A36: 年齡 | B36: Corridor100 | C36: Corridor190 | D36: Corridor210 | E36: Corridor250 | G36: 保費折扣 | H36: 原始保費 | I36: 折扣後保費 | L36: 34 | M36: 0 | N36: 0 | O36: 0 | AP36: =AP35+1 -> 5160135 | AQ36: =ROUND(ROUND(ROUND(ROUNDDOWN(ROUND(AP36*UNIT/UVUNIT*GP,3),2),3),0)*(1-$G$45),0) -> 3701891 | AR36: =IF(AQ36>資料輸入區!$E$15,0,AP36) -> 0
A37: 0 | B37: 1 | C37: 1.9 | D37: 2.1 | E37: 2.5 | G37: 0.07 | H37: 1500000 | I37: =H37*(1-G37) -> 1395000 | L37: 35 | M37: 0 | N37: 0 | O37: 0 | AP37: =AP36+1 -> 5160136 | AQ37: =ROUND(ROUND(ROUND(ROUNDDOWN(ROUND(AP37*UNIT/UVUNIT*GP,3),2),3),0)*(1-$G$45),0) -> 3701892 | AR37: =IF(AQ37>資料輸入區!$E$15,0,AP37) -> 0
A38: 1 | B38: 1 | C38: 1.9 | D38: 2.1 | E38: 2.5 | G38: 0.055 | H38: 1200000 | I38: =H38*(1-G38) -> 1134000 | L38: 36 | M38: 0 | N38: 0 | O38: 0 | X38: 性別 | AP38: =AP37+1 -> 5160137 | AQ38: =ROUND(ROUND(ROUND(ROUNDDOWN(ROUND(AP38*UNIT/UVUNIT*GP,3),2),3),0)*(1-$G$45),0) -> 3701893 | AR38: =IF(AQ38>資料輸入區!$E$15,0,AP38) -> 0
A39: 2 | B39: 1 | C39: 1.9 | D39: 2.1 | E39: 2.5 | G39: 0.04 | H39: 800000 | I39: =H39*(1-G39) -> 768000 | L39: 37 | M39: 0 | N39: 0 | O39: 0 | X39: 年齡 | Z39: 0 | AA39: 35 | AB39: 65 | AC39: 0 | AD39: 35 | AE39: 65 | AP39: =AP38+1 -> 5160138 | AQ39: =ROUND(ROUND(ROUND(ROUNDDOWN(ROUND(AP39*UNIT/UVUNIT*GP,3),2),3),0)*(1-$G$45),0) -> 3701893 | AR39: =IF(AQ39>資料輸入區!$E$15,0,AP39) -> 0
A40: 3 | B40: 1 | C40: 1.9 | D40: 2.1 | E40: 2.5 | G40: 0.03 | H40: 500000 | I40: =H40*(1-G40) -> 485000 | L40: 38 | M40: 0 | N40: 0 | O40: 0 | X40: 保單 年度 | Y40: 1 | AP40: =AP39+1 -> 5160139 | AQ40: =ROUND(ROUND(ROUND(ROUNDDOWN(ROUND(AP40*UNIT/UVUNIT*GP,3),2),3),0)*(1-$G$45),0) -> 3701894 | AR40: =IF(AQ40>資料輸入區!$E$15,0,AP40) -> 0
A41: 4 | B41: 1 | C41: 1.9 | D41: 2.1 | E41: 2.5 | G41: 0.02 | H41: 200000 | I41: =H41*(1-G41) -> 196000 | L41: 39 | M41: 0 | N41: 0 | O41: 0 | Y41: 2 | AP41: =AP40+1 -> 5160140 | AQ41: =ROUND(ROUND(ROUND(ROUNDDOWN(ROUND(AP41*UNIT/UVUNIT*GP,3),2),3),0)*(1-$G$45),0) -> 3701895 | AR41: =IF(AQ41>資料輸入區!$E$15,0,AP41) -> 0
A42: 5 | B42: 1 | C42: 1.9 | D42: 2.1 | E42: 2.5 | G42: 0.01 | H42: 100000 | I42: =H42*(1-G42) -> 99000 | L42: 40 | M42: 0 | N42: 0 | O42: 0 | Y42: 3 | AP42: =AP41+1 -> 5160141 | AQ42: =ROUND(ROUND(ROUND(ROUNDDOWN(ROUND(AP42*UNIT/UVUNIT*GP,3),2),3),0)*(1-$G$45),0) -> 3701896 | AR42: =IF(AQ42>資料輸入區!$E$15,0,AP42) -> 0
A43: 6 | B43: 1 | C43: 1.9 | D43: 2.1 | E43: 2.5 | G43: 0 | H43: 0 | I43: =H43*(1-G43) -> 0 | L43: 41 | M43: 0 | N43: 0 | O43: 0 | Y43: 4 | AP43: =AP42+1 -> 5160142 | AQ43: =ROUND(ROUND(ROUND(ROUNDDOWN(ROUND(AP43*UNIT/UVUNIT*GP,3),2),3),0)*(1-$G$45),0) -> 3701897 | AR43: =IF(AQ43>資料輸入區!$E$15,0,AP43) -> 0
A44: 7 | B44: 1 | C44: 1.9 | D44: 2.1 | E44: 2.5 | I44: 折扣後保費 | L44: 42 | M44: 0 | N44: 0 | O44: 0 | Y44: 5 | AP44: =AP43+1 -> 5160143 | AQ44: =ROUND(ROUND(ROUND(ROUNDDOWN(ROUND(AP44*UNIT/UVUNIT*GP,3),2),3),0)*(1-$G$45),0) -> 3701897 | AR44: =IF(AQ44>資料輸入區!$E$15,0,AP44) -> 0
A45: 8 | B45: 1 | C45: 1.9 | D45: 2.1 | E45: 2.5 | G45: =DMAX(G36:I43,G36,I44:I45) -> 0.07 | I45: ="<="&資料輸入區!E15 -> <=3701867 | L45: 43 | M45: 0 | N45: 0 | O45: 0 | Y45: 10 | AP45: =AP44+1 -> 5160144 | AQ45: =ROUND(ROUND(ROUND(ROUNDDOWN(ROUND(AP45*UNIT/UVUNIT*GP,3),2),3),0)*(1-$G$45),0) -> 3701898 | AR45: =IF(AQ45>資料輸入區!$E$15,0,AP45) -> 0
A46: 9 | B46: 1 | C46: 1.9 | D46: 2.1 | E46: 2.5 | L46: 44 | M46: 0 | N46: 0 | O46: 0 | Y46: 15 | AP46: =AP45+1 -> 5160145 | AQ46: =ROUND(ROUND(ROUND(ROUNDDOWN(ROUND(AP46*UNIT/UVUNIT*GP,3),2),3),0)*(1-$G$45),0) -> 3701898 | AR46: =IF(AQ46>資料輸入區!$E$15,0,AP46) -> 0
A47: 10 | B47: 1 | C47: 1.9 | D47: 2.1 | E47: 2.5 | L47: 45 | M47: 0 | N47: 0 | O47: 0 | Y47: 20 | AP47: =AP46+1 -> 5160146 | AQ47: =ROUND(ROUND(ROUND(ROUNDDOWN(ROUND(AP47*UNIT/UVUNIT*GP,3),2),3),0)*(1-$G$45),0) -> 3701899 | AR47: =IF(AQ47>資料輸入區!$E$15,0,AP47) -> 0
A48: 11 | B48: 1 | C48: 1.9 | D48: 2.1 | E48: 2.5 | L48: 46 | M48: 0 | N48: 0 | O48: 0 | AP48: =AP47+1 -> 5160147 | AQ48: =ROUND(ROUND(ROUND(ROUNDDOWN(ROUND(AP48*UNIT/UVUNIT*GP,3),2),3),0)*(1-$G$45),0) -> 3701899 | AR48: =IF(AQ48>資料輸入區!$E$15,0,AP48) -> 0
A49: 12 | B49: 1 | C49: 1.9 | D49: 2.1 | E49: 2.5 | L49: 47 | M49: 0 | N49: 0 | O49: 0 | AP49: =AP48+1 -> 5160148 | AQ49: =ROUND(ROUND(ROUND(ROUNDDOWN(ROUND(AP49*UNIT/UVUNIT*GP,3),2),3),0)*(1-$G$45),0) -> 3701900 | AR49: =IF(AQ49>資料輸入區!$E$15,0,AP49) -> 0
A50: 13 | B50: 1 | C50: 1.9 | D50: 2.1 | E50: 2.5 | L50: 48 | M50: 0 | N50: 0 | O50: 0 | AP50: =AP49+1 -> 5160149 | AQ50: =ROUND(ROUND(ROUND(ROUNDDOWN(ROUND(AP50*UNIT/UVUNIT*GP,3),2),3),0)*(1-$G$45),0) -> 3701901 | AR50: =IF(AQ50>資料輸入區!$E$15,0,AP50) -> 0
A51: 14 | B51: 1 | C51: 1.9 | D51: 2.1 | E51: 2.5 | L51: 49 | M51: 0 | N51: 0 | O51: 0 | AP51: =AP50+1 -> 5160150 | AQ51: =ROUND(ROUND(ROUND(ROUNDDOWN(ROUND(AP51*UNIT/UVUNIT*GP,3),2),3),0)*(1-$G$45),0) -> 3701902 | AR51: =IF(AQ51>資料輸入區!$E$15,0,AP51) -> 0
A52: 15 | B52: 1 | C52: 1.9 | D52: 2.1 | E52: 2.5 | L52: 50 | M52: 0 | N52: 0 | O52: 0 | AP52: =AP51+1 -> 5160151 | AQ52: =ROUND(ROUND(ROUND(ROUNDDOWN(ROUND(AP52*UNIT/UVUNIT*GP,3),2),3),0)*(1-$G$45),0) -> 3701902 | AR52: =IF(AQ52>資料輸入區!$E$15,0,AP52) -> 0
A53: 16 | B53: 1 | C53: 1.9 | D53: 2.1 | E53: 2.5 | L53: 51 | M53: 0 | N53: 0 | O53: 0 | AP53: =AP52+1 -> 5160152 | AQ53: =ROUND(ROUND(ROUND(ROUNDDOWN(ROUND(AP53*UNIT/UVUNIT*GP,3),2),3),0)*(1-$G$45),0) -> 3701903 | AR53: =IF(AQ53>資料輸入區!$E$15,0,AP53) -> 0
A54: 17 | B54: 1 | C54: 1.9 | D54: 2.1 | E54: 2.5 | L54: 52 | M54: 0 | N54: 0 | O54: 0 | AP54: =AP53+1 -> 5160153 | AQ54: =ROUND(ROUND(ROUND(ROUNDDOWN(ROUND(AP54*UNIT/UVUNIT*GP,3),2),3),0)*(1-$G$45),0) -> 3701904 | AR54: =IF(AQ54>資料輸入區!$E$15,0,AP54) -> 0
A55: 18 | B55: 1 | C55: 1.9 | D55: 2.1 | E55: 2.5 | L55: 53 | M55: 0 | N55: 0 | O55: 0 | AP55: =AP54+1 -> 5160154 | AQ55: =ROUND(ROUND(ROUND(ROUNDDOWN(ROUND(AP55*UNIT/UVUNIT*GP,3),2),3),0)*(1-$G$45),0) -> 3701905 | AR55: =IF(AQ55>資料輸入區!$E$15,0,AP55) -> 0
A56: 19 | B56: 1 | C56: 1.9 | D56: 2.1 | E56: 2.5 | L56: 54 | M56: 0 | N56: 0 | O56: 0 | AP56: =AP55+1 -> 5160155 | AQ56: =ROUND(ROUND(ROUND(ROUNDDOWN(ROUND(AP56*UNIT/UVUNIT*GP,3),2),3),0)*(1-$G$45),0) -> 3701906 | AR56: =IF(AQ56>資料輸入區!$E$15,0,AP56) -> 0
A57: 20 | B57: 1 | C57: 1.9 | D57: 2.1 | E57: 2.5 | L57: 55 | M57: 0 | N57: 0 | O57: 0 | AP57: =AP56+1 -> 5160156 | AQ57: =ROUND(ROUND(ROUND(ROUNDDOWN(ROUND(AP57*UNIT/UVUNIT*GP,3),2),3),0)*(1-$G$45),0) -> 3701906 | AR57: =IF(AQ57>資料輸入區!$E$15,0,AP57) -> 0
A58: 21 | B58: 1 | C58: 1.9 | D58: 2.1 | E58: 2.5 | L58: 56 | M58: 0 | N58: 0 | O58: 0 | AP58: =AP57+1 -> 5160157 | AQ58: =ROUND(ROUND(ROUND(ROUNDDOWN(ROUND(AP58*UNIT/UVUNIT*GP,3),2),3),0)*(1-$G$45),0) -> 3701907 | AR58: =IF(AQ58>資料輸入區!$E$15,0,AP58) -> 0
A59: 22 | B59: 1 | C59: 1.9 | D59: 2.1 | E59: 2.5 | L59: 57 | M59: 0 | N59: 0 | O59: 0 | AP59: =AP58+1 -> 5160158 | AQ59: =ROUND(ROUND(ROUND(ROUNDDOWN(ROUND(AP59*UNIT/UVUNIT*GP,3),2),3),0)*(1-$G$45),0) -> 3701908 | AR59: =IF(AQ59>資料輸入區!$E$15,0,AP59) -> 0
... A113: 76 | B113: 1 | C113: 1.02 | D113: 1.05 | E113: 1.05 | L113: 111 | M113: 0 | N113: 0 | O113: 0 | AP113: =AP112+1 -> 5160212 | AQ113: =ROUND(ROUND(ROUND(ROUNDDOWN(ROUND(AP113*UNIT/UVUNIT*GP,3),2),3),0)*(1-$G$45),0) -> 3701947 | AR113: =IF(AQ113>資料輸入區!$E$15,0,AP113) -> 0
A114: 77 | B114: 1 | C114: 1.02 | D114: 1.05 | E114: 1.05 | N114: 0 | AP114: =AP113+1 -> 5160213 | AQ114: =ROUND(ROUND(ROUND(ROUNDDOWN(ROUND(AP114*UNIT/UVUNIT*GP,3),2),3),0)*(1-$G$45),0) -> 3701947 | AR114: =IF(AQ114>資料輸入區!$E$15,0,AP114) -> 0
A115: 78 | B115: 1 | C115: 1.02 | D115: 1.05 | E115: 1.05 | N115: 0 | AP115: =AP114+1 -> 5160214 | AQ115: =ROUND(ROUND(ROUND(ROUNDDOWN(ROUND(AP115*UNIT/UVUNIT*GP,3),2),3),0)*(1-$G$45),0) -> 3701948 | AR115: =IF(AQ115>資料輸入區!$E$15,0,AP115) -> 0
A116: 79 | B116: 1 | C116: 1.02 | D116: 1.05 | E116: 1.05 | N116: 0 | AP116: =AP115+1 -> 5160215 | AQ116: =ROUND(ROUND(ROUND(ROUNDDOWN(ROUND(AP116*UNIT/UVUNIT*GP,3),2),3),0)*(1-$G$45),0) -> 3701949 | AR116: =IF(AQ116>資料輸入區!$E$15,0,AP116) -> 0
A117: 80 | B117: 1 | C117: 1.02 | D117: 1.05 | E117: 1.05 | N117: 0 | AP117: =AP116+1 -> 5160216 | AQ117: =ROUND(ROUND(ROUND(ROUNDDOWN(ROUND(AP117*UNIT/UVUNIT*GP,3),2),3),0)*(1-$G$45),0) -> 3701950 | AR117: =IF(AQ117>資料輸入區!$E$15,0,AP117) -> 0
A118: 81 | B118: 1 | C118: 1.02 | D118: 1.05 | E118: 1.05 | N118: 0 | AP118: =AP117+1 -> 5160217 | AQ118: =ROUND(ROUND(ROUND(ROUNDDOWN(ROUND(AP118*UNIT/UVUNIT*GP,3),2),3),0)*(1-$G$45),0) -> 3701950 | AR118: =IF(AQ118>資料輸入區!$E$15,0,AP118) -> 0
A119: 82 | B119: 1 | C119: 1.02 | D119: 1.05 | E119: 1.05 | N119: 0 | AP119: =AP118+1 -> 5160218 | AQ119: =ROUND(ROUND(ROUND(ROUNDDOWN(ROUND(AP119*UNIT/UVUNIT*GP,3),2),3),0)*(1-$G$45),0) -> 3701951 | AR119: =IF(AQ119>資料輸入區!$E$15,0,AP119) -> 0
A120: 83 | B120: 1 | C120: 1.02 | D120: 1.05 | E120: 1.05 | N120: 0 | AP120: =AP119+1 -> 5160219 | AQ120: =ROUND(ROUND(ROUND(ROUNDDOWN(ROUND(AP120*UNIT/UVUNIT*GP,3),2),3),0)*(1-$G$45),0) -> 3701951 | AR120: =IF(AQ120>資料輸入區!$E$15,0,AP120) -> 0
A121: 84 | B121: 1 | C121: 1.02 | D121: 1.05 | E121: 1.05 | N121: 0 | AP121: =AP120+1 -> 5160220 | AQ121: =ROUND(ROUND(ROUND(ROUNDDOWN(ROUND(AP121*UNIT/UVUNIT*GP,3),2),3),0)*(1-$G$45),0) -> 3701952 | AR121: =IF(AQ121>資料輸入區!$E$15,0,AP121) -> 0
A122: 85 | B122: 1 | C122: 1.02 | D122: 1.05 | E122: 1.05 | N122: 0 | AP122: =AP121+1 -> 5160221 | AQ122: =ROUND(ROUND(ROUND(ROUNDDOWN(ROUND(AP122*UNIT/UVUNIT*GP,3),2),3),0)*(1-$G$45),0) -> 3701952 | AR122: =IF(AQ122>資料輸入區!$E$15,0,AP122) -> 0
A123: 86 | B123: 1 | C123: 1.02 | D123: 1.05 | E123: 1.05 | N123: 0 | AP123: =AP122+1 -> 5160222 | AQ123: =ROUND(ROUND(ROUND(ROUNDDOWN(ROUND(AP123*UNIT/UVUNIT*GP,3),2),3),0)*(1-$G$45),0) -> 3701953 | AR123: =IF(AQ123>資料輸入區!$E$15,0,AP123) -> 0
A124: 87 | B124: 1 | C124: 1.02 | D124: 1.05 | E124: 1.05 | N124: 0 | AP124: =AP123+1 -> 5160223 | AQ124: =ROUND(ROUND(ROUND(ROUNDDOWN(ROUND(AP124*UNIT/UVUNIT*GP,3),2),3),0)*(1-$G$45),0) -> 3701954 | AR124: =IF(AQ124>資料輸入區!$E$15,0,AP124) -> 0
A125: 88 | B125: 1 | C125: 1.02 | D125: 1.05 | E125: 1.05 | N125: 0 | AP125: =AP124+1 -> 5160224 | AQ125: =ROUND(ROUND(ROUND(ROUNDDOWN(ROUND(AP125*UNIT/UVUNIT*GP,3),2),3),0)*(1-$G$45),0) -> 3701955 | AR125: =IF(AQ125>資料輸入區!$E$15,0,AP125) -> 0
... A147: 110 | B147: 1 | C147: 1 | D147: 1 | E147: 1 | N147: 0 | AP147: =AP146+1 -> 5160246 | AQ147: =ROUND(ROUND(ROUND(ROUNDDOWN(ROUND(AP147*UNIT/UVUNIT*GP,3),2),3),0)*(1-$G$45),0) -> 3701971 | AR147: =IF(AQ147>資料輸入區!$E$15,0,AP147) -> 0
AP148: =AP147+1 -> 5160247 | AQ148: =ROUND(ROUND(ROUND(ROUNDDOWN(ROUND(AP148*UNIT/UVUNIT*GP,3),2),3),0)*(1-$G$45),0) -> 3701972 | AR148: =IF(AQ148>資料輸入區!$E$15,0,AP148) -> 0
AP149: =AP148+1 -> 5160248 | AQ149: =ROUND(ROUND(ROUND(ROUNDDOWN(ROUND(AP149*UNIT/UVUNIT*GP,3),2),3),0)*(1-$G$45),0) -> 3701972 | AR149: =IF(AQ149>資料輸入區!$E$15,0,AP149) -> 0
AP150: =AP149+1 -> 5160249 | AQ150: =ROUND(ROUND(ROUND(ROUNDDOWN(ROUND(AP150*UNIT/UVUNIT*GP,3),2),3),0)*(1-$G$45),0) -> 3701973 | AR150: =IF(AQ150>資料輸入區!$E$15,0,AP150) -> 0
AP151: =AP150+1 -> 5160250 | AQ151: =ROUND(ROUND(ROUND(ROUNDDOWN(ROUND(AP151*UNIT/UVUNIT*GP,3),2),3),0)*(1-$G$45),0) -> 3701974 | AR151: =IF(AQ151>資料輸入區!$E$15,0,AP151) -> 0
AP152: =AP151+1 -> 5160251 | AQ152: =ROUND(ROUND(ROUND(ROUNDDOWN(ROUND(AP152*UNIT/UVUNIT*GP,3),2),3),0)*(1-$G$45),0) -> 3701975 | AR152: =IF(AQ152>資料輸入區!$E$15,0,AP152) -> 0
AP153: =AP152+1 -> 5160252 | AQ153: =ROUND(ROUND(ROUND(ROUNDDOWN(ROUND(AP153*UNIT/UVUNIT*GP,3),2),3),0)*(1-$G$45),0) -> 3701975 | AR153: =IF(AQ153>資料輸入區!$E$15,0,AP153) -> 0
AP154: =AP153+1 -> 5160253 | AQ154: =ROUND(ROUND(ROUND(ROUNDDOWN(ROUND(AP154*UNIT/UVUNIT*GP,3),2),3),0)*(1-$G$45),0) -> 3701976 | AR154: =IF(AQ154>資料輸入區!$E$15,0,AP154) -> 0
AP155: =AP154+1 -> 5160254 | AQ155: =ROUND(ROUND(ROUND(ROUNDDOWN(ROUND(AP155*UNIT/UVUNIT*GP,3),2),3),0)*(1-$G$45),0) -> 3701977 | AR155: =IF(AQ155>資料輸入區!$E$15,0,AP155) -> 0
AP156: =AP155+1 -> 5160255 | AQ156: =ROUND(ROUND(ROUND(ROUNDDOWN(ROUND(AP156*UNIT/UVUNIT*GP,3),2),3),0)*(1-$G$45),0) -> 3701978 | AR156: =IF(AQ156>資料輸入區!$E$15,0,AP156) -> 0
AP157: =AP156+1 -> 5160256 | AQ157: =ROUND(ROUND(ROUND(ROUNDDOWN(ROUND(AP157*UNIT/UVUNIT*GP,3),2),3),0)*(1-$G$45),0) -> 3701978 | AR157: =IF(AQ157>資料輸入區!$E$15,0,AP157) -> 0
AP158: =AP157+1 -> 5160257 | AQ158: =ROUND(ROUND(ROUND(ROUNDDOWN(ROUND(AP158*UNIT/UVUNIT*GP,3),2),3),0)*(1-$G$45),0) -> 3701978 | AR158: =IF(AQ158>資料輸入區!$E$15,0,AP158) -> 0
AP159: =AP158+1 -> 5160258 | AQ159: =ROUND(ROUND(ROUND(ROUNDDOWN(ROUND(AP159*UNIT/UVUNIT*GP,3),2),3),0)*(1-$G$45),0) -> 3701979 | AR159: =IF(AQ159>資料輸入區!$E$15,0,AP159) -> 0
... AP366: =AP365+1 -> 5160465 | AQ366: =ROUND(ROUND(ROUND(ROUNDDOWN(ROUND(AP366*UNIT/UVUNIT*GP,3),2),3),0)*(1-$G$45),0) -> 3702128 | AR366: =IF(AQ366>資料輸入區!$E$15,0,AP366) -> 0

Sheet 明細版-試算頁
B2: =資料輸入區!B2 -> 凱基人壽美利成臻美元利率變動型終身壽險－定期給付型
Q3: 單位：美元
D4: 性 別： | F4: =Sex -> 男性 | G4: 繳費期間： | J4: =IF(PayYear=1,"躉繳",PayYear&"年期") -> 躉繳 | L4: 經費率折減後躉繳保費： | O4: =firstpay -> 2655727 | P4: =IF(資料輸入區!E13="月","※月繳件首期須繳交2個月保費。","")
C5: 保險年齡： | F5: =Age&"歲" -> 71歲 | G5: 繳費方式： | J5: =資料輸入區!E13&"繳" -> 躉繳 | L5: 續期繳交保險費(經費率折減後)： | O5: =資料輸入區!N21 -> -7583744280120
B6: 本月宣告利率(預估值)： | F6: =DecareRate -> 4.35 | G6: 投保金額： | J6: =SA -> 3701867 | L6: =IF(PayYear=1,"高保費費率折減：","首期"&IF(資料輸入區!N15>0,"高保費與","")&資料輸入區!E16&"費率折減：") -> 高保費費率折減： | O6: =資料輸入區!N18 -> 0.07
C7: 預定利率： | F7: =PDRate -> 1.75 | G7: 原始躉繳保費： | J7: =資料輸入區!N14 -> 2855620 | L7: ="續期"&IF(資料輸入區!N15>0,"高保費與","")&資料輸入區!E17&"費率折減：" -> 續期高保費與金融機構轉帳費率折減： | O7: =資料輸入區!N19 -> 2,655,727
D9: 各保單年度末 增值回饋分享金 選擇給付方式： | G9: =IF(MAX(宣告利率!AD:AD)>0,"第1保單年度"&IF(MAX(宣告利率!AD:AD)=1,"","~第"&MAX(宣告利率!AD:AD)&"保單年度"),"") | J9: =IF(G9="","",PMST) | M9: =IF(Age<16,"※ 被保險人保險年齡到達16歲之保單週年日時，其增值回饋分享金請參照保單條款。","")
G10: =IF(OR(MAX(宣告利率!AE:AE)>0,AND(MAX(宣告利率!AE:AE)>PUAYear,ZDIVOPT02=DVAC)),"第"&MAX(宣告利率!AD:AD)+1&IF(OR(MAX(宣告利率!AE:AE)<PUAYear,ZDIVOPT02<>DVAC),IF(MAX(宣告利率!AD:AD)+1=MAX(宣告利率!AE:AE),"保單年度","保單年度~第"&MAX(宣告利率!AE:AE)&"保單年度"),"保單年度起"),"") | J10: =IF(G10="","",DVAC)
G11: =IF(OR(AND(PayYear=PUAYear,Age>15),ZDIVOPT02=PUAD,MAX(宣告利率!AD:AE)<PUAYear),"第"&MAX(宣告利率!AD:AE)+1&IF(ZDIVOPT02=PUAD,"保單年度起",IF(MAX(宣告利率!AD:AE)+1=PUAYear,"保單年度","保單年度~第"&PUAYear&"保單年度")),"") -> 第1保單年度起 | J11: =IF(G11="","",PUAD) -> 以繳清保險方式增加保險金額
G12: =IF(ZDIVOPT02='明細版-試算頁'!J11,"",IF(AND('明細版-試算頁'!J11="",ZDIVOPT02='明細版-試算頁'!J10),"","第"&MAX(MAX(宣告利率!AD:AD)+1,MAX(宣告利率!AE:AE)+1,IF(ZDIVOPT02=PMST,PayYear,PUAYear+1))&"保單年度起")) | J12: =IF(G12="","",IF(ZDIVOPT02=PMST,PUAD,ZDIVOPT02))
B13: =IF(資料輸入區!H37<15,"※ 未滿15足歲之被保險人所投保之喪葬費用保險金額，不得超過遺產及贈與稅法第十七條有關遺產稅喪葬費扣除額之半數。","")
C14: 契約生效日首日預估保單價值準備金： | G14: =ROUND((宣告利率!K3+宣告利率!M3)/(1+PDRate/100)^(364/365)/VLOOKUP(資料輸入區!E13,資料輸入區!B36:C40,2,FALSE)*IF(VLOOKUP(資料輸入區!E13,資料輸入區!B36:C40,2,FALSE)=12,2,1),0) -> 2462814 | J14: 契約生效首日預估現金價值(解約金)： | M14: =ROUND((宣告利率!K3+宣告利率!L3)/(1+PDRate/100)^(364/365)/VLOOKUP(資料輸入區!E13,資料輸入區!B36:C40,2,FALSE)*IF(VLOOKUP(資料輸入區!E13,資料輸入區!B36:C40,2,FALSE)=12,2,1),0) -> 2265614
Q16: 單位：美元
B17: 保單 年度 (末) | C17: 保險 年齡 | D17: =IF(OR(Age<16,ZDIVOPT01=PMST),"累積所繳保險費(扣除抵繳保費) (A) (註2)","累積所繳保險費 (A)") -> 累積所繳保險費 (A) | E17: 基本保險金額對應之保單價值準備金 【含祝壽保險金】 | F17: 基本保險金額 對應之現金價值 【含祝壽保險金】 (B) | G17: 基本保險金額 對應之壽險保障 (身故保險金) | J17: ="假設投保後未來各保單年度宣告利率為"&TEXT(DecareRate,"0.00")&"% (下表為預估假設值)" -> 假設投保後未來各保單年度宣告利率為4.35% (下表為預估假設值) | R17: ="年度末終止契約時合計可領取之金額(含增值回饋分享金) (F)"&IF(ZDIVOPT02=CSWD,"+(D)","")&IF(ZDIVOPT02=DVAC,"+(E)","") -> 年度末終止契約時合計可領取之金額(含增值回饋分享金) (F) | S17: ="次年度期初終止契約時合計可領取之金額(含增值回饋分享金) (H)=(G)"&IF(ZDIVOPT02=CSWD,"+(D)","")&IF(ZDIVOPT02=DVAC,"+(E)","") -> 次年度期初終止契約時合計可領取之金額(含增值回饋分享金) (H)=(G) | T17: 累積 應繳保費 | U17: 期末保單價值準備金(含基本保險金額、累計增加保險金額) 【含祝壽保險金】 | V17: (E)+(F) | W17: ((E)+(F))/(A) | X17: (G)+(E) | Y17: ((G)+(E))/(A) | Z17: (I)/(A)
H18: 增值回饋分享金 | I18: 選擇以繳清保險方式增加保險金額 | M18: ="選擇"&IF(ZDIVOPT02=DVAC,DVAC,CSWD) -> 選擇現金給付 | O18: 下表數值含「基本保險金額、累計增加保險金額」
I19: 增額繳清保險金額 | J19: 累計增加 保險金額 | K19: 累計增加保險金額對應之年度末保單價值準備金 【含祝壽保險金】 | L19: 累計增加保險金額對應之現金價值 【含祝壽保險金】(C) | M19: 增值回饋 分享金 (D) | N19: =IF(ZDIVOPT02=DVAC,DVAC,"累計之增值回饋分享金")&" (E)" -> 累計之增值回饋分享金 (E) | O19: 壽險保障 (身故保險金) (I) | P19: 年度末現金價值 【含祝壽保險金】 (F)=(B)+(C) | Q19: 次年度期初 現金價值 (G)
B20: 1 | C20: =Age -> 71 | D20: =IF(B20="","",OFFSET(宣告利率!$I$2,B20,0)) -> 2655727 | E20: =IF(B20="","",OFFSET(宣告利率!$M$2,B20,0)+OFFSET(宣告利率!$K$2,B20,0)) -> 2505794 | F20: =IF(B20="","",OFFSET(宣告利率!$L$2,B20,0)+OFFSET(宣告利率!$K$2,B20,0)) -> 2305153 | G20: =IF(B20="","",OFFSET(宣告利率!$J$2,B20,0)) -> 2855620 | H20: =IF(B20="","",OFFSET(宣告利率!$G$2,B20,0)) -> 65151 | I20: =IF(B20="","",IF(C20<16,0,IF(C20=16,OFFSET(宣告利率!$O$2,B20-1,0),0)+OFFSET(宣告利率!$O$2,B20,0))) -> 96249 | J20: =IF(B20="","",IF(C20<16,0,OFFSET(宣告利率!$P$2,B20,0))) -> 96249 | K20: =IF(B20="","",IF(C20<16,OFFSET(宣告利率!$N$2,B20,0)+OFFSET(宣告利率!$U$2,B20,0),OFFSET(宣告利率!$Q$2,B20,0)+OFFSET(宣告利率!$U$2,B20,0))) -> 65151 | L20: =IF(B20="","",IF(C20<16,OFFSET(宣告利率!$N$2,B20,0),OFFSET(宣告利率!$Q$2,B20,0)+OFFSET(宣告利率!$U$2,B20,0))) -> 65151 | M20: =IF(B20="","",IF(OR(ZDIVOPT02=CSWD,ZDIVOPT02=DVAC),OFFSET(宣告利率!$R$2,B20,0),0)) -> 0 | N20: =IF(B20="","",IF(ZDIVOPT02=CSWD,OFFSET(宣告利率!$S$2,B20,0),IF(ZDIVOPT02=DVAC,OFFSET(宣告利率!$T$2,B20,0),0))) -> 0 | O20: =IF(B20="","",IF(C20<0,0,OFFSET(宣告利率!$J$2,B20,0)+MAX(OFFSET(宣告利率!$V$2,B20,0,1,3)))) -> 2855620 | P20: =IF(B20="","",F20+L20) -> 2370304 | Q20: =IF(B20="","",IF(C20=109,0,OFFSET(宣告利率!$AB$2,B20,0)+OFFSET(宣告利率!$AC$2,B20,0))) -> 2370400 | R20: =IF(B20="","",P20+IF(ZDIVOPT02=CSWD,M20,0)+IF(ZDIVOPT02=DVAC,N20,0)) -> 2370304 | S20: =IF(C20=109,0,IF(B20="","",Q20+IF(ZDIVOPT02=CSWD,M20,0)+IF(ZDIVOPT02=DVAC,N20,0))) -> 2370400 | T20: =FYPremium -> 2655727 | U20: =IF(B20="","",OFFSET(宣告利率!$Y$2,B20,0)) -> 2505793.8 | V20: =IF(B20="","",P20+N20) -> 2370304 | W20: =IF(B20="","",V20/D20) -> 0.89252547 | X20: =IF(B20="","",IF(C20=109,0,Q20+N20)) -> 2370400 | Y20: =IF(B20="","",IF(OR(B20<PayYear,C20=109),"-",X20/D20)) -> 0.89256162 | Z20: =IF(B20="","",O20/D20) -> 1.0752687 | AA20: =AND(INDIRECT("B"&ROW())>0,MOD(INDIRECT("B"&ROW()),5)=0) -> FALSE
B21: =IF(B20="","",IF(C20=險種基本資料!$B$21,"",B20+1)) -> 2 | C21: =IF(B21="","",Age+B21-1) -> 72 | D21: =IF(B21="","",OFFSET(宣告利率!$I$2,B21,0)) -> 2655727 | E21: =IF(B21="","",OFFSET(宣告利率!$M$2,B21,0)+OFFSET(宣告利率!$K$2,B21,0)) -> 2542442 | F21: =IF(B21="","",OFFSET(宣告利率!$L$2,B21,0)+OFFSET(宣告利率!$K$2,B21,0)) -> 2339210 | G21: =IF(B21="","",OFFSET(宣告利率!$J$2,B21,0)) -> 2855620 | H21: =IF(B21="","",OFFSET(宣告利率!$G$2,B21,0)) -> 67822 | I21: =IF(B21="","",IF(C21<16,0,IF(C21=16,OFFSET(宣告利率!$O$2,B21-1,0),0)+OFFSET(宣告利率!$O$2,B21,0))) -> 98751 | J21: =IF(B21="","",IF(C21<16,0,OFFSET(宣告利率!$P$2,B21,0))) -> 195000 | K21: =IF(B21="","",IF(C21<16,OFFSET(宣告利率!$N$2,B21,0)+OFFSET(宣告利率!$U$2,B21,0),OFFSET(宣告利率!$Q$2,B21,0)+OFFSET(宣告利率!$U$2,B21,0))) -> 133926 | L21: =IF(B21="","",IF(C21<16,OFFSET(宣告利率!$N$2,B21,0),OFFSET(宣告利率!$Q$2,B21,0)+OFFSET(宣告利率!$U$2,B21,0))) -> 133926 | M21: =IF(B21="","",IF(OR(ZDIVOPT02=CSWD,ZDIVOPT02=DVAC),OFFSET(宣告利率!$R$2,B21,0),0)) -> 0 | N21: =IF(B21="","",IF(ZDIVOPT02=CSWD,OFFSET(宣告利率!$S$2,B21,0),IF(ZDIVOPT02=DVAC,OFFSET(宣告利率!$T$2,B21,0),0))) -> 0 | O21: =IF(B21="","",IF(C21<0,0,OFFSET(宣告利率!$J$2,B21,0)+MAX(OFFSET(宣告利率!$V$2,B21,0,1,3)))) -> 2929866 | P21: =IF(B21="","",F21+L21) -> 2473136 | Q21: =IF(B21="","",IF(C21=109,0,OFFSET(宣告利率!$AB$2,B21,0)+OFFSET(宣告利率!$AC$2,B21,0))) -> 2650932 | R21: =IF(B21="","",P21+IF(ZDIVOPT02=CSWD,M21,0)+IF(ZDIVOPT02=DVAC,N21,0)) -> 2473136 | S21: =IF(C21=109,0,IF(B21="","",Q21+IF(ZDIVOPT02=CSWD,M21,0)+IF(ZDIVOPT02=DVAC,N21,0))) -> 2650932 | T21: =IF(B21="","",FYPremium+(MIN(PayYear,B21)-1)*CYPremium) -> 2655727 | U21: =IF(B21="","",OFFSET(宣告利率!$Y$2,B21,0)) -> 2608546.1 | V21: =IF(B21="","",P21+N21) -> 2473136 | W21: =IF(B21="","",V21/D21) -> 0.93124632 | X21: =IF(B21="","",IF(C21=109,0,Q21+N21)) -> 2650932 | Y21: =IF(B21="","",IF(OR(B21<PayYear,C21=109),"-",X21/D21)) -> 0.99819447 | Z21: =IF(B21="","",O21/D21) -> 1.1032256 | AA21: =AND(INDIRECT("B"&ROW())>0,MOD(INDIRECT("B"&ROW()),5)=0) -> FALSE
B22: =IF(B21="","",IF(C21=險種基本資料!$B$21,"",B21+1)) -> 3 | C22: =IF(B22="","",Age+B22-1) -> 73 | D22: =IF(B22="","",OFFSET(宣告利率!$I$2,B22,0)) -> 2655727 | E22: =IF(B22="","",OFFSET(宣告利率!$M$2,B22,0)+OFFSET(宣告利率!$K$2,B22,0)) -> 2579831 | F22: =IF(B22="","",OFFSET(宣告利率!$L$2,B22,0)+OFFSET(宣告利率!$K$2,B22,0)) -> 2553918 | G22: =IF(B22="","",OFFSET(宣告利率!$J$2,B22,0)) -> 2855620 | H22: =IF(B22="","",OFFSET(宣告利率!$G$2,B22,0)) -> 70609 | I22: =IF(B22="","",IF(C22<16,0,IF(C22=16,OFFSET(宣告利率!$O$2,B22-1,0),0)+OFFSET(宣告利率!$O$2,B22,0))) -> 101319 | J22: =IF(B22="","",IF(C22<16,0,OFFSET(宣告利率!$P$2,B22,0))) -> 296319 | K22: =IF(B22="","",IF(C22<16,OFFSET(宣告利率!$N$2,B22,0)+OFFSET(宣告利率!$U$2,B22,0),OFFSET(宣告利率!$Q$2,B22,0)+OFFSET(宣告利率!$U$2,B22,0))) -> 206505 | L22: =IF(B22="","",IF(C22<16,OFFSET(宣告利率!$N$2,B22,0),OFFSET(宣告利率!$Q$2,B22,0)+OFFSET(宣告利率!$U$2,B22,0))) -> 206505 | M22: =IF(B22="","",IF(OR(ZDIVOPT02=CSWD,ZDIVOPT02=DVAC),OFFSET(宣告利率!$R$2,B22,0),0)) -> 0 | N22: =IF(B22="","",IF(ZDIVOPT02=CSWD,OFFSET(宣告利率!$S$2,B22,0),IF(ZDIVOPT02=DVAC,OFFSET(宣告利率!$T$2,B22,0),0))) -> 0 | O22: =IF(B22="","",IF(C22<0,0,OFFSET(宣告利率!$J$2,B22,0)+MAX(OFFSET(宣告利率!$V$2,B22,0,1,3)))) -> 3006043 | P22: =IF(B22="","",F22+L22) -> 2760423 | Q22: =IF(B22="","",IF(C22=109,0,OFFSET(宣告利率!$AB$2,B22,0)+OFFSET(宣告利率!$AC$2,B22,0))) -> 2760534 | R22: =IF(B22="","",P22+IF(ZDIVOPT02=CSWD,M22,0)+IF(ZDIVOPT02=DVAC,N22,0)) -> 2760423 | S22: =IF(C22=109,0,IF(B22="","",Q22+IF(ZDIVOPT02=CSWD,M22,0)+IF(ZDIVOPT02=DVAC,N22,0))) -> 2760534 | T22: =IF(B22="","",FYPremium+(MIN(PayYear,B22)-1)*CYPremium) -> 2655727 | U22: =IF(B22="","",OFFSET(宣告利率!$Y$2,B22,0)) -> 2715726.6 | V22: =IF(B22="","",P22+N22) -> 2760423 | W22: =IF(B22="","",V22/D22) -> 1.0394227 | X22: =IF(B22="","",IF(C22=109,0,Q22+N22)) -> 2760534 | Y22: =IF(B22="","",IF(OR(B22<PayYear,C22=109),"-",X22/D22)) -> 1.0394645 | Z22: =IF(B22="","",O22/D22) -> 1.1319096 | AA22: =AND(INDIRECT("B"&ROW())>0,MOD(INDIRECT("B"&ROW()),5)=0) -> FALSE
B23: =IF(B22="","",IF(C22=險種基本資料!$B$21,"",B22+1)) -> 4 | C23: =IF(B23="","",Age+B23-1) -> 74 | D23: =IF(B23="","",OFFSET(宣告利率!$I$2,B23,0)) -> 2655727 | E23: =IF(B23="","",OFFSET(宣告利率!$M$2,B23,0)+OFFSET(宣告利率!$K$2,B23,0)) -> 2617960 | F23: =IF(B23="","",OFFSET(宣告利率!$L$2,B23,0)+OFFSET(宣告利率!$K$2,B23,0)) -> 2591677 | G23: =IF(B23="","",OFFSET(宣告利率!$J$2,B23,0)) -> 2855620 | H23: =IF(B23="","",OFFSET(宣告利率!$G$2,B23,0)) -> 73515 | I23: =IF(B23="","",IF(C23<16,0,IF(C23=16,OFFSET(宣告利率!$O$2,B23-1,0),0)+OFFSET(宣告利率!$O$2,B23,0))) -> 103952 | J23: =IF(B23="","",IF(C23<16,0,OFFSET(宣告利率!$P$2,B23,0))) -> 400271 | K23: =IF(B23="","",IF(C23<16,OFFSET(宣告利率!$N$2,B23,0)+OFFSET(宣告利率!$U$2,B23,0),OFFSET(宣告利率!$Q$2,B23,0)+OFFSET(宣告利率!$U$2,B23,0))) -> 283072 | L23: =IF(B23="","",IF(C23<16,OFFSET(宣告利率!$N$2,B23,0),OFFSET(宣告利率!$Q$2,B23,0)+OFFSET(宣告利率!$U$2,B23,0))) -> 283072 | M23: =IF(B23="","",IF(OR(ZDIVOPT02=CSWD,ZDIVOPT02=DVAC),OFFSET(宣告利率!$R$2,B23,0),0)) -> 0 | N23: =IF(B23="","",IF(ZDIVOPT02=CSWD,OFFSET(宣告利率!$S$2,B23,0),IF(ZDIVOPT02=DVAC,OFFSET(宣告利率!$T$2,B23,0),0))) -> 0 | O23: =IF(B23="","",IF(C23<0,0,OFFSET(宣告利率!$J$2,B23,0)+MAX(OFFSET(宣告利率!$V$2,B23,0,1,3)))) -> 3084200 | P23: =IF(B23="","",F23+L23) -> 2874749 | Q23: =IF(B23="","",IF(C23=109,0,OFFSET(宣告利率!$AB$2,B23,0)+OFFSET(宣告利率!$AC$2,B23,0))) -> 2874793 | R23: =IF(B23="","",P23+IF(ZDIVOPT02=CSWD,M23,0)+IF(ZDIVOPT02=DVAC,N23,0)) -> 2874749 | S23: =IF(C23=109,0,IF(B23="","",Q23+IF(ZDIVOPT02=CSWD,M23,0)+IF(ZDIVOPT02=DVAC,N23,0))) -> 2874793 | T23: =IF(B23="","",FYPremium+(MIN(PayYear,B23)-1)*CYPremium) -> 2655727 | U23: =IF(B23="","",OFFSET(宣告利率!$Y$2,B23,0)) -> 2827517.1 | V23: =IF(B23="","",P23+N23) -> 2874749 | W23: =IF(B23="","",V23/D23) -> 1.0824716 | X23: =IF(B23="","",IF(C23=109,0,Q23+N23)) -> 2874793 | Y23: =IF(B23="","",IF(OR(B23<PayYear,C23=109),"-",X23/D23)) -> 1.0824881 | Z23: =IF(B23="","",O23/D23) -> 1.1613392 | AA23: =AND(INDIRECT("B"&ROW())>0,MOD(INDIRECT("B"&ROW()),5)=0) -> FALSE
B24: =IF(B23="","",IF(C23=險種基本資料!$B$21,"",B23+1)) -> 5 | C24: =IF(B24="","",Age+B24-1) -> 75 | D24: =IF(B24="","",OFFSET(宣告利率!$I$2,B24,0)) -> 2655727 | E24: =IF(B24="","",OFFSET(宣告利率!$M$2,B24,0)+OFFSET(宣告利率!$K$2,B24,0)) -> 2632398 | F24: =IF(B24="","",OFFSET(宣告利率!$L$2,B24,0)+OFFSET(宣告利率!$K$2,B24,0)) -> 2606114 | G24: =IF(B24="","",OFFSET(宣告利率!$J$2,B24,0)) -> 3701867 | H24: =IF(B24="","",OFFSET(宣告利率!$G$2,B24,0)) -> 75843 | I24: =IF(B24="","",IF(C24<16,0,IF(C24=16,OFFSET(宣告利率!$O$2,B24-1,0),0)+OFFSET(宣告利率!$O$2,B24,0))) -> 106656 | J24: =IF(B24="","",IF(C24<16,0,OFFSET(宣告利率!$P$2,B24,0))) -> 506927 | K24: =IF(B24="","",IF(C24<16,OFFSET(宣告利率!$N$2,B24,0)+OFFSET(宣告利率!$U$2,B24,0),OFFSET(宣告利率!$Q$2,B24,0)+OFFSET(宣告利率!$U$2,B24,0))) -> 360476 | L24: =IF(B24="","",IF(C24<16,OFFSET(宣告利率!$N$2,B24,0),OFFSET(宣告利率!$Q$2,B24,0)+OFFSET(宣告利率!$U$2,B24,0))) -> 360476 | M24: =IF(B24="","",IF(OR(ZDIVOPT02=CSWD,ZDIVOPT02=DVAC),OFFSET(宣告利率!$R$2,B24,0),0)) -> 0 | N24: =IF(B24="","",IF(ZDIVOPT02=CSWD,OFFSET(宣告利率!$S$2,B24,0),IF(ZDIVOPT02=DVAC,OFFSET(宣告利率!$T$2,B24,0),0))) -> 0 | O24: =IF(B24="","",IF(C24<0,0,OFFSET(宣告利率!$J$2,B24,0)+MAX(OFFSET(宣告利率!$V$2,B24,0,1,3)))) -> 4102138 | P24: =IF(B24="","",F24+L24) -> 2966590 | Q24: =IF(B24="","",IF(C24=109,0,OFFSET(宣告利率!$AB$2,B24,0)+OFFSET(宣告利率!$AC$2,B24,0))) -> 2966628 | R24: =IF(B24="","",P24+IF(ZDIVOPT02=CSWD,M24,0)+IF(ZDIVOPT02=DVAC,N24,0)) -> 2966590 | S24: =IF(C24=109,0,IF(B24="","",Q24+IF(ZDIVOPT02=CSWD,M24,0)+IF(ZDIVOPT02=DVAC,N24,0))) -> 2966628 | T24: =IF(B24="","",FYPremium+(MIN(PayYear,B24)-1)*CYPremium) -> 2655727 | U24: =IF(B24="","",OFFSET(宣告利率!$Y$2,B24,0)) -> 2917030.3 | V24: =IF(B24="","",P24+N24) -> 2966590 | W24: =IF(B24="","",V24/D24) -> 1.1170538 | X24: =IF(B24="","",IF(C24=109,0,Q24+N24)) -> 2966628 | Y24: =IF(B24="","",IF(OR(B24<PayYear,C24=109),"-",X24/D24)) -> 1.1170681 | Z24: =IF(B24="","",O24/D24) -> 1.5446384 | AA24: =AND(INDIRECT("B"&ROW())>0,MOD(INDIRECT("B"&ROW()),5)=0) -> TRUE
B25: =IF(B24="","",IF(C24=險種基本資料!$B$21,"",B24+1)) -> 6 | C25: =IF(B25="","",Age+B25-1) -> 76 | D25: =IF(B25="","",OFFSET(宣告利率!$I$2,B25,0)) -> 2655727 | E25: =IF(B25="","",OFFSET(宣告利率!$M$2,B25,0)+OFFSET(宣告利率!$K$2,B25,0)) -> 2644614 | F25: =IF(B25="","",OFFSET(宣告利率!$L$2,B25,0)+OFFSET(宣告利率!$K$2,B25,0)) -> 2618331 | G25: =IF(B25="","",OFFSET(宣告利率!$J$2,B25,0)) -> 3701867 | H25: =IF(B25="","",OFFSET(宣告利率!$G$2,B25,0)) -> 78176 | I25: =IF(B25="","",IF(C25<16,0,IF(C25=16,OFFSET(宣告利率!$O$2,B25-1,0),0)+OFFSET(宣告利率!$O$2,B25,0))) -> 109429 | J25: =IF(B25="","",IF(C25<16,0,OFFSET(宣告利率!$P$2,B25,0))) -> 616356 | K25: =IF(B25="","",IF(C25<16,OFFSET(宣告利率!$N$2,B25,0)+OFFSET(宣告利率!$U$2,B25,0),OFFSET(宣告利率!$Q$2,B25,0)+OFFSET(宣告利率!$U$2,B25,0))) -> 440325 | L25: =IF(B25="","",IF(C25<16,OFFSET(宣告利率!$N$2,B25,0),OFFSET(宣告利率!$Q$2,B25,0)+OFFSET(宣告利率!$U$2,B25,0))) -> 440325 | M25: =IF(B25="","",IF(OR(ZDIVOPT02=CSWD,ZDIVOPT02=DVAC),OFFSET(宣告利率!$R$2,B25,0),0)) -> 0 | N25: =IF(B25="","",IF(ZDIVOPT02=CSWD,OFFSET(宣告利率!$S$2,B25,0),IF(ZDIVOPT02=DVAC,OFFSET(宣告利率!$T$2,B25,0),0))) -> 0 | O25: =IF(B25="","",IF(C25<0,0,OFFSET(宣告利率!$J$2,B25,0)+MAX(OFFSET(宣告利率!$V$2,B25,0,1,3)))) -> 4208794 | P25: =IF(B25="","",F25+L25) -> 3058656 | Q25: =IF(B25="","",IF(C25=109,0,OFFSET(宣告利率!$AB$2,B25,0)+OFFSET(宣告利率!$AC$2,B25,0))) -> 3084969 | R25: =IF(B25="","",P25+IF(ZDIVOPT02=CSWD,M25,0)+IF(ZDIVOPT02=DVAC,N25,0)) -> 3058656 | S25: =IF(C25=109,0,IF(B25="","",Q25+IF(ZDIVOPT02=CSWD,M25,0)+IF(ZDIVOPT02=DVAC,N25,0))) -> 3084969 | T25: =IF(B25="","",FYPremium+(MIN(PayYear,B25)-1)*CYPremium) -> 2655727 | U25: =IF(B25="","",OFFSET(宣告利率!$Y$2,B25,0)) -> 3006762.4 | V25: =IF(B25="","",P25+N25) -> 3058656 | W25: =IF(B25="","",V25/D25) -> 1.1517208 | X25: =IF(B25="","",IF(C25=109,0,Q25+N25)) -> 3084969 | Y25: =IF(B25="","",IF(OR(B25<PayYear,C25=109),"-",X25/D25)) -> 1.1616288 | Z25: =IF(B25="","",O25/D25) -> 1.5847992 | AA25: =AND(INDIRECT("B"&ROW())>0,MOD(INDIRECT("B"&ROW()),5)=0) -> FALSE
B26: =IF(B25="","",IF(C25=險種基本資料!$B$21,"",B25+1)) -> 7 | C26: =IF(B26="","",Age+B26-1) -> 77 | D26: =IF(B26="","",OFFSET(宣告利率!$I$2,B26,0)) -> 2655727 | E26: =IF(B26="","",OFFSET(宣告利率!$M$2,B26,0)+OFFSET(宣告利率!$K$2,B26,0)) -> 2654239 | F26: =IF(B26="","",OFFSET(宣告利率!$L$2,B26,0)+OFFSET(宣告利率!$K$2,B26,0)) -> 2654239 | G26: =IF(B26="","",OFFSET(宣告利率!$J$2,B26,0)) -> 3701867 | H26: =IF(B26="","",OFFSET(宣告利率!$G$2,B26,0)) -> 80500 | I26: =IF(B26="","",IF(C26<16,0,IF(C26=16,OFFSET(宣告利率!$O$2,B26-1,0),0)+OFFSET(宣告利率!$O$2,B26,0))) -> 112273 | J26: =IF(B26="","",IF(C26<16,0,OFFSET(宣告利率!$P$2,B26,0))) -> 728629 | K26: =IF(B26="","",IF(C26<16,OFFSET(宣告利率!$N$2,B26,0)+OFFSET(宣告利率!$U$2,B26,0),OFFSET(宣告利率!$Q$2,B26,0)+OFFSET(宣告利率!$U$2,B26,0))) -> 522427 | L26: =IF(B26="","",IF(C26<16,OFFSET(宣告利率!$N$2,B26,0),OFFSET(宣告利率!$Q$2,B26,0)+OFFSET(宣告利率!$U$2,B26,0))) -> 522427 | M26: =IF(B26="","",IF(OR(ZDIVOPT02=CSWD,ZDIVOPT02=DVAC),OFFSET(宣告利率!$R$2,B26,0),0)) -> 0 | N26: =IF(B26="","",IF(ZDIVOPT02=CSWD,OFFSET(宣告利率!$S$2,B26,0),IF(ZDIVOPT02=DVAC,OFFSET(宣告利率!$T$2,B26,0),0))) -> 0 | O26: =IF(B26="","",IF(C26<0,0,OFFSET(宣告利率!$J$2,B26,0)+MAX(OFFSET(宣告利率!$V$2,B26,0,1,3)))) -> 4318223 | P26: =IF(B26="","",F26+L26) -> 3176666 | Q26: =IF(B26="","",IF(C26=109,0,OFFSET(宣告利率!$AB$2,B26,0)+OFFSET(宣告利率!$AC$2,B26,0))) -> 3176686 | R26: =IF(B26="","",P26+IF(ZDIVOPT02=CSWD,M26,0)+IF(ZDIVOPT02=DVAC,N26,0)) -> 3176666 | S26: =IF(C26=109,0,IF(B26="","",Q26+IF(ZDIVOPT02=CSWD,M26,0)+IF(ZDIVOPT02=DVAC,N26,0))) -> 3176686 | T26: =IF(B26="","",FYPremium+(MIN(PayYear,B26)-1)*CYPremium) -> 2655727 | U26: =IF(B26="","",OFFSET(宣告利率!$Y$2,B26,0)) -> 3096165.9 | V26: =IF(B26="","",P26+N26) -> 3176666 | W26: =IF(B26="","",V26/D26) -> 1.1961568 | X26: =IF(B26="","",IF(C26=109,0,Q26+N26)) -> 3176686 | Y26: =IF(B26="","",IF(OR(B26<PayYear,C26=109),"-",X26/D26)) -> 1.1961644 | Z26: =IF(B26="","",O26/D26) -> 1.6260041 | AA26: =AND(INDIRECT("B"&ROW())>0,MOD(INDIRECT("B"&ROW()),5)=0) -> FALSE
B27: =IF(B26="","",IF(C26=險種基本資料!$B$21,"",B26+1)) -> 8 | C27: =IF(B27="","",Age+B27-1) -> 78 | D27: =IF(B27="","",OFFSET(宣告利率!$I$2,B27,0)) -> 2655727 | E27: =IF(B27="","",OFFSET(宣告利率!$M$2,B27,0)+OFFSET(宣告利率!$K$2,B27,0)) -> 2660532 | F27: =IF(B27="","",OFFSET(宣告利率!$L$2,B27,0)+OFFSET(宣告利率!$K$2,B27,0)) -> 2660532 | G27: =IF(B27="","",OFFSET(宣告利率!$J$2,B27,0)) -> 3701867 | H27: =IF(B27="","",OFFSET(宣告利率!$G$2,B27,0)) -> 82789 | I27: =IF(B27="","",IF(C27<16,0,IF(C27=16,OFFSET(宣告利率!$O$2,B27-1,0),0)+OFFSET(宣告利率!$O$2,B27,0))) -> 115193 | J27: =IF(B27="","",IF(C27<16,0,OFFSET(宣告利率!$P$2,B27,0))) -> 843822 | K27: =IF(B27="","",IF(C27<16,OFFSET(宣告利率!$N$2,B27,0)+OFFSET(宣告利率!$U$2,B27,0),OFFSET(宣告利率!$Q$2,B27,0)+OFFSET(宣告利率!$U$2,B27,0))) -> 606455 | L27: =IF(B27="","",IF(C27<16,OFFSET(宣告利率!$N$2,B27,0),OFFSET(宣告利率!$Q$2,B27,0)+OFFSET(宣告利率!$U$2,B27,0))) -> 606455 | M27: =IF(B27="","",IF(OR(ZDIVOPT02=CSWD,ZDIVOPT02=DVAC),OFFSET(宣告利率!$R$2,B27,0),0)) -> 0 | N27: =IF(B27="","",IF(ZDIVOPT02=CSWD,OFFSET(宣告利率!$S$2,B27,0),IF(ZDIVOPT02=DVAC,OFFSET(宣告利率!$T$2,B27,0),0))) -> 0 | O27: =IF(B27="","",IF(C27<0,0,OFFSET(宣告利率!$J$2,B27,0)+MAX(OFFSET(宣告利率!$V$2,B27,0,1,3)))) -> 4430496 | P27: =IF(B27="","",F27+L27) -> 3266987 | Q27: =IF(B27="","",IF(C27=109,0,OFFSET(宣告利率!$AB$2,B27,0)+OFFSET(宣告利率!$AC$2,B27,0))) -> 3266995 | R27: =IF(B27="","",P27+IF(ZDIVOPT02=CSWD,M27,0)+IF(ZDIVOPT02=DVAC,N27,0)) -> 3266987 | S27: =IF(C27=109,0,IF(B27="","",Q27+IF(ZDIVOPT02=CSWD,M27,0)+IF(ZDIVOPT02=DVAC,N27,0))) -> 3266995 | T27: =IF(B27="","",FYPremium+(MIN(PayYear,B27)-1)*CYPremium) -> 2655727 | U27: =IF(B27="","",OFFSET(宣告利率!$Y$2,B27,0)) -> 3184197.5 | V27: =IF(B27="","",P27+N27) -> 3266987 | W27: =IF(B27="","",V27/D27) -> 1.2301667 | X27: =IF(B27="","",IF(C27=109,0,Q27+N27)) -> 3266995 | Y27: =IF(B27="","",IF(OR(B27<PayYear,C27=109),"-",X27/D27)) -> 1.2301697 | Z27: =IF(B27="","",O27/D27) -> 1.6682799 | AA27: =AND(INDIRECT("B"&ROW())>0,MOD(INDIRECT("B"&ROW()),5)=0) -> FALSE
B28: =IF(B27="","",IF(C27=險種基本資料!$B$21,"",B27+1)) -> 9 | C28: =IF(B28="","",Age+B28-1) -> 79 | D28: =IF(B28="","",OFFSET(宣告利率!$I$2,B28,0)) -> 2655727 | E28: =IF(B28="","",OFFSET(宣告利率!$M$2,B28,0)+OFFSET(宣告利率!$K$2,B28,0)) -> 2663123 | F28: =IF(B28="","",OFFSET(宣告利率!$L$2,B28,0)+OFFSET(宣告利率!$K$2,B28,0)) -> 2663123 | G28: =IF(B28="","",OFFSET(宣告利率!$J$2,B28,0)) -> 3701867 | H28: =IF(B28="","",OFFSET(宣告利率!$G$2,B28,0)) -> 85024 | I28: =IF(B28="","",IF(C28<16,0,IF(C28=16,OFFSET(宣告利率!$O$2,B28-1,0),0)+OFFSET(宣告利率!$O$2,B28,0))) -> 118187 | J28: =IF(B28="","",IF(C28<16,0,OFFSET(宣告利率!$P$2,B28,0))) -> 962009 | K28: =IF(B28="","",IF(C28<16,OFFSET(宣告利率!$N$2,B28,0)+OFFSET(宣告利率!$U$2,B28,0),OFFSET(宣告利率!$Q$2,B28,0)+OFFSET(宣告利率!$U$2,B28,0))) -> 692069 | L28: =IF(B28="","",IF(C28<16,OFFSET(宣告利率!$N$2,B28,0),OFFSET(宣告利率!$Q$2,B28,0)+OFFSET(宣告利率!$U$2,B28,0))) -> 692069 | M28: =IF(B28="","",IF(OR(ZDIVOPT02=CSWD,ZDIVOPT02=DVAC),OFFSET(宣告利率!$R$2,B28,0),0)) -> 0 | N28: =IF(B28="","",IF(ZDIVOPT02=CSWD,OFFSET(宣告利率!$S$2,B28,0),IF(ZDIVOPT02=DVAC,OFFSET(宣告利率!$T$2,B28,0),0))) -> 0 | O28: =IF(B28="","",IF(C28<0,0,OFFSET(宣告利率!$J$2,B28,0)+MAX(OFFSET(宣告利率!$V$2,B28,0,1,3)))) -> 4545689 | P28: =IF(B28="","",F28+L28) -> 3355192 | Q28: =IF(B28="","",IF(C28=109,0,OFFSET(宣告利率!$AB$2,B28,0)+OFFSET(宣告利率!$AC$2,B28,0))) -> 3355187 | R28: =IF(B28="","",P28+IF(ZDIVOPT02=CSWD,M28,0)+IF(ZDIVOPT02=DVAC,N28,0)) -> 3355192 | S28: =IF(C28=109,0,IF(B28="","",Q28+IF(ZDIVOPT02=CSWD,M28,0)+IF(ZDIVOPT02=DVAC,N28,0))) -> 3355187 | T28: =IF(B28="","",FYPremium+(MIN(PayYear,B28)-1)*CYPremium) -> 2655727 | U28: =IF(B28="","",OFFSET(宣告利率!$Y$2,B28,0)) -> 3270168.7 | V28: =IF(B28="","",P28+N28) -> 3355192 | W28: =IF(B28="","",V28/D28) -> 1.2633799 | X28: =IF(B28="","",IF(C28=109,0,Q28+N28)) -> 3355187 | Y28: =IF(B28="","",IF(OR(B28<PayYear,C28=109),"-",X28/D28)) -> 1.263378 | Z28: =IF(B28="","",O28/D28) -> 1.7116552 | AA28: =AND(INDIRECT("B"&ROW())>0,MOD(INDIRECT("B"&ROW()),5)=0) -> FALSE
B29: =IF(B28="","",IF(C28=險種基本資料!$B$21,"",B28+1)) -> 10 | C29: =IF(B29="","",Age+B29-1) -> 80 | D29: =IF(B29="","",OFFSET(宣告利率!$I$2,B29,0)) -> 2655727 | E29: =IF(B29="","",OFFSET(宣告利率!$M$2,B29,0)+OFFSET(宣告利率!$K$2,B29,0)) -> 2661642 | F29: =IF(B29="","",OFFSET(宣告利率!$L$2,B29,0)+OFFSET(宣告利率!$K$2,B29,0)) -> 2661642 | G29: =IF(B29="","",OFFSET(宣告利率!$J$2,B29,0)) -> 3701867 | H29: =IF(B29="","",OFFSET(宣告利率!$G$2,B29,0)) -> 87186 | I29: =IF(B29="","",IF(C29<16,0,IF(C29=16,OFFSET(宣告利率!$O$2,B29-1,0),0)+OFFSET(宣告利率!$O$2,B29,0))) -> 121260 | J29: =IF(B29="","",IF(C29<16,0,OFFSET(宣告利率!$P$2,B29,0))) -> 1083269 | K29: =IF(B29="","",IF(C29<16,OFFSET(宣告利率!$N$2,B29,0)+OFFSET(宣告利率!$U$2,B29,0),OFFSET(宣告利率!$Q$2,B29,0)+OFFSET(宣告利率!$U$2,B29,0))) -> 778870 | L29: =IF(B29="","",IF(C29<16,OFFSET(宣告利率!$N$2,B29,0),OFFSET(宣告利率!$Q$2,B29,0)+OFFSET(宣告利率!$U$2,B29,0))) -> 778870 | M29: =IF(B29="","",IF(OR(ZDIVOPT02=CSWD,ZDIVOPT02=DVAC),OFFSET(宣告利率!$R$2,B29,0),0)) -> 0 | N29: =IF(B29="","",IF(ZDIVOPT02=CSWD,OFFSET(宣告利率!$S$2,B29,0),IF(ZDIVOPT02=DVAC,OFFSET(宣告利率!$T$2,B29,0),0))) -> 0 | O29: =IF(B29="","",IF(C29<0,0,OFFSET(宣告利率!$J$2,B29,0)+MAX(OFFSET(宣告利率!$V$2,B29,0,1,3)))) -> 4663876 | P29: =IF(B29="","",F29+L29) -> 3440512 | Q29: =IF(B29="","",IF(C29=109,0,OFFSET(宣告利率!$AB$2,B29,0)+OFFSET(宣告利率!$AC$2,B29,0))) -> 3440505 | R29: =IF(B29="","",P29+IF(ZDIVOPT02=CSWD,M29,0)+IF(ZDIVOPT02=DVAC,N29,0)) -> 3440512 | S29: =IF(C29=109,0,IF(B29="","",Q29+IF(ZDIVOPT02=CSWD,M29,0)+IF(ZDIVOPT02=DVAC,N29,0))) -> 3440505 | T29: =IF(B29="","",FYPremium+(MIN(PayYear,B29)-1)*CYPremium) -> 2655727 | U29: =IF(B29="","",OFFSET(宣告利率!$Y$2,B29,0)) -> 3353326.8 | V29: =IF(B29="","",P29+N29) -> 3440512 | W29: =IF(B29="","",V29/D29) -> 1.2955067 | X29: =IF(B29="","",IF(C29=109,0,Q29+N29)) -> 3440505 | Y29: =IF(B29="","",IF(OR(B29<PayYear,C29=109),"-",X29/D29)) -> 1.295504 | Z29: =IF(B29="","",O29/D29) -> 1.7561579 | AA29: =AND(INDIRECT("B"&ROW())>0,MOD(INDIRECT("B"&ROW()),5)=0) -> TRUE
B30: =IF(B29="","",IF(C29=險種基本資料!$B$21,"",B29+1)) -> 11 | C30: =IF(B30="","",Age+B30-1) -> 81 | D30: =IF(B30="","",OFFSET(宣告利率!$I$2,B30,0)) -> 2655727 | E30: =IF(B30="","",OFFSET(宣告利率!$M$2,B30,0)+OFFSET(宣告利率!$K$2,B30,0)) -> 2659421 | F30: =IF(B30="","",OFFSET(宣告利率!$L$2,B30,0)+OFFSET(宣告利率!$K$2,B30,0)) -> 2659421 | G30: =IF(B30="","",OFFSET(宣告利率!$J$2,B30,0)) -> 3627830 | H30: =IF(B30="","",OFFSET(宣告利率!$G$2,B30,0)) -> 89379 | I30: =IF(B30="","",IF(C30<16,0,IF(C30=16,OFFSET(宣告利率!$O$2,B30-1,0),0)+OFFSET(宣告利率!$O$2,B30,0))) -> 124414 | J30: =IF(B30="","",IF(C30<16,0,OFFSET(宣告利率!$P$2,B30,0))) -> 1207683 | K30: =IF(B30="","",IF(C30<16,OFFSET(宣告利率!$N$2,B30,0)+OFFSET(宣告利率!$U$2,B30,0),OFFSET(宣告利率!$Q$2,B30,0)+OFFSET(宣告利率!$U$2,B30,0))) -> 867599 | L30: =IF(B30="","",IF(C30<16,OFFSET(宣告利率!$N$2,B30,0),OFFSET(宣告利率!$Q$2,B30,0)+OFFSET(宣告利率!$U$2,B30,0))) -> 867599 | M30: =IF(B30="","",IF(OR(ZDIVOPT02=CSWD,ZDIVOPT02=DVAC),OFFSET(宣告利率!$R$2,B30,0),0)) -> 0 | N30: =IF(B30="","",IF(ZDIVOPT02=CSWD,OFFSET(宣告利率!$S$2,B30,0),IF(ZDIVOPT02=DVAC,OFFSET(宣告利率!$T$2,B30,0),0))) -> 0 | O30: =IF(B30="","",IF(C30<0,0,OFFSET(宣告利率!$J$2,B30,0)+MAX(OFFSET(宣告利率!$V$2,B30,0,1,3)))) -> 4689434 | P30: =IF(B30="","",F30+L30) -> 3527020 | Q30: =IF(B30="","",IF(C30=109,0,OFFSET(宣告利率!$AB$2,B30,0)+OFFSET(宣告利率!$AC$2,B30,0))) -> 3527008 | R30: =IF(B30="","",P30+IF(ZDIVOPT02=CSWD,M30,0)+IF(ZDIVOPT02=DVAC,N30,0)) -> 3527020 | S30: =IF(C30=109,0,IF(B30="","",Q30+IF(ZDIVOPT02=CSWD,M30,0)+IF(ZDIVOPT02=DVAC,N30,0))) -> 3527008 | T30: =IF(B30="","",FYPremium+(MIN(PayYear,B30)-1)*CYPremium) -> 2655727 | U30: =IF(B30="","",OFFSET(宣告利率!$Y$2,B30,0)) -> 3437641.7 | V30: =IF(B30="","",P30+N30) -> 3527020 | W30: =IF(B30="","",V30/D30) -> 1.3280808 | X30: =IF(B30="","",IF(C30=109,0,Q30+N30)) -> 3527008 | Y30: =IF(B30="","",IF(OR(B30<PayYear,C30=109),"-",X30/D30)) -> 1.3280763 | Z30: =IF(B30="","",O30/D30) -> 1.7657816 | AA30: =AND(INDIRECT("B"&ROW())>0,MOD(INDIRECT("B"&ROW()),5)=0) -> FALSE
B31: =IF(B30="","",IF(C30=險種基本資料!$B$21,"",B30+1)) -> 12 | C31: =IF(B31="","",Age+B31-1) -> 82 | D31: =IF(B31="","",OFFSET(宣告利率!$I$2,B31,0)) -> 2655727 | E31: =IF(B31="","",OFFSET(宣告利率!$M$2,B31,0)+OFFSET(宣告利率!$K$2,B31,0)) -> 2656090 | F31: =IF(B31="","",OFFSET(宣告利率!$L$2,B31,0)+OFFSET(宣告利率!$K$2,B31,0)) -> 2656090 | G31: =IF(B31="","",OFFSET(宣告利率!$J$2,B31,0)) -> 3555273 | H31: =IF(B31="","",OFFSET(宣告利率!$G$2,B31,0)) -> 91588 | I31: =IF(B31="","",IF(C31<16,0,IF(C31=16,OFFSET(宣告利率!$O$2,B31-1,0),0)+OFFSET(宣告利率!$O$2,B31,0))) -> 127649 | J31: =IF(B31="","",IF(C31<16,0,OFFSET(宣告利率!$P$2,B31,0))) -> 1335332 | K31: =IF(B31="","",IF(C31<16,OFFSET(宣告利率!$N$2,B31,0)+OFFSET(宣告利率!$U$2,B31,0),OFFSET(宣告利率!$Q$2,B31,0)+OFFSET(宣告利率!$U$2,B31,0))) -> 958101 | L31: =IF(B31="","",IF(C31<16,OFFSET(宣告利率!$N$2,B31,0),OFFSET(宣告利率!$Q$2,B31,0)+OFFSET(宣告利率!$U$2,B31,0))) -> 958101 | M31: =IF(B31="","",IF(OR(ZDIVOPT02=CSWD,ZDIVOPT02=DVAC),OFFSET(宣告利率!$R$2,B31,0),0)) -> 0 | N31: =IF(B31="","",IF(ZDIVOPT02=CSWD,OFFSET(宣告利率!$S$2,B31,0),IF(ZDIVOPT02=DVAC,OFFSET(宣告利率!$T$2,B31,0),0))) -> 0 | O31: =IF(B31="","",IF(C31<0,0,OFFSET(宣告利率!$J$2,B31,0)+MAX(OFFSET(宣告利率!$V$2,B31,0,1,3)))) -> 4715132 | P31: =IF(B31="","",F31+L31) -> 3614191 | Q31: =IF(B31="","",IF(C31=109,0,OFFSET(宣告利率!$AB$2,B31,0)+OFFSET(宣告利率!$AC$2,B31,0))) -> 3614175 | R31: =IF(B31="","",P31+IF(ZDIVOPT02=CSWD,M31,0)+IF(ZDIVOPT02=DVAC,N31,0)) -> 3614191 | S31: =IF(C31=109,0,IF(B31="","",Q31+IF(ZDIVOPT02=CSWD,M31,0)+IF(ZDIVOPT02=DVAC,N31,0))) -> 3614175 | T31: =IF(B31="","",FYPremium+(MIN(PayYear,B31)-1)*CYPremium) -> 2655727 | U31: =IF(B31="","",OFFSET(宣告利率!$Y$2,B31,0)) -> 3522602.1 | V31: =IF(B31="","",P31+N31) -> 3614191 | W31: =IF(B31="","",V31/D31) -> 1.3609046 | X31: =IF(B31="","",IF(C31=109,0,Q31+N31)) -> 3614175 | Y31: =IF(B31="","",IF(OR(B31<PayYear,C31=109),"-",X31/D31)) -> 1.3608985 | Z31: =IF(B31="","",O31/D31) -> 1.7754581 | AA31: =AND(INDIRECT("B"&ROW())>0,MOD(INDIRECT("B"&ROW()),5)=0) -> FALSE
B32: =IF(B31="","",IF(C31=險種基本資料!$B$21,"",B31+1)) -> 13 | C32: =IF(B32="","",Age+B32-1) -> 83 | D32: =IF(B32="","",OFFSET(宣告利率!$I$2,B32,0)) -> 2655727 | E32: =IF(B32="","",OFFSET(宣告利率!$M$2,B32,0)+OFFSET(宣告利率!$K$2,B32,0)) -> 2652018 | F32: =IF(B32="","",OFFSET(宣告利率!$L$2,B32,0)+OFFSET(宣告利率!$K$2,B32,0)) -> 2652018 | G32: =IF(B32="","",OFFSET(宣告利率!$J$2,B32,0)) -> 3484197 | H32: =IF(B32="","",OFFSET(宣告利率!$G$2,B32,0)) -> 93825 | I32: =IF(B32="","",IF(C32<16,0,IF(C32=16,OFFSET(宣告利率!$O$2,B32-1,0),0)+OFFSET(宣告利率!$O$2,B32,0))) -> 130967 | J32: =IF(B32="","",IF(C32<16,0,OFFSET(宣告利率!$P$2,B32,0))) -> 1466299 | K32: =IF(B32="","",IF(C32<16,OFFSET(宣告利率!$N$2,B32,0)+OFFSET(宣告利率!$U$2,B32,0),OFFSET(宣告利率!$Q$2,B32,0)+OFFSET(宣告利率!$U$2,B32,0))) -> 1050457 | L32: =IF(B32="","",IF(C32<16,OFFSET(宣告利率!$N$2,B32,0),OFFSET(宣告利率!$Q$2,B32,0)+OFFSET(宣告利率!$U$2,B32,0))) -> 1050457 | M32: =IF(B32="","",IF(OR(ZDIVOPT02=CSWD,ZDIVOPT02=DVAC),OFFSET(宣告利率!$R$2,B32,0),0)) -> 0 | N32: =IF(B32="","",IF(ZDIVOPT02=CSWD,OFFSET(宣告利率!$S$2,B32,0),IF(ZDIVOPT02=DVAC,OFFSET(宣告利率!$T$2,B32,0),0))) -> 0 | O32: =IF(B32="","",IF(C32<0,0,OFFSET(宣告利率!$J$2,B32,0)+MAX(OFFSET(宣告利率!$V$2,B32,0,1,3)))) -> 4741011 | P32: =IF(B32="","",F32+L32) -> 3702475 | Q32: =IF(B32="","",IF(C32=109,0,OFFSET(宣告利率!$AB$2,B32,0)+OFFSET(宣告利率!$AC$2,B32,0))) -> 3702457 | R32: =IF(B32="","",P32+IF(ZDIVOPT02=CSWD,M32,0)+IF(ZDIVOPT02=DVAC,N32,0)) -> 3702475 | S32: =IF(C32=109,0,IF(B32="","",Q32+IF(ZDIVOPT02=CSWD,M32,0)+IF(ZDIVOPT02=DVAC,N32,0))) -> 3702457 | T32: =IF(B32="","",FYPremium+(MIN(PayYear,B32)-1)*CYPremium) -> 2655727 | U32: =IF(B32="","",OFFSET(宣告利率!$Y$2,B32,0)) -> 3608649.4 | V32: =IF(B32="","",P32+N32) -> 3702475 | W32: =IF(B32="","",V32/D32) -> 1.3941474 | X32: =IF(B32="","",IF(C32=109,0,Q32+N32)) -> 3702457 | Y32: =IF(B32="","",IF(OR(B32<PayYear,C32=109),"-",X32/D32)) -> 1.3941407 | Z32: =IF(B32="","",O32/D32) -> 1.7852027 | AA32: =AND(INDIRECT("B"&ROW())>0,MOD(INDIRECT("B"&ROW()),5)=0) -> FALSE
... B34: =IF(B33="","",IF(C33=險種基本資料!$B$21,"",B33+1)) -> 15 | C34: =IF(B34="","",Age+B34-1) -> 85 | D34: =IF(B34="","",OFFSET(宣告利率!$I$2,B34,0)) -> 2655727 | E34: =IF(B34="","",OFFSET(宣告利率!$M$2,B34,0)+OFFSET(宣告利率!$K$2,B34,0)) -> 2642763 | F34: =IF(B34="","",OFFSET(宣告利率!$L$2,B34,0)+OFFSET(宣告利率!$K$2,B34,0)) -> 2642763 | G34: =IF(B34="","",OFFSET(宣告利率!$J$2,B34,0)) -> 3346488 | H34: =IF(B34="","",OFFSET(宣告利率!$G$2,B34,0)) -> 98423 | I34: =IF(B34="","",IF(C34<16,0,IF(C34=16,OFFSET(宣告利率!$O$2,B34-1,0),0)+OFFSET(宣告利率!$O$2,B34,0))) -> 137867 | J34: =IF(B34="","",IF(C34<16,0,OFFSET(宣告利率!$P$2,B34,0))) -> 1738538 | K34: =IF(B34="","",IF(C34<16,OFFSET(宣告利率!$N$2,B34,0)+OFFSET(宣告利率!$U$2,B34,0),OFFSET(宣告利率!$Q$2,B34,0)+OFFSET(宣告利率!$U$2,B34,0))) -> 1241142 | L34: =IF(B34="","",IF(C34<16,OFFSET(宣告利率!$N$2,B34,0),OFFSET(宣告利率!$Q$2,B34,0)+OFFSET(宣告利率!$U$2,B34,0))) -> 1241142 | M34: =IF(B34="","",IF(OR(ZDIVOPT02=CSWD,ZDIVOPT02=DVAC),OFFSET(宣告利率!$R$2,B34,0),0)) -> 0 | N34: =IF(B34="","",IF(ZDIVOPT02=CSWD,OFFSET(宣告利率!$S$2,B34,0),IF(ZDIVOPT02=DVAC,OFFSET(宣告利率!$T$2,B34,0),0))) -> 0 | O34: =IF(B34="","",IF(C34<0,0,OFFSET(宣告利率!$J$2,B34,0)+MAX(OFFSET(宣告利率!$V$2,B34,0,1,3)))) -> 4793495 | P34: =IF(B34="","",F34+L34) -> 3883905 | Q34: =IF(B34="","",IF(C34=109,0,OFFSET(宣告利率!$AB$2,B34,0)+OFFSET(宣告利率!$AC$2,B34,0))) -> 3883886 | R34: =IF(B34="","",P34+IF(ZDIVOPT02=CSWD,M34,0)+IF(ZDIVOPT02=DVAC,N34,0)) -> 3883905 | S34: =IF(C34=109,0,IF(B34="","",Q34+IF(ZDIVOPT02=CSWD,M34,0)+IF(ZDIVOPT02=DVAC,N34,0))) -> 3883886 | T34: =IF(B34="","",FYPremium+(MIN(PayYear,B34)-1)*CYPremium) -> 2655727 | U34: =IF(B34="","",OFFSET(宣告利率!$Y$2,B34,0)) -> 3785481.9 | V34: =IF(B34="","",P34+N34) -> 3883905 | W34: =IF(B34="","",V34/D34) -> 1.462464 | X34: =IF(B34="","",IF(C34=109,0,Q34+N34)) -> 3883886 | Y34: =IF(B34="","",IF(OR(B34<PayYear,C34=109),"-",X34/D34)) -> 1.4624568 | Z34: =IF(B34="","",O34/D34) -> 1.8049653 | AA34: =AND(INDIRECT("B"&ROW())>0,MOD(INDIRECT("B"&ROW()),5)=0) -> TRUE
B35: =B17 -> 保單 年度 (末) | C35: =C17 -> 保險 年齡 | D35: =D17 -> 累積所繳保險費 (A) | E35: =E17 -> 基本保險金額對應之保單價值準備金 【含祝壽保險金】 | F35: =F17 -> 基本保險金額 對應之現金價值 【含祝壽保險金】 (B) | G35: =G17 -> 基本保險金額 對應之壽險保障 (身故保險金) | J35: =J17 -> 假設投保後未來各保單年度宣告利率為4.35% (下表為預估假設值) | R35: =R17 -> 年度末終止契約時合計可領取之金額(含增值回饋分享金) (F) | S35: =S17 -> 次年度期初終止契約時合計可領取之金額(含增值回饋分享金) (H)=(G) | T35: =T17 -> 累積 應繳保費 | U35: =U17 -> 期末保單價值準備金(含基本保險金額、累計增加保險金額) 【含祝壽保險金】 | V35: =V17 -> (E)+(F) | W35: =W17 -> ((E)+(F))/(A) | X35: =X17 -> (G)+(E) | Y35: =Y17 -> ((G)+(E))/(A) | Z35: =Z17 -> (I)/(A) | AA35: =AND(INDIRECT("B"&ROW())>0,MOD(INDIRECT("B"&ROW()),5)=0) -> #VALUE!
C36: =C18 -> 0 | D36: =D18 -> 0 | E36: =E18 -> 0 | F36: =F18 -> 0 | G36: =G18 -> 0 | H36: =H18 -> 增值回饋分享金 | I36: =I18 -> 選擇以繳清保險方式增加保險金額 | J36: =J18 -> 0 | ... Q36: =Q18 -> 0 | T36: =T18 -> 0 | U36: =U18 -> 0 | V36: =V18 -> 0 | W36: =W18 -> 0 | X36: =X18 -> 0 | Y36: =Y18 -> 0 | AA36: =AND(INDIRECT("B"&ROW())>0,MOD(INDIRECT("B"&ROW()),5)=0) -> FALSE
C37: =C19 -> 0 | D37: =D19 -> 0 | E37: =E19 -> 0 | F37: =F19 -> 0 | G37: =G19 -> 0 | H37: =H19 -> 0 | I37: =I19 -> 增額繳清保險金額 | J37: =J19 -> 累計增加 保險金額 | ... Q37: =Q19 -> 次年度期初 現金價值 (G) | T37: =T19 -> 0 | U37: =U19 -> 0 | V37: =V19 -> 0 | W37: =W19 -> 0 | X37: =X19 -> 0 | Y37: =Y19 -> 0 | AA37: =AND(INDIRECT("B"&ROW())>0,MOD(INDIRECT("B"&ROW()),5)=0) -> FALSE
B38: =IF(B34="","",IF(C34=險種基本資料!$B$21,"",B34+1)) -> 16 | C38: =IF(B38="","",Age+B38-1) -> 86 | D38: =IF(B38="","",OFFSET(宣告利率!$I$2,B38,0)) -> 2655727 | E38: =IF(B38="","",OFFSET(宣告利率!$M$2,B38,0)+OFFSET(宣告利率!$K$2,B38,0)) -> 2637950 | F38: =IF(B38="","",OFFSET(宣告利率!$L$2,B38,0)+OFFSET(宣告利率!$K$2,B38,0)) -> 2637950 | G38: =IF(B38="","",OFFSET(宣告利率!$J$2,B38,0)) -> 3279484 | H38: =IF(B38="","",OFFSET(宣告利率!$G$2,B38,0)) -> 100798 | I38: =IF(B38="","",IF(C38<16,0,IF(C38=16,OFFSET(宣告利率!$O$2,B38-1,0),0)+OFFSET(宣告利率!$O$2,B38,0))) -> 141451 | J38: =IF(B38="","",IF(C38<16,0,OFFSET(宣告利率!$P$2,B38,0))) -> 1879989 | K38: =IF(B38="","",IF(C38<16,OFFSET(宣告利率!$N$2,B38,0)+OFFSET(宣告利率!$U$2,B38,0),OFFSET(宣告利率!$Q$2,B38,0)+OFFSET(宣告利率!$U$2,B38,0))) -> 1339680 | L38: =IF(B38="","",IF(C38<16,OFFSET(宣告利率!$N$2,B38,0),OFFSET(宣告利率!$Q$2,B38,0)+OFFSET(宣告利率!$U$2,B38,0))) -> 1339680 | M38: =IF(B38="","",IF(OR(ZDIVOPT02=CSWD,ZDIVOPT02=DVAC),OFFSET(宣告利率!$R$2,B38,0),0)) -> 0 | N38: =IF(B38="","",IF(ZDIVOPT02=CSWD,OFFSET(宣告利率!$S$2,B38,0),IF(ZDIVOPT02=DVAC,OFFSET(宣告利率!$T$2,B38,0),0))) -> 0 | O38: =IF(B38="","",IF(C38<0,0,OFFSET(宣告利率!$J$2,B38,0)+MAX(OFFSET(宣告利率!$V$2,B38,0,1,3)))) -> 4819655 | P38: =IF(B38="","",F38+L38) -> 3977630 | Q38: =IF(B38="","",IF(C38=109,0,OFFSET(宣告利率!$AB$2,B38,0)+OFFSET(宣告利率!$AC$2,B38,0))) -> 3977610 | R38: =IF(B38="","",P38+IF(ZDIVOPT02=CSWD,M38,0)+IF(ZDIVOPT02=DVAC,N38,0)) -> 3977630 | S38: =IF(C38=109,0,IF(B38="","",Q38+IF(ZDIVOPT02=CSWD,M38,0)+IF(ZDIVOPT02=DVAC,N38,0))) -> 3977610 | T38: =IF(B38="","",FYPremium+(MIN(PayYear,B38)-1)*CYPremium) -> 2655727 | U38: =IF(B38="","",OFFSET(宣告利率!$Y$2,B38,0)) -> 3876832.6 | V38: =IF(B38="","",P38+N38) -> 3977630 | W38: =IF(B38="","",V38/D38) -> 1.4977556 | X38: =IF(B38="","",IF(C38=109,0,Q38+N38)) -> 3977610 | Y38: =IF(B38="","",IF(OR(B38<PayYear,C38=109),"-",X38/D38)) -> 1.4977481 | Z38: =IF(B38="","",O38/D38) -> 1.8148157 | AA38: =AND(INDIRECT("B"&ROW())>0,MOD(INDIRECT("B"&ROW()),5)=0) -> FALSE
B39: =IF(B38="","",IF(C38=險種基本資料!$B$21,"",B38+1)) -> 17 | C39: =IF(B39="","",Age+B39-1) -> 87 | D39: =IF(B39="","",OFFSET(宣告利率!$I$2,B39,0)) -> 2655727 | E39: =IF(B39="","",OFFSET(宣告利率!$M$2,B39,0)+OFFSET(宣告利率!$K$2,B39,0)) -> 2633138 | F39: =IF(B39="","",OFFSET(宣告利率!$L$2,B39,0)+OFFSET(宣告利率!$K$2,B39,0)) -> 2633138 | G39: =IF(B39="","",OFFSET(宣告利率!$J$2,B39,0)) -> 3213961 | H39: =IF(B39="","",OFFSET(宣告利率!$G$2,B39,0)) -> 103230 | I39: =IF(B39="","",IF(C39<16,0,IF(C39=16,OFFSET(宣告利率!$O$2,B39-1,0),0)+OFFSET(宣告利率!$O$2,B39,0))) -> 145129 | J39: =IF(B39="","",IF(C39<16,0,OFFSET(宣告利率!$P$2,B39,0))) -> 2025118 | K39: =IF(B39="","",IF(C39<16,OFFSET(宣告利率!$N$2,B39,0)+OFFSET(宣告利率!$U$2,B39,0),OFFSET(宣告利率!$Q$2,B39,0)+OFFSET(宣告利率!$U$2,B39,0))) -> 1440466 | L39: =IF(B39="","",IF(C39<16,OFFSET(宣告利率!$N$2,B39,0),OFFSET(宣告利率!$Q$2,B39,0)+OFFSET(宣告利率!$U$2,B39,0))) -> 1440466 | M39: =IF(B39="","",IF(OR(ZDIVOPT02=CSWD,ZDIVOPT02=DVAC),OFFSET(宣告利率!$R$2,B39,0),0)) -> 0 | N39: =IF(B39="","",IF(ZDIVOPT02=CSWD,OFFSET(宣告利率!$S$2,B39,0),IF(ZDIVOPT02=DVAC,OFFSET(宣告利率!$T$2,B39,0),0))) -> 0 | O39: =IF(B39="","",IF(C39<0,0,OFFSET(宣告利率!$J$2,B39,0)+MAX(OFFSET(宣告利率!$V$2,B39,0,1,3)))) -> 4846167 | P39: =IF(B39="","",F39+L39) -> 4073604 | Q39: =IF(B39="","",IF(C39=109,0,OFFSET(宣告利率!$AB$2,B39,0)+OFFSET(宣告利率!$AC$2,B39,0))) -> 4073589 | R39: =IF(B39="","",P39+IF(ZDIVOPT02=CSWD,M39,0)+IF(ZDIVOPT02=DVAC,N39,0)) -> 4073604 | S39: =IF(C39=109,0,IF(B39="","",Q39+IF(ZDIVOPT02=CSWD,M39,0)+IF(ZDIVOPT02=DVAC,N39,0))) -> 4073589 | T39: =IF(B39="","",FYPremium+(MIN(PayYear,B39)-1)*CYPremium) -> 2655727 | U39: =IF(B39="","",OFFSET(宣告利率!$Y$2,B39,0)) -> 3970374.2 | V39: =IF(B39="","",P39+N39) -> 4073604 | W39: =IF(B39="","",V39/D39) -> 1.5338941 | X39: =IF(B39="","",IF(C39=109,0,Q39+N39)) -> 4073589 | Y39: =IF(B39="","",IF(OR(B39<PayYear,C39=109),"-",X39/D39)) -> 1.5338885 | Z39: =IF(B39="","",O39/D39) -> 1.8247986 | AA39: =AND(INDIRECT("B"&ROW())>0,MOD(INDIRECT("B"&ROW()),5)=0) -> FALSE
B40: =IF(B39="","",IF(C39=險種基本資料!$B$21,"",B39+1)) -> 18 | C40: =IF(B40="","",Age+B40-1) -> 88 | D40: =IF(B40="","",OFFSET(宣告利率!$I$2,B40,0)) -> 2655727 | E40: =IF(B40="","",OFFSET(宣告利率!$M$2,B40,0)+OFFSET(宣告利率!$K$2,B40,0)) -> 2629436 | F40: =IF(B40="","",OFFSET(宣告利率!$L$2,B40,0)+OFFSET(宣告利率!$K$2,B40,0)) -> 2629436 | G40: =IF(B40="","",OFFSET(宣告利率!$J$2,B40,0)) -> 3149548 | H40: =IF(B40="","",OFFSET(宣告利率!$G$2,B40,0)) -> 105765 | I40: =IF(B40="","",IF(C40<16,0,IF(C40=16,OFFSET(宣告利率!$O$2,B40-1,0),0)+OFFSET(宣告利率!$O$2,B40,0))) -> 148902 | J40: =IF(B40="","",IF(C40<16,0,OFFSET(宣告利率!$P$2,B40,0))) -> 2174020 | K40: =IF(B40="","",IF(C40<16,OFFSET(宣告利率!$N$2,B40,0)+OFFSET(宣告利率!$U$2,B40,0),OFFSET(宣告利率!$Q$2,B40,0)+OFFSET(宣告利率!$U$2,B40,0))) -> 1544206 | L40: =IF(B40="","",IF(C40<16,OFFSET(宣告利率!$N$2,B40,0),OFFSET(宣告利率!$Q$2,B40,0)+OFFSET(宣告利率!$U$2,B40,0))) -> 1544206 | M40: =IF(B40="","",IF(OR(ZDIVOPT02=CSWD,ZDIVOPT02=DVAC),OFFSET(宣告利率!$R$2,B40,0),0)) -> 0 | N40: =IF(B40="","",IF(ZDIVOPT02=CSWD,OFFSET(宣告利率!$S$2,B40,0),IF(ZDIVOPT02=DVAC,OFFSET(宣告利率!$T$2,B40,0),0))) -> 0 | O40: =IF(B40="","",IF(C40<0,0,OFFSET(宣告利率!$J$2,B40,0)+MAX(OFFSET(宣告利率!$V$2,B40,0,1,3)))) -> 4872518 | P40: =IF(B40="","",F40+L40) -> 4173642 | Q40: =IF(B40="","",IF(C40=109,0,OFFSET(宣告利率!$AB$2,B40,0)+OFFSET(宣告利率!$AC$2,B40,0))) -> 4173633 | R40: =IF(B40="","",P40+IF(ZDIVOPT02=CSWD,M40,0)+IF(ZDIVOPT02=DVAC,N40,0)) -> 4173642 | S40: =IF(C40=109,0,IF(B40="","",Q40+IF(ZDIVOPT02=CSWD,M40,0)+IF(ZDIVOPT02=DVAC,N40,0))) -> 4173633 | T40: =IF(B40="","",FYPremium+(MIN(PayYear,B40)-1)*CYPremium) -> 2655727 | U40: =IF(B40="","",OFFSET(宣告利率!$Y$2,B40,0)) -> 4067877.5 | V40: =IF(B40="","",P40+N40) -> 4173642 | W40: =IF(B40="","",V40/D40) -> 1.5715629 | X40: =IF(B40="","",IF(C40=109,0,Q40+N40)) -> 4173633 | Y40: =IF(B40="","",IF(OR(B40<PayYear,C40=109),"-",X40/D40)) -> 1.5715595 | Z40: =IF(B40="","",O40/D40) -> 1.834721 | AA40: =AND(INDIRECT("B"&ROW())>0,MOD(INDIRECT("B"&ROW()),5)=0) -> FALSE
B41: =IF(B40="","",IF(C40=險種基本資料!$B$21,"",B40+1)) -> 19 | C41: =IF(B41="","",Age+B41-1) -> 89 | D41: =IF(B41="","",OFFSET(宣告利率!$I$2,B41,0)) -> 2655727 | E41: =IF(B41="","",OFFSET(宣告利率!$M$2,B41,0)+OFFSET(宣告利率!$K$2,B41,0)) -> 2627215 | F41: =IF(B41="","",OFFSET(宣告利率!$L$2,B41,0)+OFFSET(宣告利率!$K$2,B41,0)) -> 2627215 | G41: =IF(B41="","",OFFSET(宣告利率!$J$2,B41,0)) -> 3086617 | H41: =IF(B41="","",OFFSET(宣告利率!$G$2,B41,0)) -> 108423 | I41: =IF(B41="","",IF(C41<16,0,IF(C41=16,OFFSET(宣告利率!$O$2,B41-1,0),0)+OFFSET(宣告利率!$O$2,B41,0))) -> 152773 | J41: =IF(B41="","",IF(C41<16,0,OFFSET(宣告利率!$P$2,B41,0))) -> 2326793 | K41: =IF(B41="","",IF(C41<16,OFFSET(宣告利率!$N$2,B41,0)+OFFSET(宣告利率!$U$2,B41,0),OFFSET(宣告利率!$Q$2,B41,0)+OFFSET(宣告利率!$U$2,B41,0))) -> 1651325 | L41: =IF(B41="","",IF(C41<16,OFFSET(宣告利率!$N$2,B41,0),OFFSET(宣告利率!$Q$2,B41,0)+OFFSET(宣告利率!$U$2,B41,0))) -> 1651325 | M41: =IF(B41="","",IF(OR(ZDIVOPT02=CSWD,ZDIVOPT02=DVAC),OFFSET(宣告利率!$R$2,B41,0),0)) -> 0 | N41: =IF(B41="","",IF(ZDIVOPT02=CSWD,OFFSET(宣告利率!$S$2,B41,0),IF(ZDIVOPT02=DVAC,OFFSET(宣告利率!$T$2,B41,0),0))) -> 0 | O41: =IF(B41="","",IF(C41<0,0,OFFSET(宣告利率!$J$2,B41,0)+MAX(OFFSET(宣告利率!$V$2,B41,0,1,3)))) -> 4899315 | P41: =IF(B41="","",F41+L41) -> 4278540 | Q41: =IF(B41="","",IF(C41=109,0,OFFSET(宣告利率!$AB$2,B41,0)+OFFSET(宣告利率!$AC$2,B41,0))) -> 4278540 | R41: =IF(B41="","",P41+IF(ZDIVOPT02=CSWD,M41,0)+IF(ZDIVOPT02=DVAC,N41,0)) -> 4278540 | S41: =IF(C41=109,0,IF(B41="","",Q41+IF(ZDIVOPT02=CSWD,M41,0)+IF(ZDIVOPT02=DVAC,N41,0))) -> 4278540 | T41: =IF(B41="","",FYPremium+(MIN(PayYear,B41)-1)*CYPremium) -> 2655727 | U41: =IF(B41="","",OFFSET(宣告利率!$Y$2,B41,0)) -> 4170117 | V41: =IF(B41="","",P41+N41) -> 4278540 | W41: =IF(B41="","",V41/D41) -> 1.6110617 | X41: =IF(B41="","",IF(C41=109,0,Q41+N41)) -> 4278540 | Y41: =IF(B41="","",IF(OR(B41<PayYear,C41=109),"-",X41/D41)) -> 1.6110617 | Z41: =IF(B41="","",O41/D41) -> 1.8448112 | AA41: =AND(INDIRECT("B"&ROW())>0,MOD(INDIRECT("B"&ROW()),5)=0) -> FALSE
B42: =IF(B41="","",IF(C41=險種基本資料!$B$21,"",B41+1)) -> 20 | C42: =IF(B42="","",Age+B42-1) -> 90 | D42: =IF(B42="","",OFFSET(宣告利率!$I$2,B42,0)) -> 2655727 | E42: =IF(B42="","",OFFSET(宣告利率!$M$2,B42,0)+OFFSET(宣告利率!$K$2,B42,0)) -> 2627215 | F42: =IF(B42="","",OFFSET(宣告利率!$L$2,B42,0)+OFFSET(宣告利率!$K$2,B42,0)) -> 2627215 | G42: =IF(B42="","",OFFSET(宣告利率!$J$2,B42,0)) -> 3024796 | H42: =IF(B42="","",OFFSET(宣告利率!$G$2,B42,0)) -> 111242 | I42: =IF(B42="","",IF(C42<16,0,IF(C42=16,OFFSET(宣告利率!$O$2,B42-1,0),0)+OFFSET(宣告利率!$O$2,B42,0))) -> 156745 | J42: =IF(B42="","",IF(C42<16,0,OFFSET(宣告利率!$P$2,B42,0))) -> 2483538 | K42: =IF(B42="","",IF(C42<16,OFFSET(宣告利率!$N$2,B42,0)+OFFSET(宣告利率!$U$2,B42,0),OFFSET(宣告利率!$Q$2,B42,0)+OFFSET(宣告利率!$U$2,B42,0))) -> 1762567 | L42: =IF(B42="","",IF(C42<16,OFFSET(宣告利率!$N$2,B42,0),OFFSET(宣告利率!$Q$2,B42,0)+OFFSET(宣告利率!$U$2,B42,0))) -> 1762567 | M42: =IF(B42="","",IF(OR(ZDIVOPT02=CSWD,ZDIVOPT02=DVAC),OFFSET(宣告利率!$R$2,B42,0),0)) -> 0 | N42: =IF(B42="","",IF(ZDIVOPT02=CSWD,OFFSET(宣告利率!$S$2,B42,0),IF(ZDIVOPT02=DVAC,OFFSET(宣告利率!$T$2,B42,0),0))) -> 0 | O42: =IF(B42="","",IF(C42<0,0,OFFSET(宣告利率!$J$2,B42,0)+MAX(OFFSET(宣告利率!$V$2,B42,0,1,3)))) -> 4926019 | P42: =IF(B42="","",F42+L42) -> 4389782 | Q42: =IF(B42="","",IF(C42=109,0,OFFSET(宣告利率!$AB$2,B42,0)+OFFSET(宣告利率!$AC$2,B42,0))) -> 4389795 | R42: =IF(B42="","",P42+IF(ZDIVOPT02=CSWD,M42,0)+IF(ZDIVOPT02=DVAC,N42,0)) -> 4389782 | S42: =IF(C42=109,0,IF(B42="","",Q42+IF(ZDIVOPT02=CSWD,M42,0)+IF(ZDIVOPT02=DVAC,N42,0))) -> 4389795 | T42: =IF(B42="","",FYPremium+(MIN(PayYear,B42)-1)*CYPremium) -> 2655727 | U42: =IF(B42="","",OFFSET(宣告利率!$Y$2,B42,0)) -> 4278540 | V42: =IF(B42="","",P42+N42) -> 4389782 | W42: =IF(B42="","",V42/D42) -> 1.6529493 | X42: =IF(B42="","",IF(C42=109,0,Q42+N42)) -> 4389795 | Y42: =IF(B42="","",IF(OR(B42<PayYear,C42=109),"-",X42/D42)) -> 1.6529542 | Z42: =IF(B42="","",O42/D42) -> 1.8548665 | AA42: =AND(INDIRECT("B"&ROW())>0,MOD(INDIRECT("B"&ROW()),5)=0) -> TRUE
B43: =IF(B42="","",IF(C42=險種基本資料!$B$21,"",B42+1)) -> 21 | C43: =IF(B43="","",Age+B43-1) -> 91 | D43: =IF(B43="","",OFFSET(宣告利率!$I$2,B43,0)) -> 2655727 | E43: =IF(B43="","",OFFSET(宣告利率!$M$2,B43,0)+OFFSET(宣告利率!$K$2,B43,0)) -> 2630177 | F43: =IF(B43="","",OFFSET(宣告利率!$L$2,B43,0)+OFFSET(宣告利率!$K$2,B43,0)) -> 2630177 | G43: =IF(B43="","",OFFSET(宣告利率!$J$2,B43,0)) -> 2964455 | H43: =IF(B43="","",OFFSET(宣告利率!$G$2,B43,0)) -> 114263 | I43: =IF(B43="","",IF(C43<16,0,IF(C43=16,OFFSET(宣告利率!$O$2,B43-1,0),0)+OFFSET(宣告利率!$O$2,B43,0))) -> 160821 | J43: =IF(B43="","",IF(C43<16,0,OFFSET(宣告利率!$P$2,B43,0))) -> 2644359 | K43: =IF(B43="","",IF(C43<16,OFFSET(宣告利率!$N$2,B43,0)+OFFSET(宣告利率!$U$2,B43,0),OFFSET(宣告利率!$Q$2,B43,0)+OFFSET(宣告利率!$U$2,B43,0))) -> 1878817 | L43: =IF(B43="","",IF(C43<16,OFFSET(宣告利率!$N$2,B43,0),OFFSET(宣告利率!$Q$2,B43,0)+OFFSET(宣告利率!$U$2,B43,0))) -> 1878817 | M43: =IF(B43="","",IF(OR(ZDIVOPT02=CSWD,ZDIVOPT02=DVAC),OFFSET(宣告利率!$R$2,B43,0),0)) -> 0 | N43: =IF(B43="","",IF(ZDIVOPT02=CSWD,OFFSET(宣告利率!$S$2,B43,0),IF(ZDIVOPT02=DVAC,OFFSET(宣告利率!$T$2,B43,0),0))) -> 0 | O43: =IF(B43="","",IF(C43<0,0,OFFSET(宣告利率!$J$2,B43,0)+MAX(OFFSET(宣告利率!$V$2,B43,0,1,3)))) -> 4953272 | P43: =IF(B43="","",F43+L43) -> 4508994 | Q43: =IF(B43="","",IF(C43=109,0,OFFSET(宣告利率!$AB$2,B43,0)+OFFSET(宣告利率!$AC$2,B43,0))) -> 4509032 | R43: =IF(B43="","",P43+IF(ZDIVOPT02=CSWD,M43,0)+IF(ZDIVOPT02=DVAC,N43,0)) -> 4508994 | S43: =IF(C43=109,0,IF(B43="","",Q43+IF(ZDIVOPT02=CSWD,M43,0)+IF(ZDIVOPT02=DVAC,N43,0))) -> 4509032 | T43: =IF(B43="","",FYPremium+(MIN(PayYear,B43)-1)*CYPremium) -> 2655727 | U43: =IF(B43="","",OFFSET(宣告利率!$Y$2,B43,0)) -> 4394730.2 | V43: =IF(B43="","",P43+N43) -> 4508994 | W43: =IF(B43="","",V43/D43) -> 1.6978379 | X43: =IF(B43="","",IF(C43=109,0,Q43+N43)) -> 4509032 | Y43: =IF(B43="","",IF(OR(B43<PayYear,C43=109),"-",X43/D43)) -> 1.6978522 | Z43: =IF(B43="","",O43/D43) -> 1.8651285 | AA43: =AND(INDIRECT("B"&ROW())>0,MOD(INDIRECT("B"&ROW()),5)=0) -> FALSE
B44: =IF(B43="","",IF(C43=險種基本資料!$B$21,"",B43+1)) -> 22 | C44: =IF(B44="","",Age+B44-1) -> 92 | D44: =IF(B44="","",OFFSET(宣告利率!$I$2,B44,0)) -> 2655727 | E44: =IF(B44="","",OFFSET(宣告利率!$M$2,B44,0)+OFFSET(宣告利率!$K$2,B44,0)) -> 2638321 | F44: =IF(B44="","",OFFSET(宣告利率!$L$2,B44,0)+OFFSET(宣告利率!$K$2,B44,0)) -> 2638321 | G44: =IF(B44="","",OFFSET(宣告利率!$J$2,B44,0)) -> 2905225 | H44: =IF(B44="","",OFFSET(宣告利率!$G$2,B44,0)) -> 117597 | I44: =IF(B44="","",IF(C44<16,0,IF(C44=16,OFFSET(宣告利率!$O$2,B44-1,0),0)+OFFSET(宣告利率!$O$2,B44,0))) -> 165002 | J44: =IF(B44="","",IF(C44<16,0,OFFSET(宣告利率!$P$2,B44,0))) -> 2809361 | K44: =IF(B44="","",IF(C44<16,OFFSET(宣告利率!$N$2,B44,0)+OFFSET(宣告利率!$U$2,B44,0),OFFSET(宣告利率!$Q$2,B44,0)+OFFSET(宣告利率!$U$2,B44,0))) -> 2002232 | L44: =IF(B44="","",IF(C44<16,OFFSET(宣告利率!$N$2,B44,0),OFFSET(宣告利率!$Q$2,B44,0)+OFFSET(宣告利率!$U$2,B44,0))) -> 2002232 | M44: =IF(B44="","",IF(OR(ZDIVOPT02=CSWD,ZDIVOPT02=DVAC),OFFSET(宣告利率!$R$2,B44,0),0)) -> 0 | N44: =IF(B44="","",IF(ZDIVOPT02=CSWD,OFFSET(宣告利率!$S$2,B44,0),IF(ZDIVOPT02=DVAC,OFFSET(宣告利率!$T$2,B44,0),0))) -> 0 | O44: =IF(B44="","",IF(C44<0,0,OFFSET(宣告利率!$J$2,B44,0)+MAX(OFFSET(宣告利率!$V$2,B44,0,1,3)))) -> 4980518 | P44: =IF(B44="","",F44+L44) -> 4640553 | Q44: =IF(B44="","",IF(C44=109,0,OFFSET(宣告利率!$AB$2,B44,0)+OFFSET(宣告利率!$AC$2,B44,0))) -> 4640620 | R44: =IF(B44="","",P44+IF(ZDIVOPT02=CSWD,M44,0)+IF(ZDIVOPT02=DVAC,N44,0)) -> 4640553 | S44: =IF(C44=109,0,IF(B44="","",Q44+IF(ZDIVOPT02=CSWD,M44,0)+IF(ZDIVOPT02=DVAC,N44,0))) -> 4640620 | T44: =IF(B44="","",FYPremium+(MIN(PayYear,B44)-1)*CYPremium) -> 2655727 | U44: =IF(B44="","",OFFSET(宣告利率!$Y$2,B44,0)) -> 4522955.3 | V44: =IF(B44="","",P44+N44) -> 4640553 | W44: =IF(B44="","",V44/D44) -> 1.7473758 | X44: =IF(B44="","",IF(C44=109,0,Q44+N44)) -> 4640620 | Y44: =IF(B44="","",IF(OR(B44<PayYear,C44=109),"-",X44/D44)) -> 1.747401 | Z44: =IF(B44="","",O44/D44) -> 1.8753878 | AA44: =AND(INDIRECT("B"&ROW())>0,MOD(INDIRECT("B"&ROW()),5)=0) -> FALSE
B45: =IF(B44="","",IF(C44=險種基本資料!$B$21,"",B44+1)) -> 23 | C45: =IF(B45="","",Age+B45-1) -> 93 | D45: =IF(B45="","",OFFSET(宣告利率!$I$2,B45,0)) -> 2655727 | E45: =IF(B45="","",OFFSET(宣告利率!$M$2,B45,0)+OFFSET(宣告利率!$K$2,B45,0)) -> 2652388 | F45: =IF(B45="","",OFFSET(宣告利率!$L$2,B45,0)+OFFSET(宣告利率!$K$2,B45,0)) -> 2652388 | G45: =IF(B45="","",OFFSET(宣告利率!$J$2,B45,0)) -> 2855620 | H45: =IF(B45="","",OFFSET(宣告利率!$G$2,B45,0)) -> 121298 | I45: =IF(B45="","",IF(C45<16,0,IF(C45=16,OFFSET(宣告利率!$O$2,B45-1,0),0)+OFFSET(宣告利率!$O$2,B45,0))) -> 169292 | J45: =IF(B45="","",IF(C45<16,0,OFFSET(宣告利率!$P$2,B45,0))) -> 2978653 | K45: =IF(B45="","",IF(C45<16,OFFSET(宣告利率!$N$2,B45,0)+OFFSET(宣告利率!$U$2,B45,0),OFFSET(宣告利率!$Q$2,B45,0)+OFFSET(宣告利率!$U$2,B45,0))) -> 2134205 | L45: =IF(B45="","",IF(C45<16,OFFSET(宣告利率!$N$2,B45,0),OFFSET(宣告利率!$Q$2,B45,0)+OFFSET(宣告利率!$U$2,B45,0))) -> 2134205 | M45: =IF(B45="","",IF(OR(ZDIVOPT02=CSWD,ZDIVOPT02=DVAC),OFFSET(宣告利率!$R$2,B45,0),0)) -> 0 | N45: =IF(B45="","",IF(ZDIVOPT02=CSWD,OFFSET(宣告利率!$S$2,B45,0),IF(ZDIVOPT02=DVAC,OFFSET(宣告利率!$T$2,B45,0),0))) -> 0 | O45: =IF(B45="","",IF(C45<0,0,OFFSET(宣告利率!$J$2,B45,0)+MAX(OFFSET(宣告利率!$V$2,B45,0,1,3)))) -> 5022761 | P45: =IF(B45="","",F45+L45) -> 4786593 | Q45: =IF(B45="","",IF(C45=109,0,OFFSET(宣告利率!$AB$2,B45,0)+OFFSET(宣告利率!$AC$2,B45,0))) -> 4786658 | R45: =IF(B45="","",P45+IF(ZDIVOPT02=CSWD,M45,0)+IF(ZDIVOPT02=DVAC,N45,0)) -> 4786593 | S45: =IF(C45=109,0,IF(B45="","",Q45+IF(ZDIVOPT02=CSWD,M45,0)+IF(ZDIVOPT02=DVAC,N45,0))) -> 4786658 | T45: =IF(B45="","",FYPremium+(MIN(PayYear,B45)-1)*CYPremium) -> 2655727 | U45: =IF(B45="","",OFFSET(宣告利率!$Y$2,B45,0)) -> 4665294.9 | V45: =IF(B45="","",P45+N45) -> 4786593 | W45: =IF(B45="","",V45/D45) -> 1.8023664 | X45: =IF(B45="","",IF(C45=109,0,Q45+N45)) -> 4786658 | Y45: =IF(B45="","",IF(OR(B45<PayYear,C45=109),"-",X45/D45)) -> 1.8023908 | Z45: =IF(B45="","",O45/D45) -> 1.8912942 | AA45: =AND(INDIRECT("B"&ROW())>0,MOD(INDIRECT("B"&ROW()),5)=0) -> FALSE
B46: =IF(B45="","",IF(C45=險種基本資料!$B$21,"",B45+1)) -> 24 | C46: =IF(B46="","",Age+B46-1) -> 94 | D46: =IF(B46="","",OFFSET(宣告利率!$I$2,B46,0)) -> 2655727 | E46: =IF(B46="","",OFFSET(宣告利率!$M$2,B46,0)+OFFSET(宣告利率!$K$2,B46,0)) -> 2665714 | F46: =IF(B46="","",OFFSET(宣告利率!$L$2,B46,0)+OFFSET(宣告利率!$K$2,B46,0)) -> 2665714 | G46: =IF(B46="","",OFFSET(宣告利率!$J$2,B46,0)) -> 2855620 | H46: =IF(B46="","",OFFSET(宣告利率!$G$2,B46,0)) -> 125077 | I46: =IF(B46="","",IF(C46<16,0,IF(C46=16,OFFSET(宣告利率!$O$2,B46-1,0),0)+OFFSET(宣告利率!$O$2,B46,0))) -> 173694 | J46: =IF(B46="","",IF(C46<16,0,OFFSET(宣告利率!$P$2,B46,0))) -> 3152347 | K46: =IF(B46="","",IF(C46<16,OFFSET(宣告利率!$N$2,B46,0)+OFFSET(宣告利率!$U$2,B46,0),OFFSET(宣告利率!$Q$2,B46,0)+OFFSET(宣告利率!$U$2,B46,0))) -> 2270005 | L46: =IF(B46="","",IF(C46<16,OFFSET(宣告利率!$N$2,B46,0),OFFSET(宣告利率!$Q$2,B46,0)+OFFSET(宣告利率!$U$2,B46,0))) -> 2270005 | M46: =IF(B46="","",IF(OR(ZDIVOPT02=CSWD,ZDIVOPT02=DVAC),OFFSET(宣告利率!$R$2,B46,0),0)) -> 0 | N46: =IF(B46="","",IF(ZDIVOPT02=CSWD,OFFSET(宣告利率!$S$2,B46,0),IF(ZDIVOPT02=DVAC,OFFSET(宣告利率!$T$2,B46,0),0))) -> 0 | O46: =IF(B46="","",IF(C46<0,0,OFFSET(宣告利率!$J$2,B46,0)+MAX(OFFSET(宣告利率!$V$2,B46,0,1,3)))) -> 5153353 | P46: =IF(B46="","",F46+L46) -> 4935719 | Q46: =IF(B46="","",IF(C46=109,0,OFFSET(宣告利率!$AB$2,B46,0)+OFFSET(宣告利率!$AC$2,B46,0))) -> 4935783 | R46: =IF(B46="","",P46+IF(ZDIVOPT02=CSWD,M46,0)+IF(ZDIVOPT02=DVAC,N46,0)) -> 4935719 | S46: =IF(C46=109,0,IF(B46="","",Q46+IF(ZDIVOPT02=CSWD,M46,0)+IF(ZDIVOPT02=DVAC,N46,0))) -> 4935783 | T46: =IF(B46="","",FYPremium+(MIN(PayYear,B46)-1)*CYPremium) -> 2655727 | U46: =IF(B46="","",OFFSET(宣告利率!$Y$2,B46,0)) -> 4810642.5 | V46: =IF(B46="","",P46+N46) -> 4935719 | W46: =IF(B46="","",V46/D46) -> 1.858519 | X46: =IF(B46="","",IF(C46=109,0,Q46+N46)) -> 4935783 | Y46: =IF(B46="","",IF(OR(B46<PayYear,C46=109),"-",X46/D46)) -> 1.8585431 | Z46: =IF(B46="","",O46/D46) -> 1.9404679 | AA46: =AND(INDIRECT("B"&ROW())>0,MOD(INDIRECT("B"&ROW()),5)=0) -> FALSE
B47: =IF(B46="","",IF(C46=險種基本資料!$B$21,"",B46+1)) -> 25 | C47: =IF(B47="","",Age+B47-1) -> 95 | D47: =IF(B47="","",OFFSET(宣告利率!$I$2,B47,0)) -> 2655727 | E47: =IF(B47="","",OFFSET(宣告利率!$M$2,B47,0)+OFFSET(宣告利率!$K$2,B47,0)) -> 2678301 | F47: =IF(B47="","",OFFSET(宣告利率!$L$2,B47,0)+OFFSET(宣告利率!$K$2,B47,0)) -> 2678301 | G47: =IF(B47="","",OFFSET(宣告利率!$J$2,B47,0)) -> 2855620 | H47: =IF(B47="","",OFFSET(宣告利率!$G$2,B47,0)) -> 128935 | I47: =IF(B47="","",IF(C47<16,0,IF(C47=16,OFFSET(宣告利率!$O$2,B47-1,0),0)+OFFSET(宣告利率!$O$2,B47,0))) -> 178210 | J47: =IF(B47="","",IF(C47<16,0,OFFSET(宣告利率!$P$2,B47,0))) -> 3330557 | K47: =IF(B47="","",IF(C47<16,OFFSET(宣告利率!$N$2,B47,0)+OFFSET(宣告利率!$U$2,B47,0),OFFSET(宣告利率!$Q$2,B47,0)+OFFSET(宣告利率!$U$2,B47,0))) -> 2409658 | L47: =IF(B47="","",IF(C47<16,OFFSET(宣告利率!$N$2,B47,0),OFFSET(宣告利率!$Q$2,B47,0)+OFFSET(宣告利率!$U$2,B47,0))) -> 2409658 | M47: =IF(B47="","",IF(OR(ZDIVOPT02=CSWD,ZDIVOPT02=DVAC),OFFSET(宣告利率!$R$2,B47,0),0)) -> 0 | N47: =IF(B47="","",IF(ZDIVOPT02=CSWD,OFFSET(宣告利率!$S$2,B47,0),IF(ZDIVOPT02=DVAC,OFFSET(宣告利率!$T$2,B47,0),0))) -> 0 | O47: =IF(B47="","",IF(C47<0,0,OFFSET(宣告利率!$J$2,B47,0)+MAX(OFFSET(宣告利率!$V$2,B47,0,1,3)))) -> 5287340 | P47: =IF(B47="","",F47+L47) -> 5087959 | Q47: =IF(B47="","",IF(C47=109,0,OFFSET(宣告利率!$AB$2,B47,0)+OFFSET(宣告利率!$AC$2,B47,0))) -> 5088022 | R47: =IF(B47="","",P47+IF(ZDIVOPT02=CSWD,M47,0)+IF(ZDIVOPT02=DVAC,N47,0)) -> 5087959 | S47: =IF(C47=109,0,IF(B47="","",Q47+IF(ZDIVOPT02=CSWD,M47,0)+IF(ZDIVOPT02=DVAC,N47,0))) -> 5088022 | T47: =IF(B47="","",FYPremium+(MIN(PayYear,B47)-1)*CYPremium) -> 2655727 | U47: =IF(B47="","",OFFSET(宣告利率!$Y$2,B47,0)) -> 4959023.8 | V47: =IF(B47="","",P47+N47) -> 5087959 | W47: =IF(B47="","",V47/D47) -> 1.9158441 | X47: =IF(B47="","",IF(C47=109,0,Q47+N47)) -> 5088022 | Y47: =IF(B47="","",IF(OR(B47<PayYear,C47=109),"-",X47/D47)) -> 1.9158679 | Z47: =IF(B47="","",O47/D47) -> 1.99092 | AA47: =AND(INDIRECT("B"&ROW())>0,MOD(INDIRECT("B"&ROW()),5)=0) -> TRUE
B48: =IF(B47="","",IF(C47=險種基本資料!$B$21,"",B47+1)) -> 26 | C48: =IF(B48="","",Age+B48-1) -> 96 | D48: =IF(B48="","",OFFSET(宣告利率!$I$2,B48,0)) -> 2655727 | E48: =IF(B48="","",OFFSET(宣告利率!$M$2,B48,0)+OFFSET(宣告利率!$K$2,B48,0)) -> 2690517 | F48: =IF(B48="","",OFFSET(宣告利率!$L$2,B48,0)+OFFSET(宣告利率!$K$2,B48,0)) -> 2690517 | G48: =IF(B48="","",OFFSET(宣告利率!$J$2,B48,0)) -> 2855620 | H48: =IF(B48="","",OFFSET(宣告利率!$G$2,B48,0)) -> 132890 | I48: =IF(B48="","",IF(C48<16,0,IF(C48=16,OFFSET(宣告利率!$O$2,B48-1,0),0)+OFFSET(宣告利率!$O$2,B48,0))) -> 182843 | J48: =IF(B48="","",IF(C48<16,0,OFFSET(宣告利率!$P$2,B48,0))) -> 3513400 | K48: =IF(B48="","",IF(C48<16,OFFSET(宣告利率!$N$2,B48,0)+OFFSET(宣告利率!$U$2,B48,0),OFFSET(宣告利率!$Q$2,B48,0)+OFFSET(宣告利率!$U$2,B48,0))) -> 2553539 | L48: =IF(B48="","",IF(C48<16,OFFSET(宣告利率!$N$2,B48,0),OFFSET(宣告利率!$Q$2,B48,0)+OFFSET(宣告利率!$U$2,B48,0))) -> 2553539 | M48: =IF(B48="","",IF(OR(ZDIVOPT02=CSWD,ZDIVOPT02=DVAC),OFFSET(宣告利率!$R$2,B48,0),0)) -> 0 | N48: =IF(B48="","",IF(ZDIVOPT02=CSWD,OFFSET(宣告利率!$S$2,B48,0),IF(ZDIVOPT02=DVAC,OFFSET(宣告利率!$T$2,B48,0),0))) -> 0 | O48: =IF(B48="","",IF(C48<0,0,OFFSET(宣告利率!$J$2,B48,0)+MAX(OFFSET(宣告利率!$V$2,B48,0,1,3)))) -> 5424812 | P48: =IF(B48="","",F48+L48) -> 5244056 | Q48: =IF(B48="","",IF(C48=109,0,OFFSET(宣告利率!$AB$2,B48,0)+OFFSET(宣告利率!$AC$2,B48,0))) -> 5244119 | R48: =IF(B48="","",P48+IF(ZDIVOPT02=CSWD,M48,0)+IF(ZDIVOPT02=DVAC,N48,0)) -> 5244056 | S48: =IF(C48=109,0,IF(B48="","",Q48+IF(ZDIVOPT02=CSWD,M48,0)+IF(ZDIVOPT02=DVAC,N48,0))) -> 5244119 | T48: =IF(B48="","",FYPremium+(MIN(PayYear,B48)-1)*CYPremium) -> 2655727 | U48: =IF(B48="","",OFFSET(宣告利率!$Y$2,B48,0)) -> 5111165.8 | V48: =IF(B48="","",P48+N48) -> 5244056 | W48: =IF(B48="","",V48/D48) -> 1.9746216 | X48: =IF(B48="","",IF(C48=109,0,Q48+N48)) -> 5244119 | Y48: =IF(B48="","",IF(OR(B48<PayYear,C48=109),"-",X48/D48)) -> 1.9746454 | Z48: =IF(B48="","",O48/D48) -> 2.0426844 | AA48: =AND(INDIRECT("B"&ROW())>0,MOD(INDIRECT("B"&ROW()),5)=0) -> FALSE
B49: =IF(B48="","",IF(C48=險種基本資料!$B$21,"",B48+1)) -> 27 | C49: =IF(B49="","",Age+B49-1) -> 97 | D49: =IF(B49="","",OFFSET(宣告利率!$I$2,B49,0)) -> 2655727 | E49: =IF(B49="","",OFFSET(宣告利率!$M$2,B49,0)+OFFSET(宣告利率!$K$2,B49,0)) -> 2702363 | F49: =IF(B49="","",OFFSET(宣告利率!$L$2,B49,0)+OFFSET(宣告利率!$K$2,B49,0)) -> 2702363 | G49: =IF(B49="","",OFFSET(宣告利率!$J$2,B49,0)) -> 2855620 | H49: =IF(B49="","",OFFSET(宣告利率!$G$2,B49,0)) -> 136946 | I49: =IF(B49="","",IF(C49<16,0,IF(C49=16,OFFSET(宣告利率!$O$2,B49-1,0),0)+OFFSET(宣告利率!$O$2,B49,0))) -> 187597 | J49: =IF(B49="","",IF(C49<16,0,OFFSET(宣告利率!$P$2,B49,0))) -> 3700997 | K49: =IF(B49="","",IF(C49<16,OFFSET(宣告利率!$N$2,B49,0)+OFFSET(宣告利率!$U$2,B49,0),OFFSET(宣告利率!$Q$2,B49,0)+OFFSET(宣告利率!$U$2,B49,0))) -> 2701728 | L49: =IF(B49="","",IF(C49<16,OFFSET(宣告利率!$N$2,B49,0),OFFSET(宣告利率!$Q$2,B49,0)+OFFSET(宣告利率!$U$2,B49,0))) -> 2701728 | M49: =IF(B49="","",IF(OR(ZDIVOPT02=CSWD,ZDIVOPT02=DVAC),OFFSET(宣告利率!$R$2,B49,0),0)) -> 0 | N49: =IF(B49="","",IF(ZDIVOPT02=CSWD,OFFSET(宣告利率!$S$2,B49,0),IF(ZDIVOPT02=DVAC,OFFSET(宣告利率!$T$2,B49,0),0))) -> 0 | O49: =IF(B49="","",IF(C49<0,0,OFFSET(宣告利率!$J$2,B49,0)+MAX(OFFSET(宣告利率!$V$2,B49,0,1,3)))) -> 5565857 | P49: =IF(B49="","",F49+L49) -> 5404091 | Q49: =IF(B49="","",IF(C49=109,0,OFFSET(宣告利率!$AB$2,B49,0)+OFFSET(宣告利率!$AC$2,B49,0))) -> 5404149 | R49: =IF(B49="","",P49+IF(ZDIVOPT02=CSWD,M49,0)+IF(ZDIVOPT02=DVAC,N49,0)) -> 5404091 | S49: =IF(C49=109,0,IF(B49="","",Q49+IF(ZDIVOPT02=CSWD,M49,0)+IF(ZDIVOPT02=DVAC,N49,0))) -> 5404149 | T49: =IF(B49="","",FYPremium+(MIN(PayYear,B49)-1)*CYPremium) -> 2655727 | U49: =IF(B49="","",OFFSET(宣告利率!$Y$2,B49,0)) -> 5267144.9 | V49: =IF(B49="","",P49+N49) -> 5404091 | W49: =IF(B49="","",V49/D49) -> 2.034882 | X49: =IF(B49="","",IF(C49=109,0,Q49+N49)) -> 5404149 | Y49: =IF(B49="","",IF(OR(B49<PayYear,C49=109),"-",X49/D49)) -> 2.0349038 | Z49: =IF(B49="","",O49/D49) -> 2.0957941 | AA49: =AND(INDIRECT("B"&ROW())>0,MOD(INDIRECT("B"&ROW()),5)=0) -> FALSE
B50: =IF(B49="","",IF(C49=險種基本資料!$B$21,"",B49+1)) -> 28 | C50: =IF(B50="","",Age+B50-1) -> 98 | D50: =IF(B50="","",OFFSET(宣告利率!$I$2,B50,0)) -> 2655727 | E50: =IF(B50="","",OFFSET(宣告利率!$M$2,B50,0)+OFFSET(宣告利率!$K$2,B50,0)) -> 2713098 | F50: =IF(B50="","",OFFSET(宣告利率!$L$2,B50,0)+OFFSET(宣告利率!$K$2,B50,0)) -> 2713098 | G50: =IF(B50="","",OFFSET(宣告利率!$J$2,B50,0)) -> 2855620 | H50: =IF(B50="","",OFFSET(宣告利率!$G$2,B50,0)) -> 141065 | I50: =IF(B50="","",IF(C50<16,0,IF(C50=16,OFFSET(宣告利率!$O$2,B50-1,0),0)+OFFSET(宣告利率!$O$2,B50,0))) -> 192475 | J50: =IF(B50="","",IF(C50<16,0,OFFSET(宣告利率!$P$2,B50,0))) -> 3893472 | K50: =IF(B50="","",IF(C50<16,OFFSET(宣告利率!$N$2,B50,0)+OFFSET(宣告利率!$U$2,B50,0),OFFSET(宣告利率!$Q$2,B50,0)+OFFSET(宣告利率!$U$2,B50,0))) -> 2853526 | L50: =IF(B50="","",IF(C50<16,OFFSET(宣告利率!$N$2,B50,0),OFFSET(宣告利率!$Q$2,B50,0)+OFFSET(宣告利率!$U$2,B50,0))) -> 2853526 | M50: =IF(B50="","",IF(OR(ZDIVOPT02=CSWD,ZDIVOPT02=DVAC),OFFSET(宣告利率!$R$2,B50,0),0)) -> 0 | N50: =IF(B50="","",IF(ZDIVOPT02=CSWD,OFFSET(宣告利率!$S$2,B50,0),IF(ZDIVOPT02=DVAC,OFFSET(宣告利率!$T$2,B50,0),0))) -> 0 | O50: =IF(B50="","",IF(C50<0,0,OFFSET(宣告利率!$J$2,B50,0)+MAX(OFFSET(宣告利率!$V$2,B50,0,1,3)))) -> 5710569 | P50: =IF(B50="","",F50+L50) -> 5566624 | Q50: =IF(B50="","",IF(C50=109,0,OFFSET(宣告利率!$AB$2,B50,0)+OFFSET(宣告利率!$AC$2,B50,0))) -> 5566682 | R50: =IF(B50="","",P50+IF(ZDIVOPT02=CSWD,M50,0)+IF(ZDIVOPT02=DVAC,N50,0)) -> 5566624 | S50: =IF(C50=109,0,IF(B50="","",Q50+IF(ZDIVOPT02=CSWD,M50,0)+IF(ZDIVOPT02=DVAC,N50,0))) -> 5566682 | T50: =IF(B50="","",FYPremium+(MIN(PayYear,B50)-1)*CYPremium) -> 2655727 | U50: =IF(B50="","",OFFSET(宣告利率!$Y$2,B50,0)) -> 5425559 | V50: =IF(B50="","",P50+N50) -> 5566624 | W50: =IF(B50="","",V50/D50) -> 2.0960829 | X50: =IF(B50="","",IF(C50=109,0,Q50+N50)) -> 5566682 | Y50: =IF(B50="","",IF(OR(B50<PayYear,C50=109),"-",X50/D50)) -> 2.0961048 | Z50: =IF(B50="","",O50/D50) -> 2.1502846 | AA50: =AND(INDIRECT("B"&ROW())>0,MOD(INDIRECT("B"&ROW()),5)=0) -> FALSE
... B62: =IF(B61="","",IF(C61=險種基本資料!$B$21,"",B61+1)) | C62: =IF(B62="","",Age+B62-1) | D62: =IF(B62="","",OFFSET(宣告利率!$I$2,B62,0)) | E62: =IF(B62="","",OFFSET(宣告利率!$M$2,B62,0)+OFFSET(宣告利率!$K$2,B62,0)) | F62: =IF(B62="","",OFFSET(宣告利率!$L$2,B62,0)+OFFSET(宣告利率!$K$2,B62,0)) | G62: =IF(B62="","",OFFSET(宣告利率!$J$2,B62,0)) | H62: =IF(B62="","",OFFSET(宣告利率!$G$2,B62,0)) | I62: =IF(B62="","",IF(C62<16,0,IF(C62=16,OFFSET(宣告利率!$O$2,B62-1,0),0)+OFFSET(宣告利率!$O$2,B62,0))) | J62: =IF(B62="","",IF(C62<16,0,OFFSET(宣告利率!$P$2,B62,0))) | K62: =IF(B62="","",IF(C62<16,OFFSET(宣告利率!$N$2,B62,0)+OFFSET(宣告利率!$U$2,B62,0),OFFSET(宣告利率!$Q$2,B62,0)+OFFSET(宣告利率!$U$2,B62,0))) | L62: =IF(B62="","",IF(C62<16,OFFSET(宣告利率!$N$2,B62,0),OFFSET(宣告利率!$Q$2,B62,0)+OFFSET(宣告利率!$U$2,B62,0))) | M62: =IF(B62="","",IF(OR(ZDIVOPT02=CSWD,ZDIVOPT02=DVAC),OFFSET(宣告利率!$R$2,B62,0),0)) | N62: =IF(B62="","",IF(ZDIVOPT02=CSWD,OFFSET(宣告利率!$S$2,B62,0),IF(ZDIVOPT02=DVAC,OFFSET(宣告利率!$T$2,B62,0),0))) | O62: =IF(B62="","",IF(C62<0,0,OFFSET(宣告利率!$J$2,B62,0)+MAX(OFFSET(宣告利率!$V$2,B62,0,1,3)))) | P62: =IF(B62="","",F62+L62) | Q62: =IF(B62="","",IF(C62=109,0,OFFSET(宣告利率!$AB$2,B62,0)+OFFSET(宣告利率!$AC$2,B62,0))) | R62: =IF(B62="","",P62+IF(ZDIVOPT02=CSWD,M62,0)+IF(ZDIVOPT02=DVAC,N62,0)) | S62: =IF(C62=109,0,IF(B62="","",Q62+IF(ZDIVOPT02=CSWD,M62,0)+IF(ZDIVOPT02=DVAC,N62,0))) | T62: =IF(B62="","",FYPremium+(MIN(PayYear,B62)-1)*CYPremium) | U62: =IF(B62="","",OFFSET(宣告利率!$Y$2,B62,0)) | V62: =IF(B62="","",P62+N62) | W62: =IF(B62="","",V62/D62) | X62: =IF(B62="","",IF(C62=109,0,Q62+N62)) | Y62: =IF(B62="","",IF(OR(B62<PayYear,C62=109),"-",X62/D62)) | Z62: =IF(B62="","",O62/D62) | AA62: =AND(INDIRECT("B"&ROW())>0,MOD(INDIRECT("B"&ROW()),5)=0) -> #VALUE!
B63: =B17 -> 保單 年度 (末) | C63: =C17 -> 保險 年齡 | D63: =D17 -> 累積所繳保險費 (A) | E63: =E17 -> 基本保險金額對應之保單價值準備金 【含祝壽保險金】 | F63: =F17 -> 基本保險金額 對應之現金價值 【含祝壽保險金】 (B) | G63: =G17 -> 基本保險金額 對應之壽險保障 (身故保險金) | J63: =J17 -> 假設投保後未來各保單年度宣告利率為4.35% (下表為預估假設值) | R63: =R17 -> 年度末終止契約時合計可領取之金額(含增值回饋分享金) (F) | S63: =S17 -> 次年度期初終止契約時合計可領取之金額(含增值回饋分享金) (H)=(G) | T63: =T17 -> 累積 應繳保費 | U63: =U17 -> 期末保單價值準備金(含基本保險金額、累計增加保險金額) 【含祝壽保險金】 | V63: =V17 -> (E)+(F) | W63: =W17 -> ((E)+(F))/(A) | X63: =X17 -> (G)+(E) | Y63: =Y17 -> ((G)+(E))/(A) | Z63: =Z17 -> (I)/(A) | AA63: =AND(INDIRECT("B"&ROW())>0,MOD(INDIRECT("B"&ROW()),5)=0) -> #VALUE!
B64: =B18 -> 0 | C64: =C18 -> 0 | D64: =D18 -> 0 | E64: =E18 -> 0 | F64: =F18 -> 0 | G64: =G18 -> 0 | H64: =H18 -> 增值回饋分享金 | I64: =I18 -> 選擇以繳清保險方式增加保險金額 | ... Q64: =Q18 -> 0 | T64: =T18 -> 0 | U64: =U18 -> 0 | V64: =V18 -> 0 | W64: =W18 -> 0 | X64: =X18 -> 0 | Y64: =Y18 -> 0 | AA64: =AND(INDIRECT("B"&ROW())>0,MOD(INDIRECT("B"&ROW()),5)=0) -> FALSE
B65: =B19 -> 0 | C65: =C19 -> 0 | D65: =D19 -> 0 | E65: =E19 -> 0 | F65: =F19 -> 0 | G65: =G19 -> 0 | H65: =H19 -> 0 | I65: =I19 -> 增額繳清保險金額 | ... Q65: =Q19 -> 次年度期初 現金價值 (G) | T65: =T19 -> 0 | U65: =U19 -> 0 | V65: =V19 -> 0 | W65: =W19 -> 0 | X65: =X19 -> 0 | Y65: =Y19 -> 0 | AA65: =AND(INDIRECT("B"&ROW())>0,MOD(INDIRECT("B"&ROW()),5)=0) -> FALSE
B66: =IF(B62="","",IF(C62=險種基本資料!$B$21,"",B62+1)) | C66: =IF(B66="","",Age+B66-1) | D66: =IF(B66="","",OFFSET(宣告利率!$I$2,B66,0)) | E66: =IF(B66="","",OFFSET(宣告利率!$M$2,B66,0)+OFFSET(宣告利率!$K$2,B66,0)) | F66: =IF(B66="","",OFFSET(宣告利率!$L$2,B66,0)+OFFSET(宣告利率!$K$2,B66,0)) | G66: =IF(B66="","",OFFSET(宣告利率!$J$2,B66,0)) | H66: =IF(B66="","",OFFSET(宣告利率!$G$2,B66,0)) | I66: =IF(B66="","",IF(C66<16,0,IF(C66=16,OFFSET(宣告利率!$O$2,B66-1,0),0)+OFFSET(宣告利率!$O$2,B66,0))) | J66: =IF(B66="","",IF(C66<16,0,OFFSET(宣告利率!$P$2,B66,0))) | K66: =IF(B66="","",IF(C66<16,OFFSET(宣告利率!$N$2,B66,0)+OFFSET(宣告利率!$U$2,B66,0),OFFSET(宣告利率!$Q$2,B66,0)+OFFSET(宣告利率!$U$2,B66,0))) | L66: =IF(B66="","",IF(C66<16,OFFSET(宣告利率!$N$2,B66,0),OFFSET(宣告利率!$Q$2,B66,0)+OFFSET(宣告利率!$U$2,B66,0))) | M66: =IF(B66="","",IF(OR(ZDIVOPT02=CSWD,ZDIVOPT02=DVAC),OFFSET(宣告利率!$R$2,B66,0),0)) | N66: =IF(B66="","",IF(ZDIVOPT02=CSWD,OFFSET(宣告利率!$S$2,B66,0),IF(ZDIVOPT02=DVAC,OFFSET(宣告利率!$T$2,B66,0),0))) | O66: =IF(B66="","",IF(C66<0,0,OFFSET(宣告利率!$J$2,B66,0)+MAX(OFFSET(宣告利率!$V$2,B66,0,1,3)))) | P66: =IF(B66="","",F66+L66) | Q66: =IF(B66="","",IF(C66=109,0,OFFSET(宣告利率!$AB$2,B66,0)+OFFSET(宣告利率!$AC$2,B66,0))) | R66: =IF(B66="","",P66+IF(ZDIVOPT02=CSWD,M66,0)+IF(ZDIVOPT02=DVAC,N66,0)) | S66: =IF(C66=109,0,IF(B66="","",Q66+IF(ZDIVOPT02=CSWD,M66,0)+IF(ZDIVOPT02=DVAC,N66,0))) | T66: =IF(B66="","",FYPremium+(MIN(PayYear,B66)-1)*CYPremium) | U66: =IF(B66="","",OFFSET(宣告利率!$Y$2,B66,0)) | V66: =IF(B66="","",P66+N66) | W66: =IF(B66="","",V66/D66) | X66: =IF(B66="","",IF(C66=109,0,Q66+N66)) | Y66: =IF(B66="","",IF(OR(B66<PayYear,C66=109),"-",X66/D66)) | Z66: =IF(B66="","",O66/D66) | AA66: =AND(INDIRECT("B"&ROW())>0,MOD(INDIRECT("B"&ROW()),5)=0) -> #VALUE!
B67: =IF(B66="","",IF(C66=險種基本資料!$B$21,"",B66+1)) | C67: =IF(B67="","",Age+B67-1) | D67: =IF(B67="","",OFFSET(宣告利率!$I$2,B67,0)) | E67: =IF(B67="","",OFFSET(宣告利率!$M$2,B67,0)+OFFSET(宣告利率!$K$2,B67,0)) | F67: =IF(B67="","",OFFSET(宣告利率!$L$2,B67,0)+OFFSET(宣告利率!$K$2,B67,0)) | G67: =IF(B67="","",OFFSET(宣告利率!$J$2,B67,0)) | H67: =IF(B67="","",OFFSET(宣告利率!$G$2,B67,0)) | I67: =IF(B67="","",IF(C67<16,0,IF(C67=16,OFFSET(宣告利率!$O$2,B67-1,0),0)+OFFSET(宣告利率!$O$2,B67,0))) | J67: =IF(B67="","",IF(C67<16,0,OFFSET(宣告利率!$P$2,B67,0))) | K67: =IF(B67="","",IF(C67<16,OFFSET(宣告利率!$N$2,B67,0)+OFFSET(宣告利率!$U$2,B67,0),OFFSET(宣告利率!$Q$2,B67,0)+OFFSET(宣告利率!$U$2,B67,0))) | L67: =IF(B67="","",IF(C67<16,OFFSET(宣告利率!$N$2,B67,0),OFFSET(宣告利率!$Q$2,B67,0)+OFFSET(宣告利率!$U$2,B67,0))) | M67: =IF(B67="","",IF(OR(ZDIVOPT02=CSWD,ZDIVOPT02=DVAC),OFFSET(宣告利率!$R$2,B67,0),0)) | N67: =IF(B67="","",IF(ZDIVOPT02=CSWD,OFFSET(宣告利率!$S$2,B67,0),IF(ZDIVOPT02=DVAC,OFFSET(宣告利率!$T$2,B67,0),0))) | O67: =IF(B67="","",IF(C67<0,0,OFFSET(宣告利率!$J$2,B67,0)+MAX(OFFSET(宣告利率!$V$2,B67,0,1,3)))) | P67: =IF(B67="","",F67+L67) | Q67: =IF(B67="","",IF(C67=109,0,OFFSET(宣告利率!$AB$2,B67,0)+OFFSET(宣告利率!$AC$2,B67,0))) | R67: =IF(B67="","",P67+IF(ZDIVOPT02=CSWD,M67,0)+IF(ZDIVOPT02=DVAC,N67,0)) | S67: =IF(C67=109,0,IF(B67="","",Q67+IF(ZDIVOPT02=CSWD,M67,0)+IF(ZDIVOPT02=DVAC,N67,0))) | T67: =IF(B67="","",FYPremium+(MIN(PayYear,B67)-1)*CYPremium) | U67: =IF(B67="","",OFFSET(宣告利率!$Y$2,B67,0)) | V67: =IF(B67="","",P67+N67) | W67: =IF(B67="","",V67/D67) | X67: =IF(B67="","",IF(C67=109,0,Q67+N67)) | Y67: =IF(B67="","",IF(OR(B67<PayYear,C67=109),"-",X67/D67)) | Z67: =IF(B67="","",O67/D67) | AA67: =AND(INDIRECT("B"&ROW())>0,MOD(INDIRECT("B"&ROW()),5)=0) -> #VALUE!
B68: =IF(B67="","",IF(C67=險種基本資料!$B$21,"",B67+1)) | C68: =IF(B68="","",Age+B68-1) | D68: =IF(B68="","",OFFSET(宣告利率!$I$2,B68,0)) | E68: =IF(B68="","",OFFSET(宣告利率!$M$2,B68,0)+OFFSET(宣告利率!$K$2,B68,0)) | F68: =IF(B68="","",OFFSET(宣告利率!$L$2,B68,0)+OFFSET(宣告利率!$K$2,B68,0)) | G68: =IF(B68="","",OFFSET(宣告利率!$J$2,B68,0)) | H68: =IF(B68="","",OFFSET(宣告利率!$G$2,B68,0)) | I68: =IF(B68="","",IF(C68<16,0,IF(C68=16,OFFSET(宣告利率!$O$2,B68-1,0),0)+OFFSET(宣告利率!$O$2,B68,0))) | J68: =IF(B68="","",IF(C68<16,0,OFFSET(宣告利率!$P$2,B68,0))) | K68: =IF(B68="","",IF(C68<16,OFFSET(宣告利率!$N$2,B68,0)+OFFSET(宣告利率!$U$2,B68,0),OFFSET(宣告利率!$Q$2,B68,0)+OFFSET(宣告利率!$U$2,B68,0))) | L68: =IF(B68="","",IF(C68<16,OFFSET(宣告利率!$N$2,B68,0),OFFSET(宣告利率!$Q$2,B68,0)+OFFSET(宣告利率!$U$2,B68,0))) | M68: =IF(B68="","",IF(OR(ZDIVOPT02=CSWD,ZDIVOPT02=DVAC),OFFSET(宣告利率!$R$2,B68,0),0)) | N68: =IF(B68="","",IF(ZDIVOPT02=CSWD,OFFSET(宣告利率!$S$2,B68,0),IF(ZDIVOPT02=DVAC,OFFSET(宣告利率!$T$2,B68,0),0))) | O68: =IF(B68="","",IF(C68<0,0,OFFSET(宣告利率!$J$2,B68,0)+MAX(OFFSET(宣告利率!$V$2,B68,0,1,3)))) | P68: =IF(B68="","",F68+L68) | Q68: =IF(B68="","",IF(C68=109,0,OFFSET(宣告利率!$AB$2,B68,0)+OFFSET(宣告利率!$AC$2,B68,0))) | R68: =IF(B68="","",P68+IF(ZDIVOPT02=CSWD,M68,0)+IF(ZDIVOPT02=DVAC,N68,0)) | S68: =IF(C68=109,0,IF(B68="","",Q68+IF(ZDIVOPT02=CSWD,M68,0)+IF(ZDIVOPT02=DVAC,N68,0))) | T68: =IF(B68="","",FYPremium+(MIN(PayYear,B68)-1)*CYPremium) | U68: =IF(B68="","",OFFSET(宣告利率!$Y$2,B68,0)) | V68: =IF(B68="","",P68+N68) | W68: =IF(B68="","",V68/D68) | X68: =IF(B68="","",IF(C68=109,0,Q68+N68)) | Y68: =IF(B68="","",IF(OR(B68<PayYear,C68=109),"-",X68/D68)) | Z68: =IF(B68="","",O68/D68) | AA68: =AND(INDIRECT("B"&ROW())>0,MOD(INDIRECT("B"&ROW()),5)=0) -> #VALUE!
B69: =IF(B68="","",IF(C68=險種基本資料!$B$21,"",B68+1)) | C69: =IF(B69="","",Age+B69-1) | D69: =IF(B69="","",OFFSET(宣告利率!$I$2,B69,0)) | E69: =IF(B69="","",OFFSET(宣告利率!$M$2,B69,0)+OFFSET(宣告利率!$K$2,B69,0)) | F69: =IF(B69="","",OFFSET(宣告利率!$L$2,B69,0)+OFFSET(宣告利率!$K$2,B69,0)) | G69: =IF(B69="","",OFFSET(宣告利率!$J$2,B69,0)) | H69: =IF(B69="","",OFFSET(宣告利率!$G$2,B69,0)) | I69: =IF(B69="","",IF(C69<16,0,IF(C69=16,OFFSET(宣告利率!$O$2,B69-1,0),0)+OFFSET(宣告利率!$O$2,B69,0))) | J69: =IF(B69="","",IF(C69<16,0,OFFSET(宣告利率!$P$2,B69,0))) | K69: =IF(B69="","",IF(C69<16,OFFSET(宣告利率!$N$2,B69,0)+OFFSET(宣告利率!$U$2,B69,0),OFFSET(宣告利率!$Q$2,B69,0)+OFFSET(宣告利率!$U$2,B69,0))) | L69: =IF(B69="","",IF(C69<16,OFFSET(宣告利率!$N$2,B69,0),OFFSET(宣告利率!$Q$2,B69,0)+OFFSET(宣告利率!$U$2,B69,0))) | M69: =IF(B69="","",IF(OR(ZDIVOPT02=CSWD,ZDIVOPT02=DVAC),OFFSET(宣告利率!$R$2,B69,0),0)) | N69: =IF(B69="","",IF(ZDIVOPT02=CSWD,OFFSET(宣告利率!$S$2,B69,0),IF(ZDIVOPT02=DVAC,OFFSET(宣告利率!$T$2,B69,0),0))) | O69: =IF(B69="","",IF(C69<0,0,OFFSET(宣告利率!$J$2,B69,0)+MAX(OFFSET(宣告利率!$V$2,B69,0,1,3)))) | P69: =IF(B69="","",F69+L69) | Q69: =IF(B69="","",IF(C69=109,0,OFFSET(宣告利率!$AB$2,B69,0)+OFFSET(宣告利率!$AC$2,B69,0))) | R69: =IF(B69="","",P69+IF(ZDIVOPT02=CSWD,M69,0)+IF(ZDIVOPT02=DVAC,N69,0)) | S69: =IF(C69=109,0,IF(B69="","",Q69+IF(ZDIVOPT02=CSWD,M69,0)+IF(ZDIVOPT02=DVAC,N69,0))) | T69: =IF(B69="","",FYPremium+(MIN(PayYear,B69)-1)*CYPremium) | U69: =IF(B69="","",OFFSET(宣告利率!$Y$2,B69,0)) | V69: =IF(B69="","",P69+N69) | W69: =IF(B69="","",V69/D69) | X69: =IF(B69="","",IF(C69=109,0,Q69+N69)) | Y69: =IF(B69="","",IF(OR(B69<PayYear,C69=109),"-",X69/D69)) | Z69: =IF(B69="","",O69/D69) | AA69: =AND(INDIRECT("B"&ROW())>0,MOD(INDIRECT("B"&ROW()),5)=0) -> #VALUE!
B70: =IF(B69="","",IF(C69=險種基本資料!$B$21,"",B69+1)) | C70: =IF(B70="","",Age+B70-1) | D70: =IF(B70="","",OFFSET(宣告利率!$I$2,B70,0)) | E70: =IF(B70="","",OFFSET(宣告利率!$M$2,B70,0)+OFFSET(宣告利率!$K$2,B70,0)) | F70: =IF(B70="","",OFFSET(宣告利率!$L$2,B70,0)+OFFSET(宣告利率!$K$2,B70,0)) | G70: =IF(B70="","",OFFSET(宣告利率!$J$2,B70,0)) | H70: =IF(B70="","",OFFSET(宣告利率!$G$2,B70,0)) | I70: =IF(B70="","",IF(C70<16,0,IF(C70=16,OFFSET(宣告利率!$O$2,B70-1,0),0)+OFFSET(宣告利率!$O$2,B70,0))) | J70: =IF(B70="","",IF(C70<16,0,OFFSET(宣告利率!$P$2,B70,0))) | K70: =IF(B70="","",IF(C70<16,OFFSET(宣告利率!$N$2,B70,0)+OFFSET(宣告利率!$U$2,B70,0),OFFSET(宣告利率!$Q$2,B70,0)+OFFSET(宣告利率!$U$2,B70,0))) | L70: =IF(B70="","",IF(C70<16,OFFSET(宣告利率!$N$2,B70,0),OFFSET(宣告利率!$Q$2,B70,0)+OFFSET(宣告利率!$U$2,B70,0))) | M70: =IF(B70="","",IF(OR(ZDIVOPT02=CSWD,ZDIVOPT02=DVAC),OFFSET(宣告利率!$R$2,B70,0),0)) | N70: =IF(B70="","",IF(ZDIVOPT02=CSWD,OFFSET(宣告利率!$S$2,B70,0),IF(ZDIVOPT02=DVAC,OFFSET(宣告利率!$T$2,B70,0),0))) | O70: =IF(B70="","",IF(C70<0,0,OFFSET(宣告利率!$J$2,B70,0)+MAX(OFFSET(宣告利率!$V$2,B70,0,1,3)))) | P70: =IF(B70="","",F70+L70) | Q70: =IF(B70="","",IF(C70=109,0,OFFSET(宣告利率!$AB$2,B70,0)+OFFSET(宣告利率!$AC$2,B70,0))) | R70: =IF(B70="","",P70+IF(ZDIVOPT02=CSWD,M70,0)+IF(ZDIVOPT02=DVAC,N70,0)) | S70: =IF(C70=109,0,IF(B70="","",Q70+IF(ZDIVOPT02=CSWD,M70,0)+IF(ZDIVOPT02=DVAC,N70,0))) | T70: =IF(B70="","",FYPremium+(MIN(PayYear,B70)-1)*CYPremium) | U70: =IF(B70="","",OFFSET(宣告利率!$Y$2,B70,0)) | V70: =IF(B70="","",P70+N70) | W70: =IF(B70="","",V70/D70) | X70: =IF(B70="","",IF(C70=109,0,Q70+N70)) | Y70: =IF(B70="","",IF(OR(B70<PayYear,C70=109),"-",X70/D70)) | Z70: =IF(B70="","",O70/D70) | AA70: =AND(INDIRECT("B"&ROW())>0,MOD(INDIRECT("B"&ROW()),5)=0) -> #VALUE!
B71: =IF(B70="","",IF(C70=險種基本資料!$B$21,"",B70+1)) | C71: =IF(B71="","",Age+B71-1) | D71: =IF(B71="","",OFFSET(宣告利率!$I$2,B71,0)) | E71: =IF(B71="","",OFFSET(宣告利率!$M$2,B71,0)+OFFSET(宣告利率!$K$2,B71,0)) | F71: =IF(B71="","",OFFSET(宣告利率!$L$2,B71,0)+OFFSET(宣告利率!$K$2,B71,0)) | G71: =IF(B71="","",OFFSET(宣告利率!$J$2,B71,0)) | H71: =IF(B71="","",OFFSET(宣告利率!$G$2,B71,0)) | I71: =IF(B71="","",IF(C71<16,0,IF(C71=16,OFFSET(宣告利率!$O$2,B71-1,0),0)+OFFSET(宣告利率!$O$2,B71,0))) | J71: =IF(B71="","",IF(C71<16,0,OFFSET(宣告利率!$P$2,B71,0))) | K71: =IF(B71="","",IF(C71<16,OFFSET(宣告利率!$N$2,B71,0)+OFFSET(宣告利率!$U$2,B71,0),OFFSET(宣告利率!$Q$2,B71,0)+OFFSET(宣告利率!$U$2,B71,0))) | L71: =IF(B71="","",IF(C71<16,OFFSET(宣告利率!$N$2,B71,0),OFFSET(宣告利率!$Q$2,B71,0)+OFFSET(宣告利率!$U$2,B71,0))) | M71: =IF(B71="","",IF(OR(ZDIVOPT02=CSWD,ZDIVOPT02=DVAC),OFFSET(宣告利率!$R$2,B71,0),0)) | N71: =IF(B71="","",IF(ZDIVOPT02=CSWD,OFFSET(宣告利率!$S$2,B71,0),IF(ZDIVOPT02=DVAC,OFFSET(宣告利率!$T$2,B71,0),0))) | O71: =IF(B71="","",IF(C71<0,0,OFFSET(宣告利率!$J$2,B71,0)+MAX(OFFSET(宣告利率!$V$2,B71,0,1,3)))) | P71: =IF(B71="","",F71+L71) | Q71: =IF(B71="","",IF(C71=109,0,OFFSET(宣告利率!$AB$2,B71,0)+OFFSET(宣告利率!$AC$2,B71,0))) | R71: =IF(B71="","",P71+IF(ZDIVOPT02=CSWD,M71,0)+IF(ZDIVOPT02=DVAC,N71,0)) | S71: =IF(C71=109,0,IF(B71="","",Q71+IF(ZDIVOPT02=CSWD,M71,0)+IF(ZDIVOPT02=DVAC,N71,0))) | T71: =IF(B71="","",FYPremium+(MIN(PayYear,B71)-1)*CYPremium) | U71: =IF(B71="","",OFFSET(宣告利率!$Y$2,B71,0)) | V71: =IF(B71="","",P71+N71) | W71: =IF(B71="","",V71/D71) | X71: =IF(B71="","",IF(C71=109,0,Q71+N71)) | Y71: =IF(B71="","",IF(OR(B71<PayYear,C71=109),"-",X71/D71)) | Z71: =IF(B71="","",O71/D71) | AA71: =AND(INDIRECT("B"&ROW())>0,MOD(INDIRECT("B"&ROW()),5)=0) -> #VALUE!
B72: =IF(B71="","",IF(C71=險種基本資料!$B$21,"",B71+1)) | C72: =IF(B72="","",Age+B72-1) | D72: =IF(B72="","",OFFSET(宣告利率!$I$2,B72,0)) | E72: =IF(B72="","",OFFSET(宣告利率!$M$2,B72,0)+OFFSET(宣告利率!$K$2,B72,0)) | F72: =IF(B72="","",OFFSET(宣告利率!$L$2,B72,0)+OFFSET(宣告利率!$K$2,B72,0)) | G72: =IF(B72="","",OFFSET(宣告利率!$J$2,B72,0)) | H72: =IF(B72="","",OFFSET(宣告利率!$G$2,B72,0)) | I72: =IF(B72="","",IF(C72<16,0,IF(C72=16,OFFSET(宣告利率!$O$2,B72-1,0),0)+OFFSET(宣告利率!$O$2,B72,0))) | J72: =IF(B72="","",IF(C72<16,0,OFFSET(宣告利率!$P$2,B72,0))) | K72: =IF(B72="","",IF(C72<16,OFFSET(宣告利率!$N$2,B72,0)+OFFSET(宣告利率!$U$2,B72,0),OFFSET(宣告利率!$Q$2,B72,0)+OFFSET(宣告利率!$U$2,B72,0))) | L72: =IF(B72="","",IF(C72<16,OFFSET(宣告利率!$N$2,B72,0),OFFSET(宣告利率!$Q$2,B72,0)+OFFSET(宣告利率!$U$2,B72,0))) | M72: =IF(B72="","",IF(OR(ZDIVOPT02=CSWD,ZDIVOPT02=DVAC),OFFSET(宣告利率!$R$2,B72,0),0)) | N72: =IF(B72="","",IF(ZDIVOPT02=CSWD,OFFSET(宣告利率!$S$2,B72,0),IF(ZDIVOPT02=DVAC,OFFSET(宣告利率!$T$2,B72,0),0))) | O72: =IF(B72="","",IF(C72<0,0,OFFSET(宣告利率!$J$2,B72,0)+MAX(OFFSET(宣告利率!$V$2,B72,0,1,3)))) | P72: =IF(B72="","",F72+L72) | Q72: =IF(B72="","",IF(C72=109,0,OFFSET(宣告利率!$AB$2,B72,0)+OFFSET(宣告利率!$AC$2,B72,0))) | R72: =IF(B72="","",P72+IF(ZDIVOPT02=CSWD,M72,0)+IF(ZDIVOPT02=DVAC,N72,0)) | S72: =IF(C72=109,0,IF(B72="","",Q72+IF(ZDIVOPT02=CSWD,M72,0)+IF(ZDIVOPT02=DVAC,N72,0))) | T72: =IF(B72="","",FYPremium+(MIN(PayYear,B72)-1)*CYPremium) | U72: =IF(B72="","",OFFSET(宣告利率!$Y$2,B72,0)) | V72: =IF(B72="","",P72+N72) | W72: =IF(B72="","",V72/D72) | X72: =IF(B72="","",IF(C72=109,0,Q72+N72)) | Y72: =IF(B72="","",IF(OR(B72<PayYear,C72=109),"-",X72/D72)) | Z72: =IF(B72="","",O72/D72) | AA72: =AND(INDIRECT("B"&ROW())>0,MOD(INDIRECT("B"&ROW()),5)=0) -> #VALUE!
B73: =IF(B72="","",IF(C72=險種基本資料!$B$21,"",B72+1)) | C73: =IF(B73="","",Age+B73-1) | D73: =IF(B73="","",OFFSET(宣告利率!$I$2,B73,0)) | E73: =IF(B73="","",OFFSET(宣告利率!$M$2,B73,0)+OFFSET(宣告利率!$K$2,B73,0)) | F73: =IF(B73="","",OFFSET(宣告利率!$L$2,B73,0)+OFFSET(宣告利率!$K$2,B73,0)) | G73: =IF(B73="","",OFFSET(宣告利率!$J$2,B73,0)) | H73: =IF(B73="","",OFFSET(宣告利率!$G$2,B73,0)) | I73: =IF(B73="","",IF(C73<16,0,IF(C73=16,OFFSET(宣告利率!$O$2,B73-1,0),0)+OFFSET(宣告利率!$O$2,B73,0))) | J73: =IF(B73="","",IF(C73<16,0,OFFSET(宣告利率!$P$2,B73,0))) | K73: =IF(B73="","",IF(C73<16,OFFSET(宣告利率!$N$2,B73,0)+OFFSET(宣告利率!$U$2,B73,0),OFFSET(宣告利率!$Q$2,B73,0)+OFFSET(宣告利率!$U$2,B73,0))) | L73: =IF(B73="","",IF(C73<16,OFFSET(宣告利率!$N$2,B73,0),OFFSET(宣告利率!$Q$2,B73,0)+OFFSET(宣告利率!$U$2,B73,0))) | M73: =IF(B73="","",IF(OR(ZDIVOPT02=CSWD,ZDIVOPT02=DVAC),OFFSET(宣告利率!$R$2,B73,0),0)) | N73: =IF(B73="","",IF(ZDIVOPT02=CSWD,OFFSET(宣告利率!$S$2,B73,0),IF(ZDIVOPT02=DVAC,OFFSET(宣告利率!$T$2,B73,0),0))) | O73: =IF(B73="","",IF(C73<0,0,OFFSET(宣告利率!$J$2,B73,0)+MAX(OFFSET(宣告利率!$V$2,B73,0,1,3)))) | P73: =IF(B73="","",F73+L73) | Q73: =IF(B73="","",IF(C73=109,0,OFFSET(宣告利率!$AB$2,B73,0)+OFFSET(宣告利率!$AC$2,B73,0))) | R73: =IF(B73="","",P73+IF(ZDIVOPT02=CSWD,M73,0)+IF(ZDIVOPT02=DVAC,N73,0)) | S73: =IF(C73=109,0,IF(B73="","",Q73+IF(ZDIVOPT02=CSWD,M73,0)+IF(ZDIVOPT02=DVAC,N73,0))) | T73: =IF(B73="","",FYPremium+(MIN(PayYear,B73)-1)*CYPremium) | U73: =IF(B73="","",OFFSET(宣告利率!$Y$2,B73,0)) | V73: =IF(B73="","",P73+N73) | W73: =IF(B73="","",V73/D73) | X73: =IF(B73="","",IF(C73=109,0,Q73+N73)) | Y73: =IF(B73="","",IF(OR(B73<PayYear,C73=109),"-",X73/D73)) | Z73: =IF(B73="","",O73/D73) | AA73: =AND(INDIRECT("B"&ROW())>0,MOD(INDIRECT("B"&ROW()),5)=0) -> #VALUE!
B74: =IF(B73="","",IF(C73=險種基本資料!$B$21,"",B73+1)) | C74: =IF(B74="","",Age+B74-1) | D74: =IF(B74="","",OFFSET(宣告利率!$I$2,B74,0)) | E74: =IF(B74="","",OFFSET(宣告利率!$M$2,B74,0)+OFFSET(宣告利率!$K$2,B74,0)) | F74: =IF(B74="","",OFFSET(宣告利率!$L$2,B74,0)+OFFSET(宣告利率!$K$2,B74,0)) | G74: =IF(B74="","",OFFSET(宣告利率!$J$2,B74,0)) | H74: =IF(B74="","",OFFSET(宣告利率!$G$2,B74,0)) | I74: =IF(B74="","",IF(C74<16,0,IF(C74=16,OFFSET(宣告利率!$O$2,B74-1,0),0)+OFFSET(宣告利率!$O$2,B74,0))) | J74: =IF(B74="","",IF(C74<16,0,OFFSET(宣告利率!$P$2,B74,0))) | K74: =IF(B74="","",IF(C74<16,OFFSET(宣告利率!$N$2,B74,0)+OFFSET(宣告利率!$U$2,B74,0),OFFSET(宣告利率!$Q$2,B74,0)+OFFSET(宣告利率!$U$2,B74,0))) | L74: =IF(B74="","",IF(C74<16,OFFSET(宣告利率!$N$2,B74,0),OFFSET(宣告利率!$Q$2,B74,0)+OFFSET(宣告利率!$U$2,B74,0))) | M74: =IF(B74="","",IF(OR(ZDIVOPT02=CSWD,ZDIVOPT02=DVAC),OFFSET(宣告利率!$R$2,B74,0),0)) | N74: =IF(B74="","",IF(ZDIVOPT02=CSWD,OFFSET(宣告利率!$S$2,B74,0),IF(ZDIVOPT02=DVAC,OFFSET(宣告利率!$T$2,B74,0),0))) | O74: =IF(B74="","",IF(C74<0,0,OFFSET(宣告利率!$J$2,B74,0)+MAX(OFFSET(宣告利率!$V$2,B74,0,1,3)))) | P74: =IF(B74="","",F74+L74) | Q74: =IF(B74="","",IF(C74=109,0,OFFSET(宣告利率!$AB$2,B74,0)+OFFSET(宣告利率!$AC$2,B74,0))) | R74: =IF(B74="","",P74+IF(ZDIVOPT02=CSWD,M74,0)+IF(ZDIVOPT02=DVAC,N74,0)) | S74: =IF(C74=109,0,IF(B74="","",Q74+IF(ZDIVOPT02=CSWD,M74,0)+IF(ZDIVOPT02=DVAC,N74,0))) | T74: =IF(B74="","",FYPremium+(MIN(PayYear,B74)-1)*CYPremium) | U74: =IF(B74="","",OFFSET(宣告利率!$Y$2,B74,0)) | V74: =IF(B74="","",P74+N74) | W74: =IF(B74="","",V74/D74) | X74: =IF(B74="","",IF(C74=109,0,Q74+N74)) | Y74: =IF(B74="","",IF(OR(B74<PayYear,C74=109),"-",X74/D74)) | Z74: =IF(B74="","",O74/D74) | AA74: =AND(INDIRECT("B"&ROW())>0,MOD(INDIRECT("B"&ROW()),5)=0) -> #VALUE!
B75: =IF(B74="","",IF(C74=險種基本資料!$B$21,"",B74+1)) | C75: =IF(B75="","",Age+B75-1) | D75: =IF(B75="","",OFFSET(宣告利率!$I$2,B75,0)) | E75: =IF(B75="","",OFFSET(宣告利率!$M$2,B75,0)+OFFSET(宣告利率!$K$2,B75,0)) | F75: =IF(B75="","",OFFSET(宣告利率!$L$2,B75,0)+OFFSET(宣告利率!$K$2,B75,0)) | G75: =IF(B75="","",OFFSET(宣告利率!$J$2,B75,0)) | H75: =IF(B75="","",OFFSET(宣告利率!$G$2,B75,0)) | I75: =IF(B75="","",IF(C75<16,0,IF(C75=16,OFFSET(宣告利率!$O$2,B75-1,0),0)+OFFSET(宣告利率!$O$2,B75,0))) | J75: =IF(B75="","",IF(C75<16,0,OFFSET(宣告利率!$P$2,B75,0))) | K75: =IF(B75="","",IF(C75<16,OFFSET(宣告利率!$N$2,B75,0)+OFFSET(宣告利率!$U$2,B75,0),OFFSET(宣告利率!$Q$2,B75,0)+OFFSET(宣告利率!$U$2,B75,0))) | L75: =IF(B75="","",IF(C75<16,OFFSET(宣告利率!$N$2,B75,0),OFFSET(宣告利率!$Q$2,B75,0)+OFFSET(宣告利率!$U$2,B75,0))) | M75: =IF(B75="","",IF(OR(ZDIVOPT02=CSWD,ZDIVOPT02=DVAC),OFFSET(宣告利率!$R$2,B75,0),0)) | N75: =IF(B75="","",IF(ZDIVOPT02=CSWD,OFFSET(宣告利率!$S$2,B75,0),IF(ZDIVOPT02=DVAC,OFFSET(宣告利率!$T$2,B75,0),0))) | O75: =IF(B75="","",IF(C75<0,0,OFFSET(宣告利率!$J$2,B75,0)+MAX(OFFSET(宣告利率!$V$2,B75,0,1,3)))) | P75: =IF(B75="","",F75+L75) | Q75: =IF(B75="","",IF(C75=109,0,OFFSET(宣告利率!$AB$2,B75,0)+OFFSET(宣告利率!$AC$2,B75,0))) | R75: =IF(B75="","",P75+IF(ZDIVOPT02=CSWD,M75,0)+IF(ZDIVOPT02=DVAC,N75,0)) | S75: =IF(C75=109,0,IF(B75="","",Q75+IF(ZDIVOPT02=CSWD,M75,0)+IF(ZDIVOPT02=DVAC,N75,0))) | T75: =IF(B75="","",FYPremium+(MIN(PayYear,B75)-1)*CYPremium) | U75: =IF(B75="","",OFFSET(宣告利率!$Y$2,B75,0)) | V75: =IF(B75="","",P75+N75) | W75: =IF(B75="","",V75/D75) | X75: =IF(B75="","",IF(C75=109,0,Q75+N75)) | Y75: =IF(B75="","",IF(OR(B75<PayYear,C75=109),"-",X75/D75)) | Z75: =IF(B75="","",O75/D75) | AA75: =AND(INDIRECT("B"&ROW())>0,MOD(INDIRECT("B"&ROW()),5)=0) -> #VALUE!
B76: =IF(B75="","",IF(C75=險種基本資料!$B$21,"",B75+1)) | C76: =IF(B76="","",Age+B76-1) | D76: =IF(B76="","",OFFSET(宣告利率!$I$2,B76,0)) | E76: =IF(B76="","",OFFSET(宣告利率!$M$2,B76,0)+OFFSET(宣告利率!$K$2,B76,0)) | F76: =IF(B76="","",OFFSET(宣告利率!$L$2,B76,0)+OFFSET(宣告利率!$K$2,B76,0)) | G76: =IF(B76="","",OFFSET(宣告利率!$J$2,B76,0)) | H76: =IF(B76="","",OFFSET(宣告利率!$G$2,B76,0)) | I76: =IF(B76="","",IF(C76<16,0,IF(C76=16,OFFSET(宣告利率!$O$2,B76-1,0),0)+OFFSET(宣告利率!$O$2,B76,0))) | J76: =IF(B76="","",IF(C76<16,0,OFFSET(宣告利率!$P$2,B76,0))) | K76: =IF(B76="","",IF(C76<16,OFFSET(宣告利率!$N$2,B76,0)+OFFSET(宣告利率!$U$2,B76,0),OFFSET(宣告利率!$Q$2,B76,0)+OFFSET(宣告利率!$U$2,B76,0))) | L76: =IF(B76="","",IF(C76<16,OFFSET(宣告利率!$N$2,B76,0),OFFSET(宣告利率!$Q$2,B76,0)+OFFSET(宣告利率!$U$2,B76,0))) | M76: =IF(B76="","",IF(OR(ZDIVOPT02=CSWD,ZDIVOPT02=DVAC),OFFSET(宣告利率!$R$2,B76,0),0)) | N76: =IF(B76="","",IF(ZDIVOPT02=CSWD,OFFSET(宣告利率!$S$2,B76,0),IF(ZDIVOPT02=DVAC,OFFSET(宣告利率!$T$2,B76,0),0))) | O76: =IF(B76="","",IF(C76<0,0,OFFSET(宣告利率!$J$2,B76,0)+MAX(OFFSET(宣告利率!$V$2,B76,0,1,3)))) | P76: =IF(B76="","",F76+L76) | Q76: =IF(B76="","",IF(C76=109,0,OFFSET(宣告利率!$AB$2,B76,0)+OFFSET(宣告利率!$AC$2,B76,0))) | R76: =IF(B76="","",P76+IF(ZDIVOPT02=CSWD,M76,0)+IF(ZDIVOPT02=DVAC,N76,0)) | S76: =IF(C76=109,0,IF(B76="","",Q76+IF(ZDIVOPT02=CSWD,M76,0)+IF(ZDIVOPT02=DVAC,N76,0))) | T76: =IF(B76="","",FYPremium+(MIN(PayYear,B76)-1)*CYPremium) | U76: =IF(B76="","",OFFSET(宣告利率!$Y$2,B76,0)) | V76: =IF(B76="","",P76+N76) | W76: =IF(B76="","",V76/D76) | X76: =IF(B76="","",IF(C76=109,0,Q76+N76)) | Y76: =IF(B76="","",IF(OR(B76<PayYear,C76=109),"-",X76/D76)) | Z76: =IF(B76="","",O76/D76) | AA76: =AND(INDIRECT("B"&ROW())>0,MOD(INDIRECT("B"&ROW()),5)=0) -> #VALUE!
B77: =IF(B76="","",IF(C76=險種基本資料!$B$21,"",B76+1)) | C77: =IF(B77="","",Age+B77-1) | D77: =IF(B77="","",OFFSET(宣告利率!$I$2,B77,0)) | E77: =IF(B77="","",OFFSET(宣告利率!$M$2,B77,0)+OFFSET(宣告利率!$K$2,B77,0)) | F77: =IF(B77="","",OFFSET(宣告利率!$L$2,B77,0)+OFFSET(宣告利率!$K$2,B77,0)) | G77: =IF(B77="","",OFFSET(宣告利率!$J$2,B77,0)) | H77: =IF(B77="","",OFFSET(宣告利率!$G$2,B77,0)) | I77: =IF(B77="","",IF(C77<16,0,IF(C77=16,OFFSET(宣告利率!$O$2,B77-1,0),0)+OFFSET(宣告利率!$O$2,B77,0))) | J77: =IF(B77="","",IF(C77<16,0,OFFSET(宣告利率!$P$2,B77,0))) | K77: =IF(B77="","",IF(C77<16,OFFSET(宣告利率!$N$2,B77,0)+OFFSET(宣告利率!$U$2,B77,0),OFFSET(宣告利率!$Q$2,B77,0)+OFFSET(宣告利率!$U$2,B77,0))) | L77: =IF(B77="","",IF(C77<16,OFFSET(宣告利率!$N$2,B77,0),OFFSET(宣告利率!$Q$2,B77,0)+OFFSET(宣告利率!$U$2,B77,0))) | M77: =IF(B77="","",IF(OR(ZDIVOPT02=CSWD,ZDIVOPT02=DVAC),OFFSET(宣告利率!$R$2,B77,0),0)) | N77: =IF(B77="","",IF(ZDIVOPT02=CSWD,OFFSET(宣告利率!$S$2,B77,0),IF(ZDIVOPT02=DVAC,OFFSET(宣告利率!$T$2,B77,0),0))) | O77: =IF(B77="","",IF(C77<0,0,OFFSET(宣告利率!$J$2,B77,0)+MAX(OFFSET(宣告利率!$V$2,B77,0,1,3)))) | P77: =IF(B77="","",F77+L77) | Q77: =IF(B77="","",IF(C77=109,0,OFFSET(宣告利率!$AB$2,B77,0)+OFFSET(宣告利率!$AC$2,B77,0))) | R77: =IF(B77="","",P77+IF(ZDIVOPT02=CSWD,M77,0)+IF(ZDIVOPT02=DVAC,N77,0)) | S77: =IF(C77=109,0,IF(B77="","",Q77+IF(ZDIVOPT02=CSWD,M77,0)+IF(ZDIVOPT02=DVAC,N77,0))) | T77: =IF(B77="","",FYPremium+(MIN(PayYear,B77)-1)*CYPremium) | U77: =IF(B77="","",OFFSET(宣告利率!$Y$2,B77,0)) | V77: =IF(B77="","",P77+N77) | W77: =IF(B77="","",V77/D77) | X77: =IF(B77="","",IF(C77=109,0,Q77+N77)) | Y77: =IF(B77="","",IF(OR(B77<PayYear,C77=109),"-",X77/D77)) | Z77: =IF(B77="","",O77/D77) | AA77: =AND(INDIRECT("B"&ROW())>0,MOD(INDIRECT("B"&ROW()),5)=0) -> #VALUE!
B78: =IF(B77="","",IF(C77=險種基本資料!$B$21,"",B77+1)) | C78: =IF(B78="","",Age+B78-1) | D78: =IF(B78="","",OFFSET(宣告利率!$I$2,B78,0)) | E78: =IF(B78="","",OFFSET(宣告利率!$M$2,B78,0)+OFFSET(宣告利率!$K$2,B78,0)) | F78: =IF(B78="","",OFFSET(宣告利率!$L$2,B78,0)+OFFSET(宣告利率!$K$2,B78,0)) | G78: =IF(B78="","",OFFSET(宣告利率!$J$2,B78,0)) | H78: =IF(B78="","",OFFSET(宣告利率!$G$2,B78,0)) | I78: =IF(B78="","",IF(C78<16,0,IF(C78=16,OFFSET(宣告利率!$O$2,B78-1,0),0)+OFFSET(宣告利率!$O$2,B78,0))) | J78: =IF(B78="","",IF(C78<16,0,OFFSET(宣告利率!$P$2,B78,0))) | K78: =IF(B78="","",IF(C78<16,OFFSET(宣告利率!$N$2,B78,0)+OFFSET(宣告利率!$U$2,B78,0),OFFSET(宣告利率!$Q$2,B78,0)+OFFSET(宣告利率!$U$2,B78,0))) | L78: =IF(B78="","",IF(C78<16,OFFSET(宣告利率!$N$2,B78,0),OFFSET(宣告利率!$Q$2,B78,0)+OFFSET(宣告利率!$U$2,B78,0))) | M78: =IF(B78="","",IF(OR(ZDIVOPT02=CSWD,ZDIVOPT02=DVAC),OFFSET(宣告利率!$R$2,B78,0),0)) | N78: =IF(B78="","",IF(ZDIVOPT02=CSWD,OFFSET(宣告利率!$S$2,B78,0),IF(ZDIVOPT02=DVAC,OFFSET(宣告利率!$T$2,B78,0),0))) | O78: =IF(B78="","",IF(C78<0,0,OFFSET(宣告利率!$J$2,B78,0)+MAX(OFFSET(宣告利率!$V$2,B78,0,1,3)))) | P78: =IF(B78="","",F78+L78) | Q78: =IF(B78="","",IF(C78=109,0,OFFSET(宣告利率!$AB$2,B78,0)+OFFSET(宣告利率!$AC$2,B78,0))) | R78: =IF(B78="","",P78+IF(ZDIVOPT02=CSWD,M78,0)+IF(ZDIVOPT02=DVAC,N78,0)) | S78: =IF(C78=109,0,IF(B78="","",Q78+IF(ZDIVOPT02=CSWD,M78,0)+IF(ZDIVOPT02=DVAC,N78,0))) | T78: =IF(B78="","",FYPremium+(MIN(PayYear,B78)-1)*CYPremium) | U78: =IF(B78="","",OFFSET(宣告利率!$Y$2,B78,0)) | V78: =IF(B78="","",P78+N78) | W78: =IF(B78="","",V78/D78) | X78: =IF(B78="","",IF(C78=109,0,Q78+N78)) | Y78: =IF(B78="","",IF(OR(B78<PayYear,C78=109),"-",X78/D78)) | Z78: =IF(B78="","",O78/D78) | AA78: =AND(INDIRECT("B"&ROW())>0,MOD(INDIRECT("B"&ROW()),5)=0) -> #VALUE!
... B90: =IF(B89="","",IF(C89=險種基本資料!$B$21,"",B89+1)) | C90: =IF(B90="","",Age+B90-1) | D90: =IF(B90="","",OFFSET(宣告利率!$I$2,B90,0)) | E90: =IF(B90="","",OFFSET(宣告利率!$M$2,B90,0)+OFFSET(宣告利率!$K$2,B90,0)) | F90: =IF(B90="","",OFFSET(宣告利率!$L$2,B90,0)+OFFSET(宣告利率!$K$2,B90,0)) | G90: =IF(B90="","",OFFSET(宣告利率!$J$2,B90,0)) | H90: =IF(B90="","",OFFSET(宣告利率!$G$2,B90,0)) | I90: =IF(B90="","",IF(C90<16,0,IF(C90=16,OFFSET(宣告利率!$O$2,B90-1,0),0)+OFFSET(宣告利率!$O$2,B90,0))) | J90: =IF(B90="","",IF(C90<16,0,OFFSET(宣告利率!$P$2,B90,0))) | K90: =IF(B90="","",IF(C90<16,OFFSET(宣告利率!$N$2,B90,0)+OFFSET(宣告利率!$U$2,B90,0),OFFSET(宣告利率!$Q$2,B90,0)+OFFSET(宣告利率!$U$2,B90,0))) | L90: =IF(B90="","",IF(C90<16,OFFSET(宣告利率!$N$2,B90,0),OFFSET(宣告利率!$Q$2,B90,0)+OFFSET(宣告利率!$U$2,B90,0))) | M90: =IF(B90="","",IF(OR(ZDIVOPT02=CSWD,ZDIVOPT02=DVAC),OFFSET(宣告利率!$R$2,B90,0),0)) | N90: =IF(B90="","",IF(ZDIVOPT02=CSWD,OFFSET(宣告利率!$S$2,B90,0),IF(ZDIVOPT02=DVAC,OFFSET(宣告利率!$T$2,B90,0),0))) | O90: =IF(B90="","",IF(C90<0,0,OFFSET(宣告利率!$J$2,B90,0)+MAX(OFFSET(宣告利率!$V$2,B90,0,1,3)))) | P90: =IF(B90="","",F90+L90) | Q90: =IF(B90="","",IF(C90=109,0,OFFSET(宣告利率!$AB$2,B90,0)+OFFSET(宣告利率!$AC$2,B90,0))) | R90: =IF(B90="","",P90+IF(ZDIVOPT02=CSWD,M90,0)+IF(ZDIVOPT02=DVAC,N90,0)) | S90: =IF(C90=109,0,IF(B90="","",Q90+IF(ZDIVOPT02=CSWD,M90,0)+IF(ZDIVOPT02=DVAC,N90,0))) | T90: =IF(B90="","",FYPremium+(MIN(PayYear,B90)-1)*CYPremium) | U90: =IF(B90="","",OFFSET(宣告利率!$Y$2,B90,0)) | V90: =IF(B90="","",P90+N90) | W90: =IF(B90="","",V90/D90) | X90: =IF(B90="","",IF(C90=109,0,Q90+N90)) | Y90: =IF(B90="","",IF(OR(B90<PayYear,C90=109),"-",X90/D90)) | Z90: =IF(B90="","",O90/D90) | AA90: =AND(INDIRECT("B"&ROW())>0,MOD(INDIRECT("B"&ROW()),5)=0) -> #VALUE!
B91: =B17 -> 保單 年度 (末) | C91: =C17 -> 保險 年齡 | D91: =D17 -> 累積所繳保險費 (A) | E91: =E17 -> 基本保險金額對應之保單價值準備金 【含祝壽保險金】 | F91: =F17 -> 基本保險金額 對應之現金價值 【含祝壽保險金】 (B) | G91: =G17 -> 基本保險金額 對應之壽險保障 (身故保險金) | J91: =J17 -> 假設投保後未來各保單年度宣告利率為4.35% (下表為預估假設值) | R91: =R17 -> 年度末終止契約時合計可領取之金額(含增值回饋分享金) (F) | S91: =S17 -> 次年度期初終止契約時合計可領取之金額(含增值回饋分享金) (H)=(G) | T91: =T17 -> 累積 應繳保費 | U91: =U17 -> 期末保單價值準備金(含基本保險金額、累計增加保險金額) 【含祝壽保險金】 | V91: =V17 -> (E)+(F) | W91: =W17 -> ((E)+(F))/(A) | X91: =X17 -> (G)+(E) | Y91: =Y17 -> ((G)+(E))/(A) | Z91: =Z17 -> (I)/(A) | AA91: =AND(INDIRECT("B"&ROW())>0,MOD(INDIRECT("B"&ROW()),5)=0) -> #VALUE!
B92: =B18 -> 0 | C92: =C18 -> 0 | D92: =D18 -> 0 | E92: =E18 -> 0 | F92: =F18 -> 0 | G92: =G18 -> 0 | H92: =H18 -> 增值回饋分享金 | I92: =I18 -> 選擇以繳清保險方式增加保險金額 | ... Q92: =Q18 -> 0 | T92: =T18 -> 0 | U92: =U18 -> 0 | V92: =V18 -> 0 | W92: =W18 -> 0 | X92: =X18 -> 0 | Y92: =Y18 -> 0 | AA92: =AND(INDIRECT("B"&ROW())>0,MOD(INDIRECT("B"&ROW()),5)=0) -> FALSE
B93: =B19 -> 0 | C93: =C19 -> 0 | D93: =D19 -> 0 | E93: =E19 -> 0 | F93: =F19 -> 0 | G93: =G19 -> 0 | H93: =H19 -> 0 | I93: =I19 -> 增額繳清保險金額 | ... Q93: =Q19 -> 次年度期初 現金價值 (G) | T93: =T19 -> 0 | U93: =U19 -> 0 | V93: =V19 -> 0 | W93: =W19 -> 0 | X93: =X19 -> 0 | Y93: =Y19 -> 0 | AA93: =AND(INDIRECT("B"&ROW())>0,MOD(INDIRECT("B"&ROW()),5)=0) -> FALSE
B94: =IF(B90="","",IF(C90=險種基本資料!$B$21,"",B90+1)) | C94: =IF(B94="","",Age+B94-1) | D94: =IF(B94="","",OFFSET(宣告利率!$I$2,B94,0)) | E94: =IF(B94="","",OFFSET(宣告利率!$M$2,B94,0)+OFFSET(宣告利率!$K$2,B94,0)) | F94: =IF(B94="","",OFFSET(宣告利率!$L$2,B94,0)+OFFSET(宣告利率!$K$2,B94,0)) | G94: =IF(B94="","",OFFSET(宣告利率!$J$2,B94,0)) | H94: =IF(B94="","",OFFSET(宣告利率!$G$2,B94,0)) | I94: =IF(B94="","",IF(C94<16,0,IF(C94=16,OFFSET(宣告利率!$O$2,B94-1,0),0)+OFFSET(宣告利率!$O$2,B94,0))) | J94: =IF(B94="","",IF(C94<16,0,OFFSET(宣告利率!$P$2,B94,0))) | K94: =IF(B94="","",IF(C94<16,OFFSET(宣告利率!$N$2,B94,0)+OFFSET(宣告利率!$U$2,B94,0),OFFSET(宣告利率!$Q$2,B94,0)+OFFSET(宣告利率!$U$2,B94,0))) | L94: =IF(B94="","",IF(C94<16,OFFSET(宣告利率!$N$2,B94,0),OFFSET(宣告利率!$Q$2,B94,0)+OFFSET(宣告利率!$U$2,B94,0))) | M94: =IF(B94="","",IF(OR(ZDIVOPT02=CSWD,ZDIVOPT02=DVAC),OFFSET(宣告利率!$R$2,B94,0),0)) | N94: =IF(B94="","",IF(ZDIVOPT02=CSWD,OFFSET(宣告利率!$S$2,B94,0),IF(ZDIVOPT02=DVAC,OFFSET(宣告利率!$T$2,B94,0),0))) | O94: =IF(B94="","",IF(C94<0,0,OFFSET(宣告利率!$J$2,B94,0)+MAX(OFFSET(宣告利率!$V$2,B94,0,1,3)))) | P94: =IF(B94="","",F94+L94) | Q94: =IF(B94="","",IF(C94=109,0,OFFSET(宣告利率!$AB$2,B94,0)+OFFSET(宣告利率!$AC$2,B94,0))) | R94: =IF(B94="","",P94+IF(ZDIVOPT02=CSWD,M94,0)+IF(ZDIVOPT02=DVAC,N94,0)) | S94: =IF(C94=109,0,IF(B94="","",Q94+IF(ZDIVOPT02=CSWD,M94,0)+IF(ZDIVOPT02=DVAC,N94,0))) | T94: =IF(B94="","",FYPremium+(MIN(PayYear,B94)-1)*CYPremium) | U94: =IF(B94="","",OFFSET(宣告利率!$Y$2,B94,0)) | V94: =IF(B94="","",P94+N94) | W94: =IF(B94="","",V94/D94) | X94: =IF(B94="","",IF(C94=109,0,Q94+N94)) | Y94: =IF(B94="","",IF(OR(B94<PayYear,C94=109),"-",X94/D94)) | Z94: =IF(B94="","",O94/D94) | AA94: =AND(INDIRECT("B"&ROW())>0,MOD(INDIRECT("B"&ROW()),5)=0) -> #VALUE!
B95: =IF(B94="","",IF(C94=險種基本資料!$B$21,"",B94+1)) | C95: =IF(B95="","",Age+B95-1) | D95: =IF(B95="","",OFFSET(宣告利率!$I$2,B95,0)) | E95: =IF(B95="","",OFFSET(宣告利率!$M$2,B95,0)+OFFSET(宣告利率!$K$2,B95,0)) | F95: =IF(B95="","",OFFSET(宣告利率!$L$2,B95,0)+OFFSET(宣告利率!$K$2,B95,0)) | G95: =IF(B95="","",OFFSET(宣告利率!$J$2,B95,0)) | H95: =IF(B95="","",OFFSET(宣告利率!$G$2,B95,0)) | I95: =IF(B95="","",IF(C95<16,0,IF(C95=16,OFFSET(宣告利率!$O$2,B95-1,0),0)+OFFSET(宣告利率!$O$2,B95,0))) | J95: =IF(B95="","",IF(C95<16,0,OFFSET(宣告利率!$P$2,B95,0))) | K95: =IF(B95="","",IF(C95<16,OFFSET(宣告利率!$N$2,B95,0)+OFFSET(宣告利率!$U$2,B95,0),OFFSET(宣告利率!$Q$2,B95,0)+OFFSET(宣告利率!$U$2,B95,0))) | L95: =IF(B95="","",IF(C95<16,OFFSET(宣告利率!$N$2,B95,0),OFFSET(宣告利率!$Q$2,B95,0)+OFFSET(宣告利率!$U$2,B95,0))) | M95: =IF(B95="","",IF(OR(ZDIVOPT02=CSWD,ZDIVOPT02=DVAC),OFFSET(宣告利率!$R$2,B95,0),0)) | N95: =IF(B95="","",IF(ZDIVOPT02=CSWD,OFFSET(宣告利率!$S$2,B95,0),IF(ZDIVOPT02=DVAC,OFFSET(宣告利率!$T$2,B95,0),0))) | O95: =IF(B95="","",IF(C95<0,0,OFFSET(宣告利率!$J$2,B95,0)+MAX(OFFSET(宣告利率!$V$2,B95,0,1,3)))) | P95: =IF(B95="","",F95+L95) | Q95: =IF(B95="","",IF(C95=109,0,OFFSET(宣告利率!$AB$2,B95,0)+OFFSET(宣告利率!$AC$2,B95,0))) | R95: =IF(B95="","",P95+IF(ZDIVOPT02=CSWD,M95,0)+IF(ZDIVOPT02=DVAC,N95,0)) | S95: =IF(C95=109,0,IF(B95="","",Q95+IF(ZDIVOPT02=CSWD,M95,0)+IF(ZDIVOPT02=DVAC,N95,0))) | T95: =IF(B95="","",FYPremium+(MIN(PayYear,B95)-1)*CYPremium) | U95: =IF(B95="","",OFFSET(宣告利率!$Y$2,B95,0)) | V95: =IF(B95="","",P95+N95) | W95: =IF(B95="","",V95/D95) | X95: =IF(B95="","",IF(C95=109,0,Q95+N95)) | Y95: =IF(B95="","",IF(OR(B95<PayYear,C95=109),"-",X95/D95)) | Z95: =IF(B95="","",O95/D95) | AA95: =AND(INDIRECT("B"&ROW())>0,MOD(INDIRECT("B"&ROW()),5)=0) -> #VALUE!
B96: =IF(B95="","",IF(C95=險種基本資料!$B$21,"",B95+1)) | C96: =IF(B96="","",Age+B96-1) | D96: =IF(B96="","",OFFSET(宣告利率!$I$2,B96,0)) | E96: =IF(B96="","",OFFSET(宣告利率!$M$2,B96,0)+OFFSET(宣告利率!$K$2,B96,0)) | F96: =IF(B96="","",OFFSET(宣告利率!$L$2,B96,0)+OFFSET(宣告利率!$K$2,B96,0)) | G96: =IF(B96="","",OFFSET(宣告利率!$J$2,B96,0)) | H96: =IF(B96="","",OFFSET(宣告利率!$G$2,B96,0)) | I96: =IF(B96="","",IF(C96<16,0,IF(C96=16,OFFSET(宣告利率!$O$2,B96-1,0),0)+OFFSET(宣告利率!$O$2,B96,0))) | J96: =IF(B96="","",IF(C96<16,0,OFFSET(宣告利率!$P$2,B96,0))) | K96: =IF(B96="","",IF(C96<16,OFFSET(宣告利率!$N$2,B96,0)+OFFSET(宣告利率!$U$2,B96,0),OFFSET(宣告利率!$Q$2,B96,0)+OFFSET(宣告利率!$U$2,B96,0))) | L96: =IF(B96="","",IF(C96<16,OFFSET(宣告利率!$N$2,B96,0),OFFSET(宣告利率!$Q$2,B96,0)+OFFSET(宣告利率!$U$2,B96,0))) | M96: =IF(B96="","",IF(OR(ZDIVOPT02=CSWD,ZDIVOPT02=DVAC),OFFSET(宣告利率!$R$2,B96,0),0)) | N96: =IF(B96="","",IF(ZDIVOPT02=CSWD,OFFSET(宣告利率!$S$2,B96,0),IF(ZDIVOPT02=DVAC,OFFSET(宣告利率!$T$2,B96,0),0))) | O96: =IF(B96="","",IF(C96<0,0,OFFSET(宣告利率!$J$2,B96,0)+MAX(OFFSET(宣告利率!$V$2,B96,0,1,3)))) | P96: =IF(B96="","",F96+L96) | Q96: =IF(B96="","",IF(C96=109,0,OFFSET(宣告利率!$AB$2,B96,0)+OFFSET(宣告利率!$AC$2,B96,0))) | R96: =IF(B96="","",P96+IF(ZDIVOPT02=CSWD,M96,0)+IF(ZDIVOPT02=DVAC,N96,0)) | S96: =IF(C96=109,0,IF(B96="","",Q96+IF(ZDIVOPT02=CSWD,M96,0)+IF(ZDIVOPT02=DVAC,N96,0))) | T96: =IF(B96="","",FYPremium+(MIN(PayYear,B96)-1)*CYPremium) | U96: =IF(B96="","",OFFSET(宣告利率!$Y$2,B96,0)) | V96: =IF(B96="","",P96+N96) | W96: =IF(B96="","",V96/D96) | X96: =IF(B96="","",IF(C96=109,0,Q96+N96)) | Y96: =IF(B96="","",IF(OR(B96<PayYear,C96=109),"-",X96/D96)) | Z96: =IF(B96="","",O96/D96) | AA96: =AND(INDIRECT("B"&ROW())>0,MOD(INDIRECT("B"&ROW()),5)=0) -> #VALUE!
B97: =IF(B96="","",IF(C96=險種基本資料!$B$21,"",B96+1)) | C97: =IF(B97="","",Age+B97-1) | D97: =IF(B97="","",OFFSET(宣告利率!$I$2,B97,0)) | E97: =IF(B97="","",OFFSET(宣告利率!$M$2,B97,0)+OFFSET(宣告利率!$K$2,B97,0)) | F97: =IF(B97="","",OFFSET(宣告利率!$L$2,B97,0)+OFFSET(宣告利率!$K$2,B97,0)) | G97: =IF(B97="","",OFFSET(宣告利率!$J$2,B97,0)) | H97: =IF(B97="","",OFFSET(宣告利率!$G$2,B97,0)) | I97: =IF(B97="","",IF(C97<16,0,IF(C97=16,OFFSET(宣告利率!$O$2,B97-1,0),0)+OFFSET(宣告利率!$O$2,B97,0))) | J97: =IF(B97="","",IF(C97<16,0,OFFSET(宣告利率!$P$2,B97,0))) | K97: =IF(B97="","",IF(C97<16,OFFSET(宣告利率!$N$2,B97,0)+OFFSET(宣告利率!$U$2,B97,0),OFFSET(宣告利率!$Q$2,B97,0)+OFFSET(宣告利率!$U$2,B97,0))) | L97: =IF(B97="","",IF(C97<16,OFFSET(宣告利率!$N$2,B97,0),OFFSET(宣告利率!$Q$2,B97,0)+OFFSET(宣告利率!$U$2,B97,0))) | M97: =IF(B97="","",IF(OR(ZDIVOPT02=CSWD,ZDIVOPT02=DVAC),OFFSET(宣告利率!$R$2,B97,0),0)) | N97: =IF(B97="","",IF(ZDIVOPT02=CSWD,OFFSET(宣告利率!$S$2,B97,0),IF(ZDIVOPT02=DVAC,OFFSET(宣告利率!$T$2,B97,0),0))) | O97: =IF(B97="","",IF(C97<0,0,OFFSET(宣告利率!$J$2,B97,0)+MAX(OFFSET(宣告利率!$V$2,B97,0,1,3)))) | P97: =IF(B97="","",F97+L97) | Q97: =IF(B97="","",IF(C97=109,0,OFFSET(宣告利率!$AB$2,B97,0)+OFFSET(宣告利率!$AC$2,B97,0))) | R97: =IF(B97="","",P97+IF(ZDIVOPT02=CSWD,M97,0)+IF(ZDIVOPT02=DVAC,N97,0)) | S97: =IF(C97=109,0,IF(B97="","",Q97+IF(ZDIVOPT02=CSWD,M97,0)+IF(ZDIVOPT02=DVAC,N97,0))) | T97: =IF(B97="","",FYPremium+(MIN(PayYear,B97)-1)*CYPremium) | U97: =IF(B97="","",OFFSET(宣告利率!$Y$2,B97,0)) | V97: =IF(B97="","",P97+N97) | W97: =IF(B97="","",V97/D97) | X97: =IF(B97="","",IF(C97=109,0,Q97+N97)) | Y97: =IF(B97="","",IF(OR(B97<PayYear,C97=109),"-",X97/D97)) | Z97: =IF(B97="","",O97/D97) | AA97: =AND(INDIRECT("B"&ROW())>0,MOD(INDIRECT("B"&ROW()),5)=0) -> #VALUE!
B98: =IF(B97="","",IF(C97=險種基本資料!$B$21,"",B97+1)) | C98: =IF(B98="","",Age+B98-1) | D98: =IF(B98="","",OFFSET(宣告利率!$I$2,B98,0)) | E98: =IF(B98="","",OFFSET(宣告利率!$M$2,B98,0)+OFFSET(宣告利率!$K$2,B98,0)) | F98: =IF(B98="","",OFFSET(宣告利率!$L$2,B98,0)+OFFSET(宣告利率!$K$2,B98,0)) | G98: =IF(B98="","",OFFSET(宣告利率!$J$2,B98,0)) | H98: =IF(B98="","",OFFSET(宣告利率!$G$2,B98,0)) | I98: =IF(B98="","",IF(C98<16,0,IF(C98=16,OFFSET(宣告利率!$O$2,B98-1,0),0)+OFFSET(宣告利率!$O$2,B98,0))) | J98: =IF(B98="","",IF(C98<16,0,OFFSET(宣告利率!$P$2,B98,0))) | K98: =IF(B98="","",IF(C98<16,OFFSET(宣告利率!$N$2,B98,0)+OFFSET(宣告利率!$U$2,B98,0),OFFSET(宣告利率!$Q$2,B98,0)+OFFSET(宣告利率!$U$2,B98,0))) | L98: =IF(B98="","",IF(C98<16,OFFSET(宣告利率!$N$2,B98,0),OFFSET(宣告利率!$Q$2,B98,0)+OFFSET(宣告利率!$U$2,B98,0))) | M98: =IF(B98="","",IF(OR(ZDIVOPT02=CSWD,ZDIVOPT02=DVAC),OFFSET(宣告利率!$R$2,B98,0),0)) | N98: =IF(B98="","",IF(ZDIVOPT02=CSWD,OFFSET(宣告利率!$S$2,B98,0),IF(ZDIVOPT02=DVAC,OFFSET(宣告利率!$T$2,B98,0),0))) | O98: =IF(B98="","",IF(C98<0,0,OFFSET(宣告利率!$J$2,B98,0)+MAX(OFFSET(宣告利率!$V$2,B98,0,1,3)))) | P98: =IF(B98="","",F98+L98) | Q98: =IF(B98="","",IF(C98=109,0,OFFSET(宣告利率!$AB$2,B98,0)+OFFSET(宣告利率!$AC$2,B98,0))) | R98: =IF(B98="","",P98+IF(ZDIVOPT02=CSWD,M98,0)+IF(ZDIVOPT02=DVAC,N98,0)) | S98: =IF(C98=109,0,IF(B98="","",Q98+IF(ZDIVOPT02=CSWD,M98,0)+IF(ZDIVOPT02=DVAC,N98,0))) | T98: =IF(B98="","",FYPremium+(MIN(PayYear,B98)-1)*CYPremium) | U98: =IF(B98="","",OFFSET(宣告利率!$Y$2,B98,0)) | V98: =IF(B98="","",P98+N98) | W98: =IF(B98="","",V98/D98) | X98: =IF(B98="","",IF(C98=109,0,Q98+N98)) | Y98: =IF(B98="","",IF(OR(B98<PayYear,C98=109),"-",X98/D98)) | Z98: =IF(B98="","",O98/D98) | AA98: =AND(INDIRECT("B"&ROW())>0,MOD(INDIRECT("B"&ROW()),5)=0) -> #VALUE!
B99: =IF(B98="","",IF(C98=險種基本資料!$B$21,"",B98+1)) | C99: =IF(B99="","",Age+B99-1) | D99: =IF(B99="","",OFFSET(宣告利率!$I$2,B99,0)) | E99: =IF(B99="","",OFFSET(宣告利率!$M$2,B99,0)+OFFSET(宣告利率!$K$2,B99,0)) | F99: =IF(B99="","",OFFSET(宣告利率!$L$2,B99,0)+OFFSET(宣告利率!$K$2,B99,0)) | G99: =IF(B99="","",OFFSET(宣告利率!$J$2,B99,0)) | H99: =IF(B99="","",OFFSET(宣告利率!$G$2,B99,0)) | I99: =IF(B99="","",IF(C99<16,0,IF(C99=16,OFFSET(宣告利率!$O$2,B99-1,0),0)+OFFSET(宣告利率!$O$2,B99,0))) | J99: =IF(B99="","",IF(C99<16,0,OFFSET(宣告利率!$P$2,B99,0))) | K99: =IF(B99="","",IF(C99<16,OFFSET(宣告利率!$N$2,B99,0)+OFFSET(宣告利率!$U$2,B99,0),OFFSET(宣告利率!$Q$2,B99,0)+OFFSET(宣告利率!$U$2,B99,0))) | L99: =IF(B99="","",IF(C99<16,OFFSET(宣告利率!$N$2,B99,0),OFFSET(宣告利率!$Q$2,B99,0)+OFFSET(宣告利率!$U$2,B99,0))) | M99: =IF(B99="","",IF(OR(ZDIVOPT02=CSWD,ZDIVOPT02=DVAC),OFFSET(宣告利率!$R$2,B99,0),0)) | N99: =IF(B99="","",IF(ZDIVOPT02=CSWD,OFFSET(宣告利率!$S$2,B99,0),IF(ZDIVOPT02=DVAC,OFFSET(宣告利率!$T$2,B99,0),0))) | O99: =IF(B99="","",IF(C99<0,0,OFFSET(宣告利率!$J$2,B99,0)+MAX(OFFSET(宣告利率!$V$2,B99,0,1,3)))) | P99: =IF(B99="","",F99+L99) | Q99: =IF(B99="","",IF(C99=109,0,OFFSET(宣告利率!$AB$2,B99,0)+OFFSET(宣告利率!$AC$2,B99,0))) | R99: =IF(B99="","",P99+IF(ZDIVOPT02=CSWD,M99,0)+IF(ZDIVOPT02=DVAC,N99,0)) | S99: =IF(C99=109,0,IF(B99="","",Q99+IF(ZDIVOPT02=CSWD,M99,0)+IF(ZDIVOPT02=DVAC,N99,0))) | T99: =IF(B99="","",FYPremium+(MIN(PayYear,B99)-1)*CYPremium) | U99: =IF(B99="","",OFFSET(宣告利率!$Y$2,B99,0)) | V99: =IF(B99="","",P99+N99) | W99: =IF(B99="","",V99/D99) | X99: =IF(B99="","",IF(C99=109,0,Q99+N99)) | Y99: =IF(B99="","",IF(OR(B99<PayYear,C99=109),"-",X99/D99)) | Z99: =IF(B99="","",O99/D99) | AA99: =AND(INDIRECT("B"&ROW())>0,MOD(INDIRECT("B"&ROW()),5)=0) -> #VALUE!
B100: =IF(B99="","",IF(C99=險種基本資料!$B$21,"",B99+1)) | C100: =IF(B100="","",Age+B100-1) | D100: =IF(B100="","",OFFSET(宣告利率!$I$2,B100,0)) | E100: =IF(B100="","",OFFSET(宣告利率!$M$2,B100,0)+OFFSET(宣告利率!$K$2,B100,0)) | F100: =IF(B100="","",OFFSET(宣告利率!$L$2,B100,0)+OFFSET(宣告利率!$K$2,B100,0)) | G100: =IF(B100="","",OFFSET(宣告利率!$J$2,B100,0)) | H100: =IF(B100="","",OFFSET(宣告利率!$G$2,B100,0)) | I100: =IF(B100="","",IF(C100<16,0,IF(C100=16,OFFSET(宣告利率!$O$2,B100-1,0),0)+OFFSET(宣告利率!$O$2,B100,0))) | J100: =IF(B100="","",IF(C100<16,0,OFFSET(宣告利率!$P$2,B100,0))) | K100: =IF(B100="","",IF(C100<16,OFFSET(宣告利率!$N$2,B100,0)+OFFSET(宣告利率!$U$2,B100,0),OFFSET(宣告利率!$Q$2,B100,0)+OFFSET(宣告利率!$U$2,B100,0))) | L100: =IF(B100="","",IF(C100<16,OFFSET(宣告利率!$N$2,B100,0),OFFSET(宣告利率!$Q$2,B100,0)+OFFSET(宣告利率!$U$2,B100,0))) | M100: =IF(B100="","",IF(OR(ZDIVOPT02=CSWD,ZDIVOPT02=DVAC),OFFSET(宣告利率!$R$2,B100,0),0)) | N100: =IF(B100="","",IF(ZDIVOPT02=CSWD,OFFSET(宣告利率!$S$2,B100,0),IF(ZDIVOPT02=DVAC,OFFSET(宣告利率!$T$2,B100,0),0))) | O100: =IF(B100="","",IF(C100<0,0,OFFSET(宣告利率!$J$2,B100,0)+MAX(OFFSET(宣告利率!$V$2,B100,0,1,3)))) | P100: =IF(B100="","",F100+L100) | Q100: =IF(B100="","",IF(C100=109,0,OFFSET(宣告利率!$AB$2,B100,0)+OFFSET(宣告利率!$AC$2,B100,0))) | R100: =IF(B100="","",P100+IF(ZDIVOPT02=CSWD,M100,0)+IF(ZDIVOPT02=DVAC,N100,0)) | S100: =IF(C100=109,0,IF(B100="","",Q100+IF(ZDIVOPT02=CSWD,M100,0)+IF(ZDIVOPT02=DVAC,N100,0))) | T100: =IF(B100="","",FYPremium+(MIN(PayYear,B100)-1)*CYPremium) | U100: =IF(B100="","",OFFSET(宣告利率!$Y$2,B100,0)) | V100: =IF(B100="","",P100+N100) | W100: =IF(B100="","",V100/D100) | X100: =IF(B100="","",IF(C100=109,0,Q100+N100)) | Y100: =IF(B100="","",IF(OR(B100<PayYear,C100=109),"-",X100/D100)) | Z100: =IF(B100="","",O100/D100) | AA100: =AND(INDIRECT("B"&ROW())>0,MOD(INDIRECT("B"&ROW()),5)=0) -> #VALUE!
B101: =IF(B100="","",IF(C100=險種基本資料!$B$21,"",B100+1)) | C101: =IF(B101="","",Age+B101-1) | D101: =IF(B101="","",OFFSET(宣告利率!$I$2,B101,0)) | E101: =IF(B101="","",OFFSET(宣告利率!$M$2,B101,0)+OFFSET(宣告利率!$K$2,B101,0)) | F101: =IF(B101="","",OFFSET(宣告利率!$L$2,B101,0)+OFFSET(宣告利率!$K$2,B101,0)) | G101: =IF(B101="","",OFFSET(宣告利率!$J$2,B101,0)) | H101: =IF(B101="","",OFFSET(宣告利率!$G$2,B101,0)) | I101: =IF(B101="","",IF(C101<16,0,IF(C101=16,OFFSET(宣告利率!$O$2,B101-1,0),0)+OFFSET(宣告利率!$O$2,B101,0))) | J101: =IF(B101="","",IF(C101<16,0,OFFSET(宣告利率!$P$2,B101,0))) | K101: =IF(B101="","",IF(C101<16,OFFSET(宣告利率!$N$2,B101,0)+OFFSET(宣告利率!$U$2,B101,0),OFFSET(宣告利率!$Q$2,B101,0)+OFFSET(宣告利率!$U$2,B101,0))) | L101: =IF(B101="","",IF(C101<16,OFFSET(宣告利率!$N$2,B101,0),OFFSET(宣告利率!$Q$2,B101,0)+OFFSET(宣告利率!$U$2,B101,0))) | M101: =IF(B101="","",IF(OR(ZDIVOPT02=CSWD,ZDIVOPT02=DVAC),OFFSET(宣告利率!$R$2,B101,0),0)) | N101: =IF(B101="","",IF(ZDIVOPT02=CSWD,OFFSET(宣告利率!$S$2,B101,0),IF(ZDIVOPT02=DVAC,OFFSET(宣告利率!$T$2,B101,0),0))) | O101: =IF(B101="","",IF(C101<0,0,OFFSET(宣告利率!$J$2,B101,0)+MAX(OFFSET(宣告利率!$V$2,B101,0,1,3)))) | P101: =IF(B101="","",F101+L101) | Q101: =IF(B101="","",IF(C101=109,0,OFFSET(宣告利率!$AB$2,B101,0)+OFFSET(宣告利率!$AC$2,B101,0))) | R101: =IF(B101="","",P101+IF(ZDIVOPT02=CSWD,M101,0)+IF(ZDIVOPT02=DVAC,N101,0)) | S101: =IF(C101=109,0,IF(B101="","",Q101+IF(ZDIVOPT02=CSWD,M101,0)+IF(ZDIVOPT02=DVAC,N101,0))) | T101: =IF(B101="","",FYPremium+(MIN(PayYear,B101)-1)*CYPremium) | U101: =IF(B101="","",OFFSET(宣告利率!$Y$2,B101,0)) | V101: =IF(B101="","",P101+N101) | W101: =IF(B101="","",V101/D101) | X101: =IF(B101="","",IF(C101=109,0,Q101+N101)) | Y101: =IF(B101="","",IF(OR(B101<PayYear,C101=109),"-",X101/D101)) | Z101: =IF(B101="","",O101/D101) | AA101: =AND(INDIRECT("B"&ROW())>0,MOD(INDIRECT("B"&ROW()),5)=0) -> #VALUE!
B102: =IF(B101="","",IF(C101=險種基本資料!$B$21,"",B101+1)) | C102: =IF(B102="","",Age+B102-1) | D102: =IF(B102="","",OFFSET(宣告利率!$I$2,B102,0)) | E102: =IF(B102="","",OFFSET(宣告利率!$M$2,B102,0)+OFFSET(宣告利率!$K$2,B102,0)) | F102: =IF(B102="","",OFFSET(宣告利率!$L$2,B102,0)+OFFSET(宣告利率!$K$2,B102,0)) | G102: =IF(B102="","",OFFSET(宣告利率!$J$2,B102,0)) | H102: =IF(B102="","",OFFSET(宣告利率!$G$2,B102,0)) | I102: =IF(B102="","",IF(C102<16,0,IF(C102=16,OFFSET(宣告利率!$O$2,B102-1,0),0)+OFFSET(宣告利率!$O$2,B102,0))) | J102: =IF(B102="","",IF(C102<16,0,OFFSET(宣告利率!$P$2,B102,0))) | K102: =IF(B102="","",IF(C102<16,OFFSET(宣告利率!$N$2,B102,0)+OFFSET(宣告利率!$U$2,B102,0),OFFSET(宣告利率!$Q$2,B102,0)+OFFSET(宣告利率!$U$2,B102,0))) | L102: =IF(B102="","",IF(C102<16,OFFSET(宣告利率!$N$2,B102,0),OFFSET(宣告利率!$Q$2,B102,0)+OFFSET(宣告利率!$U$2,B102,0))) | M102: =IF(B102="","",IF(OR(ZDIVOPT02=CSWD,ZDIVOPT02=DVAC),OFFSET(宣告利率!$R$2,B102,0),0)) | N102: =IF(B102="","",IF(ZDIVOPT02=CSWD,OFFSET(宣告利率!$S$2,B102,0),IF(ZDIVOPT02=DVAC,OFFSET(宣告利率!$T$2,B102,0),0))) | O102: =IF(B102="","",IF(C102<0,0,OFFSET(宣告利率!$J$2,B102,0)+MAX(OFFSET(宣告利率!$V$2,B102,0,1,3)))) | P102: =IF(B102="","",F102+L102) | Q102: =IF(B102="","",IF(C102=109,0,OFFSET(宣告利率!$AB$2,B102,0)+OFFSET(宣告利率!$AC$2,B102,0))) | R102: =IF(B102="","",P102+IF(ZDIVOPT02=CSWD,M102,0)+IF(ZDIVOPT02=DVAC,N102,0)) | S102: =IF(C102=109,0,IF(B102="","",Q102+IF(ZDIVOPT02=CSWD,M102,0)+IF(ZDIVOPT02=DVAC,N102,0))) | T102: =IF(B102="","",FYPremium+(MIN(PayYear,B102)-1)*CYPremium) | U102: =IF(B102="","",OFFSET(宣告利率!$Y$2,B102,0)) | V102: =IF(B102="","",P102+N102) | W102: =IF(B102="","",V102/D102) | X102: =IF(B102="","",IF(C102=109,0,Q102+N102)) | Y102: =IF(B102="","",IF(OR(B102<PayYear,C102=109),"-",X102/D102)) | Z102: =IF(B102="","",O102/D102) | AA102: =AND(INDIRECT("B"&ROW())>0,MOD(INDIRECT("B"&ROW()),5)=0) -> #VALUE!
B103: =IF(B102="","",IF(C102=險種基本資料!$B$21,"",B102+1)) | C103: =IF(B103="","",Age+B103-1) | D103: =IF(B103="","",OFFSET(宣告利率!$I$2,B103,0)) | E103: =IF(B103="","",OFFSET(宣告利率!$M$2,B103,0)+OFFSET(宣告利率!$K$2,B103,0)) | F103: =IF(B103="","",OFFSET(宣告利率!$L$2,B103,0)+OFFSET(宣告利率!$K$2,B103,0)) | G103: =IF(B103="","",OFFSET(宣告利率!$J$2,B103,0)) | H103: =IF(B103="","",OFFSET(宣告利率!$G$2,B103,0)) | I103: =IF(B103="","",IF(C103<16,0,IF(C103=16,OFFSET(宣告利率!$O$2,B103-1,0),0)+OFFSET(宣告利率!$O$2,B103,0))) | J103: =IF(B103="","",IF(C103<16,0,OFFSET(宣告利率!$P$2,B103,0))) | K103: =IF(B103="","",IF(C103<16,OFFSET(宣告利率!$N$2,B103,0)+OFFSET(宣告利率!$U$2,B103,0),OFFSET(宣告利率!$Q$2,B103,0)+OFFSET(宣告利率!$U$2,B103,0))) | L103: =IF(B103="","",IF(C103<16,OFFSET(宣告利率!$N$2,B103,0),OFFSET(宣告利率!$Q$2,B103,0)+OFFSET(宣告利率!$U$2,B103,0))) | M103: =IF(B103="","",IF(OR(ZDIVOPT02=CSWD,ZDIVOPT02=DVAC),OFFSET(宣告利率!$R$2,B103,0),0)) | N103: =IF(B103="","",IF(ZDIVOPT02=CSWD,OFFSET(宣告利率!$S$2,B103,0),IF(ZDIVOPT02=DVAC,OFFSET(宣告利率!$T$2,B103,0),0))) | O103: =IF(B103="","",IF(C103<0,0,OFFSET(宣告利率!$J$2,B103,0)+MAX(OFFSET(宣告利率!$V$2,B103,0,1,3)))) | P103: =IF(B103="","",F103+L103) | Q103: =IF(B103="","",IF(C103=109,0,OFFSET(宣告利率!$AB$2,B103,0)+OFFSET(宣告利率!$AC$2,B103,0))) | R103: =IF(B103="","",P103+IF(ZDIVOPT02=CSWD,M103,0)+IF(ZDIVOPT02=DVAC,N103,0)) | S103: =IF(C103=109,0,IF(B103="","",Q103+IF(ZDIVOPT02=CSWD,M103,0)+IF(ZDIVOPT02=DVAC,N103,0))) | T103: =IF(B103="","",FYPremium+(MIN(PayYear,B103)-1)*CYPremium) | U103: =IF(B103="","",OFFSET(宣告利率!$Y$2,B103,0)) | V103: =IF(B103="","",P103+N103) | W103: =IF(B103="","",V103/D103) | X103: =IF(B103="","",IF(C103=109,0,Q103+N103)) | Y103: =IF(B103="","",IF(OR(B103<PayYear,C103=109),"-",X103/D103)) | Z103: =IF(B103="","",O103/D103) | AA103: =AND(INDIRECT("B"&ROW())>0,MOD(INDIRECT("B"&ROW()),5)=0) -> #VALUE!
B104: =IF(B103="","",IF(C103=險種基本資料!$B$21,"",B103+1)) | C104: =IF(B104="","",Age+B104-1) | D104: =IF(B104="","",OFFSET(宣告利率!$I$2,B104,0)) | E104: =IF(B104="","",OFFSET(宣告利率!$M$2,B104,0)+OFFSET(宣告利率!$K$2,B104,0)) | F104: =IF(B104="","",OFFSET(宣告利率!$L$2,B104,0)+OFFSET(宣告利率!$K$2,B104,0)) | G104: =IF(B104="","",OFFSET(宣告利率!$J$2,B104,0)) | H104: =IF(B104="","",OFFSET(宣告利率!$G$2,B104,0)) | I104: =IF(B104="","",IF(C104<16,0,IF(C104=16,OFFSET(宣告利率!$O$2,B104-1,0),0)+OFFSET(宣告利率!$O$2,B104,0))) | J104: =IF(B104="","",IF(C104<16,0,OFFSET(宣告利率!$P$2,B104,0))) | K104: =IF(B104="","",IF(C104<16,OFFSET(宣告利率!$N$2,B104,0)+OFFSET(宣告利率!$U$2,B104,0),OFFSET(宣告利率!$Q$2,B104,0)+OFFSET(宣告利率!$U$2,B104,0))) | L104: =IF(B104="","",IF(C104<16,OFFSET(宣告利率!$N$2,B104,0),OFFSET(宣告利率!$Q$2,B104,0)+OFFSET(宣告利率!$U$2,B104,0))) | M104: =IF(B104="","",IF(OR(ZDIVOPT02=CSWD,ZDIVOPT02=DVAC),OFFSET(宣告利率!$R$2,B104,0),0)) | N104: =IF(B104="","",IF(ZDIVOPT02=CSWD,OFFSET(宣告利率!$S$2,B104,0),IF(ZDIVOPT02=DVAC,OFFSET(宣告利率!$T$2,B104,0),0))) | O104: =IF(B104="","",IF(C104<0,0,OFFSET(宣告利率!$J$2,B104,0)+MAX(OFFSET(宣告利率!$V$2,B104,0,1,3)))) | P104: =IF(B104="","",F104+L104) | Q104: =IF(B104="","",IF(C104=109,0,OFFSET(宣告利率!$AB$2,B104,0)+OFFSET(宣告利率!$AC$2,B104,0))) | R104: =IF(B104="","",P104+IF(ZDIVOPT02=CSWD,M104,0)+IF(ZDIVOPT02=DVAC,N104,0)) | S104: =IF(C104=109,0,IF(B104="","",Q104+IF(ZDIVOPT02=CSWD,M104,0)+IF(ZDIVOPT02=DVAC,N104,0))) | T104: =IF(B104="","",FYPremium+(MIN(PayYear,B104)-1)*CYPremium) | U104: =IF(B104="","",OFFSET(宣告利率!$Y$2,B104,0)) | V104: =IF(B104="","",P104+N104) | W104: =IF(B104="","",V104/D104) | X104: =IF(B104="","",IF(C104=109,0,Q104+N104)) | Y104: =IF(B104="","",IF(OR(B104<PayYear,C104=109),"-",X104/D104)) | Z104: =IF(B104="","",O104/D104) | AA104: =AND(INDIRECT("B"&ROW())>0,MOD(INDIRECT("B"&ROW()),5)=0) -> #VALUE!
B105: =IF(B104="","",IF(C104=險種基本資料!$B$21,"",B104+1)) | C105: =IF(B105="","",Age+B105-1) | D105: =IF(B105="","",OFFSET(宣告利率!$I$2,B105,0)) | E105: =IF(B105="","",OFFSET(宣告利率!$M$2,B105,0)+OFFSET(宣告利率!$K$2,B105,0)) | F105: =IF(B105="","",OFFSET(宣告利率!$L$2,B105,0)+OFFSET(宣告利率!$K$2,B105,0)) | G105: =IF(B105="","",OFFSET(宣告利率!$J$2,B105,0)) | H105: =IF(B105="","",OFFSET(宣告利率!$G$2,B105,0)) | I105: =IF(B105="","",IF(C105<16,0,IF(C105=16,OFFSET(宣告利率!$O$2,B105-1,0),0)+OFFSET(宣告利率!$O$2,B105,0))) | J105: =IF(B105="","",IF(C105<16,0,OFFSET(宣告利率!$P$2,B105,0))) | K105: =IF(B105="","",IF(C105<16,OFFSET(宣告利率!$N$2,B105,0)+OFFSET(宣告利率!$U$2,B105,0),OFFSET(宣告利率!$Q$2,B105,0)+OFFSET(宣告利率!$U$2,B105,0))) | L105: =IF(B105="","",IF(C105<16,OFFSET(宣告利率!$N$2,B105,0),OFFSET(宣告利率!$Q$2,B105,0)+OFFSET(宣告利率!$U$2,B105,0))) | M105: =IF(B105="","",IF(OR(ZDIVOPT02=CSWD,ZDIVOPT02=DVAC),OFFSET(宣告利率!$R$2,B105,0),0)) | N105: =IF(B105="","",IF(ZDIVOPT02=CSWD,OFFSET(宣告利率!$S$2,B105,0),IF(ZDIVOPT02=DVAC,OFFSET(宣告利率!$T$2,B105,0),0))) | O105: =IF(B105="","",IF(C105<0,0,OFFSET(宣告利率!$J$2,B105,0)+MAX(OFFSET(宣告利率!$V$2,B105,0,1,3)))) | P105: =IF(B105="","",F105+L105) | Q105: =IF(B105="","",IF(C105=109,0,OFFSET(宣告利率!$AB$2,B105,0)+OFFSET(宣告利率!$AC$2,B105,0))) | R105: =IF(B105="","",P105+IF(ZDIVOPT02=CSWD,M105,0)+IF(ZDIVOPT02=DVAC,N105,0)) | S105: =IF(C105=109,0,IF(B105="","",Q105+IF(ZDIVOPT02=CSWD,M105,0)+IF(ZDIVOPT02=DVAC,N105,0))) | T105: =IF(B105="","",FYPremium+(MIN(PayYear,B105)-1)*CYPremium) | U105: =IF(B105="","",OFFSET(宣告利率!$Y$2,B105,0)) | V105: =IF(B105="","",P105+N105) | W105: =IF(B105="","",V105/D105) | X105: =IF(B105="","",IF(C105=109,0,Q105+N105)) | Y105: =IF(B105="","",IF(OR(B105<PayYear,C105=109),"-",X105/D105)) | Z105: =IF(B105="","",O105/D105) | AA105: =AND(INDIRECT("B"&ROW())>0,MOD(INDIRECT("B"&ROW()),5)=0) -> #VALUE!
B106: =IF(B105="","",IF(C105=險種基本資料!$B$21,"",B105+1)) | C106: =IF(B106="","",Age+B106-1) | D106: =IF(B106="","",OFFSET(宣告利率!$I$2,B106,0)) | E106: =IF(B106="","",OFFSET(宣告利率!$M$2,B106,0)+OFFSET(宣告利率!$K$2,B106,0)) | F106: =IF(B106="","",OFFSET(宣告利率!$L$2,B106,0)+OFFSET(宣告利率!$K$2,B106,0)) | G106: =IF(B106="","",OFFSET(宣告利率!$J$2,B106,0)) | H106: =IF(B106="","",OFFSET(宣告利率!$G$2,B106,0)) | I106: =IF(B106="","",IF(C106<16,0,IF(C106=16,OFFSET(宣告利率!$O$2,B106-1,0),0)+OFFSET(宣告利率!$O$2,B106,0))) | J106: =IF(B106="","",IF(C106<16,0,OFFSET(宣告利率!$P$2,B106,0))) | K106: =IF(B106="","",IF(C106<16,OFFSET(宣告利率!$N$2,B106,0)+OFFSET(宣告利率!$U$2,B106,0),OFFSET(宣告利率!$Q$2,B106,0)+OFFSET(宣告利率!$U$2,B106,0))) | L106: =IF(B106="","",IF(C106<16,OFFSET(宣告利率!$N$2,B106,0),OFFSET(宣告利率!$Q$2,B106,0)+OFFSET(宣告利率!$U$2,B106,0))) | M106: =IF(B106="","",IF(OR(ZDIVOPT02=CSWD,ZDIVOPT02=DVAC),OFFSET(宣告利率!$R$2,B106,0),0)) | N106: =IF(B106="","",IF(ZDIVOPT02=CSWD,OFFSET(宣告利率!$S$2,B106,0),IF(ZDIVOPT02=DVAC,OFFSET(宣告利率!$T$2,B106,0),0))) | O106: =IF(B106="","",IF(C106<0,0,OFFSET(宣告利率!$J$2,B106,0)+MAX(OFFSET(宣告利率!$V$2,B106,0,1,3)))) | P106: =IF(B106="","",F106+L106) | Q106: =IF(B106="","",IF(C106=109,0,OFFSET(宣告利率!$AB$2,B106,0)+OFFSET(宣告利率!$AC$2,B106,0))) | R106: =IF(B106="","",P106+IF(ZDIVOPT02=CSWD,M106,0)+IF(ZDIVOPT02=DVAC,N106,0)) | S106: =IF(C106=109,0,IF(B106="","",Q106+IF(ZDIVOPT02=CSWD,M106,0)+IF(ZDIVOPT02=DVAC,N106,0))) | T106: =IF(B106="","",FYPremium+(MIN(PayYear,B106)-1)*CYPremium) | U106: =IF(B106="","",OFFSET(宣告利率!$Y$2,B106,0)) | V106: =IF(B106="","",P106+N106) | W106: =IF(B106="","",V106/D106) | X106: =IF(B106="","",IF(C106=109,0,Q106+N106)) | Y106: =IF(B106="","",IF(OR(B106<PayYear,C106=109),"-",X106/D106)) | Z106: =IF(B106="","",O106/D106) | AA106: =AND(INDIRECT("B"&ROW())>0,MOD(INDIRECT("B"&ROW()),5)=0) -> #VALUE!
... B118: =IF(B117="","",IF(C117=險種基本資料!$B$21,"",B117+1)) | C118: =IF(B118="","",Age+B118-1) | D118: =IF(B118="","",OFFSET(宣告利率!$I$2,B118,0)) | E118: =IF(B118="","",OFFSET(宣告利率!$M$2,B118,0)+OFFSET(宣告利率!$K$2,B118,0)) | F118: =IF(B118="","",OFFSET(宣告利率!$L$2,B118,0)+OFFSET(宣告利率!$K$2,B118,0)) | G118: =IF(B118="","",OFFSET(宣告利率!$J$2,B118,0)) | H118: =IF(B118="","",OFFSET(宣告利率!$G$2,B118,0)) | I118: =IF(B118="","",IF(C118<16,0,IF(C118=16,OFFSET(宣告利率!$O$2,B118-1,0),0)+OFFSET(宣告利率!$O$2,B118,0))) | J118: =IF(B118="","",IF(C118<16,0,OFFSET(宣告利率!$P$2,B118,0))) | K118: =IF(B118="","",IF(C118<16,OFFSET(宣告利率!$N$2,B118,0)+OFFSET(宣告利率!$U$2,B118,0),OFFSET(宣告利率!$Q$2,B118,0)+OFFSET(宣告利率!$U$2,B118,0))) | L118: =IF(B118="","",IF(C118<16,OFFSET(宣告利率!$N$2,B118,0),OFFSET(宣告利率!$Q$2,B118,0)+OFFSET(宣告利率!$U$2,B118,0))) | M118: =IF(B118="","",IF(OR(ZDIVOPT02=CSWD,ZDIVOPT02=DVAC),OFFSET(宣告利率!$R$2,B118,0),0)) | N118: =IF(B118="","",IF(ZDIVOPT02=CSWD,OFFSET(宣告利率!$S$2,B118,0),IF(ZDIVOPT02=DVAC,OFFSET(宣告利率!$T$2,B118,0),0))) | O118: =IF(B118="","",IF(C118<0,0,OFFSET(宣告利率!$J$2,B118,0)+MAX(OFFSET(宣告利率!$V$2,B118,0,1,3)))) | P118: =IF(B118="","",F118+L118) | Q118: =IF(B118="","",IF(C118=109,0,OFFSET(宣告利率!$AB$2,B118,0)+OFFSET(宣告利率!$AC$2,B118,0))) | R118: =IF(B118="","",P118+IF(ZDIVOPT02=CSWD,M118,0)+IF(ZDIVOPT02=DVAC,N118,0)) | S118: =IF(C118=109,0,IF(B118="","",Q118+IF(ZDIVOPT02=CSWD,M118,0)+IF(ZDIVOPT02=DVAC,N118,0))) | T118: =IF(B118="","",FYPremium+(MIN(PayYear,B118)-1)*CYPremium) | U118: =IF(B118="","",OFFSET(宣告利率!$Y$2,B118,0)) | V118: =IF(B118="","",P118+N118) | W118: =IF(B118="","",V118/D118) | X118: =IF(B118="","",IF(C118=109,0,Q118+N118)) | Y118: =IF(B118="","",IF(OR(B118<PayYear,C118=109),"-",X118/D118)) | Z118: =IF(B118="","",O118/D118) | AA118: =AND(INDIRECT("B"&ROW())>0,MOD(INDIRECT("B"&ROW()),5)=0) -> #VALUE!
B119: =B17 -> 保單 年度 (末) | C119: =C17 -> 保險 年齡 | D119: =D17 -> 累積所繳保險費 (A) | E119: =E17 -> 基本保險金額對應之保單價值準備金 【含祝壽保險金】 | F119: =F17 -> 基本保險金額 對應之現金價值 【含祝壽保險金】 (B) | G119: =G17 -> 基本保險金額 對應之壽險保障 (身故保險金) | J119: =J17 -> 假設投保後未來各保單年度宣告利率為4.35% (下表為預估假設值) | R119: =R17 -> 年度末終止契約時合計可領取之金額(含增值回饋分享金) (F) | S119: =S17 -> 次年度期初終止契約時合計可領取之金額(含增值回饋分享金) (H)=(G) | T119: =T17 -> 累積 應繳保費 | U119: =U17 -> 期末保單價值準備金(含基本保險金額、累計增加保險金額) 【含祝壽保險金】 | V119: =V17 -> (E)+(F) | W119: =W17 -> ((E)+(F))/(A) | X119: =X17 -> (G)+(E) | Y119: =Y17 -> ((G)+(E))/(A) | Z119: =Z17 -> (I)/(A) | AA119: =AND(INDIRECT("B"&ROW())>0,MOD(INDIRECT("B"&ROW()),5)=0) -> #VALUE!
B120: =B18 -> 0 | C120: =C18 -> 0 | D120: =D18 -> 0 | E120: =E18 -> 0 | F120: =F18 -> 0 | G120: =G18 -> 0 | H120: =H18 -> 增值回饋分享金 | I120: =I18 -> 選擇以繳清保險方式增加保險金額 | ... Q120: =Q18 -> 0 | T120: =T18 -> 0 | U120: =U18 -> 0 | V120: =V18 -> 0 | W120: =W18 -> 0 | X120: =X18 -> 0 | Y120: =Y18 -> 0 | AA120: =AND(INDIRECT("B"&ROW())>0,MOD(INDIRECT("B"&ROW()),5)=0) -> FALSE
B121: =B19 -> 0 | C121: =C19 -> 0 | D121: =D19 -> 0 | E121: =E19 -> 0 | F121: =F19 -> 0 | G121: =G19 -> 0 | H121: =H19 -> 0 | I121: =I19 -> 增額繳清保險金額 | ... Q121: =Q19 -> 次年度期初 現金價值 (G) | T121: =T19 -> 0 | U121: =U19 -> 0 | V121: =V19 -> 0 | W121: =W19 -> 0 | X121: =X19 -> 0 | Y121: =Y19 -> 0 | AA121: =AND(INDIRECT("B"&ROW())>0,MOD(INDIRECT("B"&ROW()),5)=0) -> FALSE
B122: =IF(B118="","",IF(C118=險種基本資料!$B$21,"",B118+1)) | C122: =IF(B122="","",Age+B122-1) | D122: =IF(B122="","",OFFSET(宣告利率!$I$2,B122,0)) | E122: =IF(B122="","",OFFSET(宣告利率!$M$2,B122,0)+OFFSET(宣告利率!$K$2,B122,0)) | F122: =IF(B122="","",OFFSET(宣告利率!$L$2,B122,0)+OFFSET(宣告利率!$K$2,B122,0)) | G122: =IF(B122="","",OFFSET(宣告利率!$J$2,B122,0)) | H122: =IF(B122="","",OFFSET(宣告利率!$G$2,B122,0)) | I122: =IF(B122="","",IF(C122<16,0,IF(C122=16,OFFSET(宣告利率!$O$2,B122-1,0),0)+OFFSET(宣告利率!$O$2,B122,0))) | J122: =IF(B122="","",IF(C122<16,0,OFFSET(宣告利率!$P$2,B122,0))) | K122: =IF(B122="","",IF(C122<16,OFFSET(宣告利率!$N$2,B122,0)+OFFSET(宣告利率!$U$2,B122,0),OFFSET(宣告利率!$Q$2,B122,0)+OFFSET(宣告利率!$U$2,B122,0))) | L122: =IF(B122="","",IF(C122<16,OFFSET(宣告利率!$N$2,B122,0),OFFSET(宣告利率!$Q$2,B122,0)+OFFSET(宣告利率!$U$2,B122,0))) | M122: =IF(B122="","",IF(OR(ZDIVOPT02=CSWD,ZDIVOPT02=DVAC),OFFSET(宣告利率!$R$2,B122,0),0)) | N122: =IF(B122="","",IF(ZDIVOPT02=CSWD,OFFSET(宣告利率!$S$2,B122,0),IF(ZDIVOPT02=DVAC,OFFSET(宣告利率!$T$2,B122,0),0))) | O122: =IF(B122="","",IF(C122<0,0,OFFSET(宣告利率!$J$2,B122,0)+MAX(OFFSET(宣告利率!$V$2,B122,0,1,3)))) | P122: =IF(B122="","",F122+L122) | Q122: =IF(B122="","",IF(C122=109,0,OFFSET(宣告利率!$AB$2,B122,0)+OFFSET(宣告利率!$AC$2,B122,0))) | R122: =IF(B122="","",P122+IF(ZDIVOPT02=CSWD,M122,0)+IF(ZDIVOPT02=DVAC,N122,0)) | S122: =IF(C122=109,0,IF(B122="","",Q122+IF(ZDIVOPT02=CSWD,M122,0)+IF(ZDIVOPT02=DVAC,N122,0))) | T122: =IF(B122="","",FYPremium+(MIN(PayYear,B122)-1)*CYPremium) | U122: =IF(B122="","",OFFSET(宣告利率!$Y$2,B122,0)) | V122: =IF(B122="","",P122+N122) | W122: =IF(B122="","",V122/D122) | X122: =IF(B122="","",IF(C122=109,0,Q122+N122)) | Y122: =IF(B122="","",IF(OR(B122<PayYear,C122=109),"-",X122/D122)) | Z122: =IF(B122="","",O122/D122) | AA122: =AND(INDIRECT("B"&ROW())>0,MOD(INDIRECT("B"&ROW()),5)=0) -> #VALUE!
B123: =IF(B122="","",IF(C122=險種基本資料!$B$21,"",B122+1)) | C123: =IF(B123="","",Age+B123-1) | D123: =IF(B123="","",OFFSET(宣告利率!$I$2,B123,0)) | E123: =IF(B123="","",OFFSET(宣告利率!$M$2,B123,0)+OFFSET(宣告利率!$K$2,B123,0)) | F123: =IF(B123="","",OFFSET(宣告利率!$L$2,B123,0)+OFFSET(宣告利率!$K$2,B123,0)) | G123: =IF(B123="","",OFFSET(宣告利率!$J$2,B123,0)) | H123: =IF(B123="","",OFFSET(宣告利率!$G$2,B123,0)) | I123: =IF(B123="","",IF(C123<16,0,IF(C123=16,OFFSET(宣告利率!$O$2,B123-1,0),0)+OFFSET(宣告利率!$O$2,B123,0))) | J123: =IF(B123="","",IF(C123<16,0,OFFSET(宣告利率!$P$2,B123,0))) | K123: =IF(B123="","",IF(C123<16,OFFSET(宣告利率!$N$2,B123,0)+OFFSET(宣告利率!$U$2,B123,0),OFFSET(宣告利率!$Q$2,B123,0)+OFFSET(宣告利率!$U$2,B123,0))) | L123: =IF(B123="","",IF(C123<16,OFFSET(宣告利率!$N$2,B123,0),OFFSET(宣告利率!$Q$2,B123,0)+OFFSET(宣告利率!$U$2,B123,0))) | M123: =IF(B123="","",IF(OR(ZDIVOPT02=CSWD,ZDIVOPT02=DVAC),OFFSET(宣告利率!$R$2,B123,0),0)) | N123: =IF(B123="","",IF(ZDIVOPT02=CSWD,OFFSET(宣告利率!$S$2,B123,0),IF(ZDIVOPT02=DVAC,OFFSET(宣告利率!$T$2,B123,0),0))) | O123: =IF(B123="","",IF(C123<0,0,OFFSET(宣告利率!$J$2,B123,0)+MAX(OFFSET(宣告利率!$V$2,B123,0,1,3)))) | P123: =IF(B123="","",F123+L123) | Q123: =IF(B123="","",IF(C123=109,0,OFFSET(宣告利率!$AB$2,B123,0)+OFFSET(宣告利率!$AC$2,B123,0))) | R123: =IF(B123="","",P123+IF(ZDIVOPT02=CSWD,M123,0)+IF(ZDIVOPT02=DVAC,N123,0)) | S123: =IF(C123=109,0,IF(B123="","",Q123+IF(ZDIVOPT02=CSWD,M123,0)+IF(ZDIVOPT02=DVAC,N123,0))) | T123: =IF(B123="","",FYPremium+(MIN(PayYear,B123)-1)*CYPremium) | U123: =IF(B123="","",OFFSET(宣告利率!$Y$2,B123,0)) | V123: =IF(B123="","",P123+N123) | W123: =IF(B123="","",V123/D123) | X123: =IF(B123="","",IF(C123=109,0,Q123+N123)) | Y123: =IF(B123="","",IF(OR(B123<PayYear,C123=109),"-",X123/D123)) | Z123: =IF(B123="","",O123/D123) | AA123: =AND(INDIRECT("B"&ROW())>0,MOD(INDIRECT("B"&ROW()),5)=0) -> #VALUE!
B124: =IF(B123="","",IF(C123=險種基本資料!$B$21,"",B123+1)) | C124: =IF(B124="","",Age+B124-1) | D124: =IF(B124="","",OFFSET(宣告利率!$I$2,B124,0)) | E124: =IF(B124="","",OFFSET(宣告利率!$M$2,B124,0)+OFFSET(宣告利率!$K$2,B124,0)) | F124: =IF(B124="","",OFFSET(宣告利率!$L$2,B124,0)+OFFSET(宣告利率!$K$2,B124,0)) | G124: =IF(B124="","",OFFSET(宣告利率!$J$2,B124,0)) | H124: =IF(B124="","",OFFSET(宣告利率!$G$2,B124,0)) | I124: =IF(B124="","",IF(C124<16,0,IF(C124=16,OFFSET(宣告利率!$O$2,B124-1,0),0)+OFFSET(宣告利率!$O$2,B124,0))) | J124: =IF(B124="","",IF(C124<16,0,OFFSET(宣告利率!$P$2,B124,0))) | K124: =IF(B124="","",IF(C124<16,OFFSET(宣告利率!$N$2,B124,0)+OFFSET(宣告利率!$U$2,B124,0),OFFSET(宣告利率!$Q$2,B124,0)+OFFSET(宣告利率!$U$2,B124,0))) | L124: =IF(B124="","",IF(C124<16,OFFSET(宣告利率!$N$2,B124,0),OFFSET(宣告利率!$Q$2,B124,0)+OFFSET(宣告利率!$U$2,B124,0))) | M124: =IF(B124="","",IF(OR(ZDIVOPT02=CSWD,ZDIVOPT02=DVAC),OFFSET(宣告利率!$R$2,B124,0),0)) | N124: =IF(B124="","",IF(ZDIVOPT02=CSWD,OFFSET(宣告利率!$S$2,B124,0),IF(ZDIVOPT02=DVAC,OFFSET(宣告利率!$T$2,B124,0),0))) | O124: =IF(B124="","",IF(C124<0,0,OFFSET(宣告利率!$J$2,B124,0)+MAX(OFFSET(宣告利率!$V$2,B124,0,1,3)))) | P124: =IF(B124="","",F124+L124) | Q124: =IF(B124="","",IF(C124=109,0,OFFSET(宣告利率!$AB$2,B124,0)+OFFSET(宣告利率!$AC$2,B124,0))) | R124: =IF(B124="","",P124+IF(ZDIVOPT02=CSWD,M124,0)+IF(ZDIVOPT02=DVAC,N124,0)) | S124: =IF(C124=109,0,IF(B124="","",Q124+IF(ZDIVOPT02=CSWD,M124,0)+IF(ZDIVOPT02=DVAC,N124,0))) | T124: =IF(B124="","",FYPremium+(MIN(PayYear,B124)-1)*CYPremium) | U124: =IF(B124="","",OFFSET(宣告利率!$Y$2,B124,0)) | V124: =IF(B124="","",P124+N124) | W124: =IF(B124="","",V124/D124) | X124: =IF(B124="","",IF(C124=109,0,Q124+N124)) | Y124: =IF(B124="","",IF(OR(B124<PayYear,C124=109),"-",X124/D124)) | Z124: =IF(B124="","",O124/D124) | AA124: =AND(INDIRECT("B"&ROW())>0,MOD(INDIRECT("B"&ROW()),5)=0) -> #VALUE!
B125: =IF(B124="","",IF(C124=險種基本資料!$B$21,"",B124+1)) | C125: =IF(B125="","",Age+B125-1) | D125: =IF(B125="","",OFFSET(宣告利率!$I$2,B125,0)) | E125: =IF(B125="","",OFFSET(宣告利率!$M$2,B125,0)+OFFSET(宣告利率!$K$2,B125,0)) | F125: =IF(B125="","",OFFSET(宣告利率!$L$2,B125,0)+OFFSET(宣告利率!$K$2,B125,0)) | G125: =IF(B125="","",OFFSET(宣告利率!$J$2,B125,0)) | H125: =IF(B125="","",OFFSET(宣告利率!$G$2,B125,0)) | I125: =IF(B125="","",IF(C125<16,0,IF(C125=16,OFFSET(宣告利率!$O$2,B125-1,0),0)+OFFSET(宣告利率!$O$2,B125,0))) | J125: =IF(B125="","",IF(C125<16,0,OFFSET(宣告利率!$P$2,B125,0))) | K125: =IF(B125="","",IF(C125<16,OFFSET(宣告利率!$N$2,B125,0)+OFFSET(宣告利率!$U$2,B125,0),OFFSET(宣告利率!$Q$2,B125,0)+OFFSET(宣告利率!$U$2,B125,0))) | L125: =IF(B125="","",IF(C125<16,OFFSET(宣告利率!$N$2,B125,0),OFFSET(宣告利率!$Q$2,B125,0)+OFFSET(宣告利率!$U$2,B125,0))) | M125: =IF(B125="","",IF(OR(ZDIVOPT02=CSWD,ZDIVOPT02=DVAC),OFFSET(宣告利率!$R$2,B125,0),0)) | N125: =IF(B125="","",IF(ZDIVOPT02=CSWD,OFFSET(宣告利率!$S$2,B125,0),IF(ZDIVOPT02=DVAC,OFFSET(宣告利率!$T$2,B125,0),0))) | O125: =IF(B125="","",IF(C125<0,0,OFFSET(宣告利率!$J$2,B125,0)+MAX(OFFSET(宣告利率!$V$2,B125,0,1,3)))) | P125: =IF(B125="","",F125+L125) | Q125: =IF(B125="","",IF(C125=109,0,OFFSET(宣告利率!$AB$2,B125,0)+OFFSET(宣告利率!$AC$2,B125,0))) | R125: =IF(B125="","",P125+IF(ZDIVOPT02=CSWD,M125,0)+IF(ZDIVOPT02=DVAC,N125,0)) | S125: =IF(C125=109,0,IF(B125="","",Q125+IF(ZDIVOPT02=CSWD,M125,0)+IF(ZDIVOPT02=DVAC,N125,0))) | T125: =IF(B125="","",FYPremium+(MIN(PayYear,B125)-1)*CYPremium) | U125: =IF(B125="","",OFFSET(宣告利率!$Y$2,B125,0)) | V125: =IF(B125="","",P125+N125) | W125: =IF(B125="","",V125/D125) | X125: =IF(B125="","",IF(C125=109,0,Q125+N125)) | Y125: =IF(B125="","",IF(OR(B125<PayYear,C125=109),"-",X125/D125)) | Z125: =IF(B125="","",O125/D125) | AA125: =AND(INDIRECT("B"&ROW())>0,MOD(INDIRECT("B"&ROW()),5)=0) -> #VALUE!
B126: =IF(B125="","",IF(C125=險種基本資料!$B$21,"",B125+1)) | C126: =IF(B126="","",Age+B126-1) | D126: =IF(B126="","",OFFSET(宣告利率!$I$2,B126,0)) | E126: =IF(B126="","",OFFSET(宣告利率!$M$2,B126,0)+OFFSET(宣告利率!$K$2,B126,0)) | F126: =IF(B126="","",OFFSET(宣告利率!$L$2,B126,0)+OFFSET(宣告利率!$K$2,B126,0)) | G126: =IF(B126="","",OFFSET(宣告利率!$J$2,B126,0)) | H126: =IF(B126="","",OFFSET(宣告利率!$G$2,B126,0)) | I126: =IF(B126="","",IF(C126<16,0,IF(C126=16,OFFSET(宣告利率!$O$2,B126-1,0),0)+OFFSET(宣告利率!$O$2,B126,0))) | J126: =IF(B126="","",IF(C126<16,0,OFFSET(宣告利率!$P$2,B126,0))) | K126: =IF(B126="","",IF(C126<16,OFFSET(宣告利率!$N$2,B126,0)+OFFSET(宣告利率!$U$2,B126,0),OFFSET(宣告利率!$Q$2,B126,0)+OFFSET(宣告利率!$U$2,B126,0))) | L126: =IF(B126="","",IF(C126<16,OFFSET(宣告利率!$N$2,B126,0),OFFSET(宣告利率!$Q$2,B126,0)+OFFSET(宣告利率!$U$2,B126,0))) | M126: =IF(B126="","",IF(OR(ZDIVOPT02=CSWD,ZDIVOPT02=DVAC),OFFSET(宣告利率!$R$2,B126,0),0)) | N126: =IF(B126="","",IF(ZDIVOPT02=CSWD,OFFSET(宣告利率!$S$2,B126,0),IF(ZDIVOPT02=DVAC,OFFSET(宣告利率!$T$2,B126,0),0))) | O126: =IF(B126="","",IF(C126<0,0,OFFSET(宣告利率!$J$2,B126,0)+MAX(OFFSET(宣告利率!$V$2,B126,0,1,3)))) | P126: =IF(B126="","",F126+L126) | Q126: =IF(B126="","",IF(C126=109,0,OFFSET(宣告利率!$AB$2,B126,0)+OFFSET(宣告利率!$AC$2,B126,0))) | R126: =IF(B126="","",P126+IF(ZDIVOPT02=CSWD,M126,0)+IF(ZDIVOPT02=DVAC,N126,0)) | S126: =IF(C126=109,0,IF(B126="","",Q126+IF(ZDIVOPT02=CSWD,M126,0)+IF(ZDIVOPT02=DVAC,N126,0))) | T126: =IF(B126="","",FYPremium+(MIN(PayYear,B126)-1)*CYPremium) | U126: =IF(B126="","",OFFSET(宣告利率!$Y$2,B126,0)) | V126: =IF(B126="","",P126+N126) | W126: =IF(B126="","",V126/D126) | X126: =IF(B126="","",IF(C126=109,0,Q126+N126)) | Y126: =IF(B126="","",IF(OR(B126<PayYear,C126=109),"-",X126/D126)) | Z126: =IF(B126="","",O126/D126) | AA126: =AND(INDIRECT("B"&ROW())>0,MOD(INDIRECT("B"&ROW()),5)=0) -> #VALUE!
B127: =IF(B126="","",IF(C126=險種基本資料!$B$21,"",B126+1)) | C127: =IF(B127="","",Age+B127-1) | D127: =IF(B127="","",OFFSET(宣告利率!$I$2,B127,0)) | E127: =IF(B127="","",OFFSET(宣告利率!$M$2,B127,0)+OFFSET(宣告利率!$K$2,B127,0)) | F127: =IF(B127="","",OFFSET(宣告利率!$L$2,B127,0)+OFFSET(宣告利率!$K$2,B127,0)) | G127: =IF(B127="","",OFFSET(宣告利率!$J$2,B127,0)) | H127: =IF(B127="","",OFFSET(宣告利率!$G$2,B127,0)) | I127: =IF(B127="","",IF(C127<16,0,IF(C127=16,OFFSET(宣告利率!$O$2,B127-1,0),0)+OFFSET(宣告利率!$O$2,B127,0))) | J127: =IF(B127="","",IF(C127<16,0,OFFSET(宣告利率!$P$2,B127,0))) | K127: =IF(B127="","",IF(C127<16,OFFSET(宣告利率!$N$2,B127,0)+OFFSET(宣告利率!$U$2,B127,0),OFFSET(宣告利率!$Q$2,B127,0)+OFFSET(宣告利率!$U$2,B127,0))) | L127: =IF(B127="","",IF(C127<16,OFFSET(宣告利率!$N$2,B127,0),OFFSET(宣告利率!$Q$2,B127,0)+OFFSET(宣告利率!$U$2,B127,0))) | M127: =IF(B127="","",IF(OR(ZDIVOPT02=CSWD,ZDIVOPT02=DVAC),OFFSET(宣告利率!$R$2,B127,0),0)) | N127: =IF(B127="","",IF(ZDIVOPT02=CSWD,OFFSET(宣告利率!$S$2,B127,0),IF(ZDIVOPT02=DVAC,OFFSET(宣告利率!$T$2,B127,0),0))) | O127: =IF(B127="","",IF(C127<0,0,OFFSET(宣告利率!$J$2,B127,0)+MAX(OFFSET(宣告利率!$V$2,B127,0,1,3)))) | P127: =IF(B127="","",F127+L127) | Q127: =IF(B127="","",IF(C127=109,0,OFFSET(宣告利率!$AB$2,B127,0)+OFFSET(宣告利率!$AC$2,B127,0))) | R127: =IF(B127="","",P127+IF(ZDIVOPT02=CSWD,M127,0)+IF(ZDIVOPT02=DVAC,N127,0)) | S127: =IF(C127=109,0,IF(B127="","",Q127+IF(ZDIVOPT02=CSWD,M127,0)+IF(ZDIVOPT02=DVAC,N127,0))) | T127: =IF(B127="","",FYPremium+(MIN(PayYear,B127)-1)*CYPremium) | U127: =IF(B127="","",OFFSET(宣告利率!$Y$2,B127,0)) | V127: =IF(B127="","",P127+N127) | W127: =IF(B127="","",V127/D127) | X127: =IF(B127="","",IF(C127=109,0,Q127+N127)) | Y127: =IF(B127="","",IF(OR(B127<PayYear,C127=109),"-",X127/D127)) | Z127: =IF(B127="","",O127/D127) | AA127: =AND(INDIRECT("B"&ROW())>0,MOD(INDIRECT("B"&ROW()),5)=0) -> #VALUE!
B128: =IF(B127="","",IF(C127=險種基本資料!$B$21,"",B127+1)) | C128: =IF(B128="","",Age+B128-1) | D128: =IF(B128="","",OFFSET(宣告利率!$I$2,B128,0)) | E128: =IF(B128="","",OFFSET(宣告利率!$M$2,B128,0)+OFFSET(宣告利率!$K$2,B128,0)) | F128: =IF(B128="","",OFFSET(宣告利率!$L$2,B128,0)+OFFSET(宣告利率!$K$2,B128,0)) | G128: =IF(B128="","",OFFSET(宣告利率!$J$2,B128,0)) | H128: =IF(B128="","",OFFSET(宣告利率!$G$2,B128,0)) | I128: =IF(B128="","",IF(C128<16,0,IF(C128=16,OFFSET(宣告利率!$O$2,B128-1,0),0)+OFFSET(宣告利率!$O$2,B128,0))) | J128: =IF(B128="","",IF(C128<16,0,OFFSET(宣告利率!$P$2,B128,0))) | K128: =IF(B128="","",IF(C128<16,OFFSET(宣告利率!$N$2,B128,0)+OFFSET(宣告利率!$U$2,B128,0),OFFSET(宣告利率!$Q$2,B128,0)+OFFSET(宣告利率!$U$2,B128,0))) | L128: =IF(B128="","",IF(C128<16,OFFSET(宣告利率!$N$2,B128,0),OFFSET(宣告利率!$Q$2,B128,0)+OFFSET(宣告利率!$U$2,B128,0))) | M128: =IF(B128="","",IF(OR(ZDIVOPT02=CSWD,ZDIVOPT02=DVAC),OFFSET(宣告利率!$R$2,B128,0),0)) | N128: =IF(B128="","",IF(ZDIVOPT02=CSWD,OFFSET(宣告利率!$S$2,B128,0),IF(ZDIVOPT02=DVAC,OFFSET(宣告利率!$T$2,B128,0),0))) | O128: =IF(B128="","",IF(C128<0,0,OFFSET(宣告利率!$J$2,B128,0)+MAX(OFFSET(宣告利率!$V$2,B128,0,1,3)))) | P128: =IF(B128="","",F128+L128) | Q128: =IF(B128="","",IF(C128=109,0,OFFSET(宣告利率!$AB$2,B128,0)+OFFSET(宣告利率!$AC$2,B128,0))) | R128: =IF(B128="","",P128+IF(ZDIVOPT02=CSWD,M128,0)+IF(ZDIVOPT02=DVAC,N128,0)) | S128: =IF(C128=109,0,IF(B128="","",Q128+IF(ZDIVOPT02=CSWD,M128,0)+IF(ZDIVOPT02=DVAC,N128,0))) | T128: =IF(B128="","",FYPremium+(MIN(PayYear,B128)-1)*CYPremium) | U128: =IF(B128="","",OFFSET(宣告利率!$Y$2,B128,0)) | V128: =IF(B128="","",P128+N128) | W128: =IF(B128="","",V128/D128) | X128: =IF(B128="","",IF(C128=109,0,Q128+N128)) | Y128: =IF(B128="","",IF(OR(B128<PayYear,C128=109),"-",X128/D128)) | Z128: =IF(B128="","",O128/D128) | AA128: =AND(INDIRECT("B"&ROW())>0,MOD(INDIRECT("B"&ROW()),5)=0) -> #VALUE!
B129: =IF(B128="","",IF(C128=險種基本資料!$B$21,"",B128+1)) | C129: =IF(B129="","",Age+B129-1) | D129: =IF(B129="","",OFFSET(宣告利率!$I$2,B129,0)) | E129: =IF(B129="","",OFFSET(宣告利率!$M$2,B129,0)+OFFSET(宣告利率!$K$2,B129,0)) | F129: =IF(B129="","",OFFSET(宣告利率!$L$2,B129,0)+OFFSET(宣告利率!$K$2,B129,0)) | G129: =IF(B129="","",OFFSET(宣告利率!$J$2,B129,0)) | H129: =IF(B129="","",OFFSET(宣告利率!$G$2,B129,0)) | I129: =IF(B129="","",IF(C129<16,0,IF(C129=16,OFFSET(宣告利率!$O$2,B129-1,0),0)+OFFSET(宣告利率!$O$2,B129,0))) | J129: =IF(B129="","",IF(C129<16,0,OFFSET(宣告利率!$P$2,B129,0))) | K129: =IF(B129="","",IF(C129<16,OFFSET(宣告利率!$N$2,B129,0)+OFFSET(宣告利率!$U$2,B129,0),OFFSET(宣告利率!$Q$2,B129,0)+OFFSET(宣告利率!$U$2,B129,0))) | L129: =IF(B129="","",IF(C129<16,OFFSET(宣告利率!$N$2,B129,0),OFFSET(宣告利率!$Q$2,B129,0)+OFFSET(宣告利率!$U$2,B129,0))) | M129: =IF(B129="","",IF(OR(ZDIVOPT02=CSWD,ZDIVOPT02=DVAC),OFFSET(宣告利率!$R$2,B129,0),0)) | N129: =IF(B129="","",IF(ZDIVOPT02=CSWD,OFFSET(宣告利率!$S$2,B129,0),IF(ZDIVOPT02=DVAC,OFFSET(宣告利率!$T$2,B129,0),0))) | O129: =IF(B129="","",IF(C129<0,0,OFFSET(宣告利率!$J$2,B129,0)+MAX(OFFSET(宣告利率!$V$2,B129,0,1,3)))) | P129: =IF(B129="","",F129+L129) | Q129: =IF(B129="","",IF(C129=109,0,OFFSET(宣告利率!$AB$2,B129,0)+OFFSET(宣告利率!$AC$2,B129,0))) | R129: =IF(B129="","",P129+IF(ZDIVOPT02=CSWD,M129,0)+IF(ZDIVOPT02=DVAC,N129,0)) | S129: =IF(C129=109,0,IF(B129="","",Q129+IF(ZDIVOPT02=CSWD,M129,0)+IF(ZDIVOPT02=DVAC,N129,0))) | T129: =IF(B129="","",FYPremium+(MIN(PayYear,B129)-1)*CYPremium) | U129: =IF(B129="","",OFFSET(宣告利率!$Y$2,B129,0)) | V129: =IF(B129="","",P129+N129) | W129: =IF(B129="","",V129/D129) | X129: =IF(B129="","",IF(C129=109,0,Q129+N129)) | Y129: =IF(B129="","",IF(OR(B129<PayYear,C129=109),"-",X129/D129)) | Z129: =IF(B129="","",O129/D129) | AA129: =AND(INDIRECT("B"&ROW())>0,MOD(INDIRECT("B"&ROW()),5)=0) -> #VALUE!
B130: =IF(B129="","",IF(C129=險種基本資料!$B$21,"",B129+1)) | C130: =IF(B130="","",Age+B130-1) | D130: =IF(B130="","",OFFSET(宣告利率!$I$2,B130,0)) | E130: =IF(B130="","",OFFSET(宣告利率!$M$2,B130,0)+OFFSET(宣告利率!$K$2,B130,0)) | F130: =IF(B130="","",OFFSET(宣告利率!$L$2,B130,0)+OFFSET(宣告利率!$K$2,B130,0)) | G130: =IF(B130="","",OFFSET(宣告利率!$J$2,B130,0)) | H130: =IF(B130="","",OFFSET(宣告利率!$G$2,B130,0)) | I130: =IF(B130="","",IF(C130<16,0,IF(C130=16,OFFSET(宣告利率!$O$2,B130-1,0),0)+OFFSET(宣告利率!$O$2,B130,0))) | J130: =IF(B130="","",IF(C130<16,0,OFFSET(宣告利率!$P$2,B130,0))) | K130: =IF(B130="","",IF(C130<16,OFFSET(宣告利率!$N$2,B130,0)+OFFSET(宣告利率!$U$2,B130,0),OFFSET(宣告利率!$Q$2,B130,0)+OFFSET(宣告利率!$U$2,B130,0))) | L130: =IF(B130="","",IF(C130<16,OFFSET(宣告利率!$N$2,B130,0),OFFSET(宣告利率!$Q$2,B130,0)+OFFSET(宣告利率!$U$2,B130,0))) | M130: =IF(B130="","",IF(OR(ZDIVOPT02=CSWD,ZDIVOPT02=DVAC),OFFSET(宣告利率!$R$2,B130,0),0)) | N130: =IF(B130="","",IF(ZDIVOPT02=CSWD,OFFSET(宣告利率!$S$2,B130,0),IF(ZDIVOPT02=DVAC,OFFSET(宣告利率!$T$2,B130,0),0))) | O130: =IF(B130="","",IF(C130<0,0,OFFSET(宣告利率!$J$2,B130,0)+MAX(OFFSET(宣告利率!$V$2,B130,0,1,3)))) | P130: =IF(B130="","",F130+L130) | Q130: =IF(B130="","",IF(C130=109,0,OFFSET(宣告利率!$AB$2,B130,0)+OFFSET(宣告利率!$AC$2,B130,0))) | R130: =IF(B130="","",P130+IF(ZDIVOPT02=CSWD,M130,0)+IF(ZDIVOPT02=DVAC,N130,0)) | S130: =IF(C130=109,0,IF(B130="","",Q130+IF(ZDIVOPT02=CSWD,M130,0)+IF(ZDIVOPT02=DVAC,N130,0))) | T130: =IF(B130="","",FYPremium+(MIN(PayYear,B130)-1)*CYPremium) | U130: =IF(B130="","",OFFSET(宣告利率!$Y$2,B130,0)) | V130: =IF(B130="","",P130+N130) | W130: =IF(B130="","",V130/D130) | X130: =IF(B130="","",IF(C130=109,0,Q130+N130)) | Y130: =IF(B130="","",IF(OR(B130<PayYear,C130=109),"-",X130/D130)) | Z130: =IF(B130="","",O130/D130) | AA130: =AND(INDIRECT("B"&ROW())>0,MOD(INDIRECT("B"&ROW()),5)=0) -> #VALUE!
B131: =IF(B130="","",IF(C130=險種基本資料!$B$21,"",B130+1)) | C131: =IF(B131="","",Age+B131-1) | D131: =IF(B131="","",OFFSET(宣告利率!$I$2,B131,0)) | E131: =IF(B131="","",OFFSET(宣告利率!$M$2,B131,0)+OFFSET(宣告利率!$K$2,B131,0)) | F131: =IF(B131="","",OFFSET(宣告利率!$L$2,B131,0)+OFFSET(宣告利率!$K$2,B131,0)) | G131: =IF(B131="","",OFFSET(宣告利率!$J$2,B131,0)) | H131: =IF(B131="","",OFFSET(宣告利率!$G$2,B131,0)) | I131: =IF(B131="","",IF(C131<16,0,IF(C131=16,OFFSET(宣告利率!$O$2,B131-1,0),0)+OFFSET(宣告利率!$O$2,B131,0))) | J131: =IF(B131="","",IF(C131<16,0,OFFSET(宣告利率!$P$2,B131,0))) | K131: =IF(B131="","",IF(C131<16,OFFSET(宣告利率!$N$2,B131,0)+OFFSET(宣告利率!$U$2,B131,0),OFFSET(宣告利率!$Q$2,B131,0)+OFFSET(宣告利率!$U$2,B131,0))) | L131: =IF(B131="","",IF(C131<16,OFFSET(宣告利率!$N$2,B131,0),OFFSET(宣告利率!$Q$2,B131,0)+OFFSET(宣告利率!$U$2,B131,0))) | M131: =IF(B131="","",IF(OR(ZDIVOPT02=CSWD,ZDIVOPT02=DVAC),OFFSET(宣告利率!$R$2,B131,0),0)) | N131: =IF(B131="","",IF(ZDIVOPT02=CSWD,OFFSET(宣告利率!$S$2,B131,0),IF(ZDIVOPT02=DVAC,OFFSET(宣告利率!$T$2,B131,0),0))) | O131: =IF(B131="","",IF(C131<0,0,OFFSET(宣告利率!$J$2,B131,0)+MAX(OFFSET(宣告利率!$V$2,B131,0,1,3)))) | P131: =IF(B131="","",F131+L131) | Q131: =IF(B131="","",IF(C131=109,0,OFFSET(宣告利率!$AB$2,B131,0)+OFFSET(宣告利率!$AC$2,B131,0))) | R131: =IF(B131="","",P131+IF(ZDIVOPT02=CSWD,M131,0)+IF(ZDIVOPT02=DVAC,N131,0)) | S131: =IF(C131=109,0,IF(B131="","",Q131+IF(ZDIVOPT02=CSWD,M131,0)+IF(ZDIVOPT02=DVAC,N131,0))) | T131: =IF(B131="","",FYPremium+(MIN(PayYear,B131)-1)*CYPremium) | U131: =IF(B131="","",OFFSET(宣告利率!$Y$2,B131,0)) | V131: =IF(B131="","",P131+N131) | W131: =IF(B131="","",V131/D131) | X131: =IF(B131="","",IF(C131=109,0,Q131+N131)) | Y131: =IF(B131="","",IF(OR(B131<PayYear,C131=109),"-",X131/D131)) | Z131: =IF(B131="","",O131/D131) | AA131: =AND(INDIRECT("B"&ROW())>0,MOD(INDIRECT("B"&ROW()),5)=0) -> #VALUE!
B132: =IF(B131="","",IF(C131=險種基本資料!$B$21,"",B131+1)) | C132: =IF(B132="","",Age+B132-1) | D132: =IF(B132="","",OFFSET(宣告利率!$I$2,B132,0)) | E132: =IF(B132="","",OFFSET(宣告利率!$M$2,B132,0)+OFFSET(宣告利率!$K$2,B132,0)) | F132: =IF(B132="","",OFFSET(宣告利率!$L$2,B132,0)+OFFSET(宣告利率!$K$2,B132,0)) | G132: =IF(B132="","",OFFSET(宣告利率!$J$2,B132,0)) | H132: =IF(B132="","",OFFSET(宣告利率!$G$2,B132,0)) | I132: =IF(B132="","",IF(C132<16,0,IF(C132=16,OFFSET(宣告利率!$O$2,B132-1,0),0)+OFFSET(宣告利率!$O$2,B132,0))) | J132: =IF(B132="","",IF(C132<16,0,OFFSET(宣告利率!$P$2,B132,0))) | K132: =IF(B132="","",IF(C132<16,OFFSET(宣告利率!$N$2,B132,0)+OFFSET(宣告利率!$U$2,B132,0),OFFSET(宣告利率!$Q$2,B132,0)+OFFSET(宣告利率!$U$2,B132,0))) | L132: =IF(B132="","",IF(C132<16,OFFSET(宣告利率!$N$2,B132,0),OFFSET(宣告利率!$Q$2,B132,0)+OFFSET(宣告利率!$U$2,B132,0))) | M132: =IF(B132="","",IF(OR(ZDIVOPT02=CSWD,ZDIVOPT02=DVAC),OFFSET(宣告利率!$R$2,B132,0),0)) | N132: =IF(B132="","",IF(ZDIVOPT02=CSWD,OFFSET(宣告利率!$S$2,B132,0),IF(ZDIVOPT02=DVAC,OFFSET(宣告利率!$T$2,B132,0),0))) | O132: =IF(B132="","",IF(C132<0,0,OFFSET(宣告利率!$J$2,B132,0)+MAX(OFFSET(宣告利率!$V$2,B132,0,1,3)))) | P132: =IF(B132="","",F132+L132) | Q132: =IF(B132="","",IF(C132=109,0,OFFSET(宣告利率!$AB$2,B132,0)+OFFSET(宣告利率!$AC$2,B132,0))) | R132: =IF(B132="","",P132+IF(ZDIVOPT02=CSWD,M132,0)+IF(ZDIVOPT02=DVAC,N132,0)) | S132: =IF(C132=109,0,IF(B132="","",Q132+IF(ZDIVOPT02=CSWD,M132,0)+IF(ZDIVOPT02=DVAC,N132,0))) | T132: =IF(B132="","",FYPremium+(MIN(PayYear,B132)-1)*CYPremium) | U132: =IF(B132="","",OFFSET(宣告利率!$Y$2,B132,0)) | V132: =IF(B132="","",P132+N132) | W132: =IF(B132="","",V132/D132) | X132: =IF(B132="","",IF(C132=109,0,Q132+N132)) | Y132: =IF(B132="","",IF(OR(B132<PayYear,C132=109),"-",X132/D132)) | Z132: =IF(B132="","",O132/D132) | AA132: =AND(INDIRECT("B"&ROW())>0,MOD(INDIRECT("B"&ROW()),5)=0) -> #VALUE!
B133: =IF(B132="","",IF(C132=險種基本資料!$B$21,"",B132+1)) | C133: =IF(B133="","",Age+B133-1) | D133: =IF(B133="","",OFFSET(宣告利率!$I$2,B133,0)) | E133: =IF(B133="","",OFFSET(宣告利率!$M$2,B133,0)+OFFSET(宣告利率!$K$2,B133,0)) | F133: =IF(B133="","",OFFSET(宣告利率!$L$2,B133,0)+OFFSET(宣告利率!$K$2,B133,0)) | G133: =IF(B133="","",OFFSET(宣告利率!$J$2,B133,0)) | H133: =IF(B133="","",OFFSET(宣告利率!$G$2,B133,0)) | I133: =IF(B133="","",IF(C133<16,0,IF(C133=16,OFFSET(宣告利率!$O$2,B133-1,0),0)+OFFSET(宣告利率!$O$2,B133,0))) | J133: =IF(B133="","",IF(C133<16,0,OFFSET(宣告利率!$P$2,B133,0))) | K133: =IF(B133="","",IF(C133<16,OFFSET(宣告利率!$N$2,B133,0)+OFFSET(宣告利率!$U$2,B133,0),OFFSET(宣告利率!$Q$2,B133,0)+OFFSET(宣告利率!$U$2,B133,0))) | L133: =IF(B133="","",IF(C133<16,OFFSET(宣告利率!$N$2,B133,0),OFFSET(宣告利率!$Q$2,B133,0)+OFFSET(宣告利率!$U$2,B133,0))) | M133: =IF(B133="","",IF(OR(ZDIVOPT02=CSWD,ZDIVOPT02=DVAC),OFFSET(宣告利率!$R$2,B133,0),0)) | N133: =IF(B133="","",IF(ZDIVOPT02=CSWD,OFFSET(宣告利率!$S$2,B133,0),IF(ZDIVOPT02=DVAC,OFFSET(宣告利率!$T$2,B133,0),0))) | O133: =IF(B133="","",IF(C133<0,0,OFFSET(宣告利率!$J$2,B133,0)+MAX(OFFSET(宣告利率!$V$2,B133,0,1,3)))) | P133: =IF(B133="","",F133+L133) | Q133: =IF(B133="","",IF(C133=109,0,OFFSET(宣告利率!$AB$2,B133,0)+OFFSET(宣告利率!$AC$2,B133,0))) | R133: =IF(B133="","",P133+IF(ZDIVOPT02=CSWD,M133,0)+IF(ZDIVOPT02=DVAC,N133,0)) | S133: =IF(C133=109,0,IF(B133="","",Q133+IF(ZDIVOPT02=CSWD,M133,0)+IF(ZDIVOPT02=DVAC,N133,0))) | T133: =IF(B133="","",FYPremium+(MIN(PayYear,B133)-1)*CYPremium) | U133: =IF(B133="","",OFFSET(宣告利率!$Y$2,B133,0)) | V133: =IF(B133="","",P133+N133) | W133: =IF(B133="","",V133/D133) | X133: =IF(B133="","",IF(C133=109,0,Q133+N133)) | Y133: =IF(B133="","",IF(OR(B133<PayYear,C133=109),"-",X133/D133)) | Z133: =IF(B133="","",O133/D133) | AA133: =AND(INDIRECT("B"&ROW())>0,MOD(INDIRECT("B"&ROW()),5)=0) -> #VALUE!
B134: =IF(B133="","",IF(C133=險種基本資料!$B$21,"",B133+1)) | C134: =IF(B134="","",Age+B134-1) | D134: =IF(B134="","",OFFSET(宣告利率!$I$2,B134,0)) | E134: =IF(B134="","",OFFSET(宣告利率!$M$2,B134,0)+OFFSET(宣告利率!$K$2,B134,0)) | F134: =IF(B134="","",OFFSET(宣告利率!$L$2,B134,0)+OFFSET(宣告利率!$K$2,B134,0)) | G134: =IF(B134="","",OFFSET(宣告利率!$J$2,B134,0)) | H134: =IF(B134="","",OFFSET(宣告利率!$G$2,B134,0)) | I134: =IF(B134="","",IF(C134<16,0,IF(C134=16,OFFSET(宣告利率!$O$2,B134-1,0),0)+OFFSET(宣告利率!$O$2,B134,0))) | J134: =IF(B134="","",IF(C134<16,0,OFFSET(宣告利率!$P$2,B134,0))) | K134: =IF(B134="","",IF(C134<16,OFFSET(宣告利率!$N$2,B134,0)+OFFSET(宣告利率!$U$2,B134,0),OFFSET(宣告利率!$Q$2,B134,0)+OFFSET(宣告利率!$U$2,B134,0))) | L134: =IF(B134="","",IF(C134<16,OFFSET(宣告利率!$N$2,B134,0),OFFSET(宣告利率!$Q$2,B134,0)+OFFSET(宣告利率!$U$2,B134,0))) | M134: =IF(B134="","",IF(OR(ZDIVOPT02=CSWD,ZDIVOPT02=DVAC),OFFSET(宣告利率!$R$2,B134,0),0)) | N134: =IF(B134="","",IF(ZDIVOPT02=CSWD,OFFSET(宣告利率!$S$2,B134,0),IF(ZDIVOPT02=DVAC,OFFSET(宣告利率!$T$2,B134,0),0))) | O134: =IF(B134="","",IF(C134<0,0,OFFSET(宣告利率!$J$2,B134,0)+MAX(OFFSET(宣告利率!$V$2,B134,0,1,3)))) | P134: =IF(B134="","",F134+L134) | Q134: =IF(B134="","",IF(C134=109,0,OFFSET(宣告利率!$AB$2,B134,0)+OFFSET(宣告利率!$AC$2,B134,0))) | R134: =IF(B134="","",P134+IF(ZDIVOPT02=CSWD,M134,0)+IF(ZDIVOPT02=DVAC,N134,0)) | S134: =IF(C134=109,0,IF(B134="","",Q134+IF(ZDIVOPT02=CSWD,M134,0)+IF(ZDIVOPT02=DVAC,N134,0))) | T134: =IF(B134="","",FYPremium+(MIN(PayYear,B134)-1)*CYPremium) | U134: =IF(B134="","",OFFSET(宣告利率!$Y$2,B134,0)) | V134: =IF(B134="","",P134+N134) | W134: =IF(B134="","",V134/D134) | X134: =IF(B134="","",IF(C134=109,0,Q134+N134)) | Y134: =IF(B134="","",IF(OR(B134<PayYear,C134=109),"-",X134/D134)) | Z134: =IF(B134="","",O134/D134) | AA134: =AND(INDIRECT("B"&ROW())>0,MOD(INDIRECT("B"&ROW()),5)=0) -> #VALUE!
... B141: =IF(B140="","",IF(C140=險種基本資料!$B$21,"",B140+1)) | C141: =IF(B141="","",Age+B141-1) | D141: =IF(B141="","",OFFSET(宣告利率!$I$2,B141,0)) | E141: =IF(B141="","",OFFSET(宣告利率!$M$2,B141,0)+OFFSET(宣告利率!$K$2,B141,0)) | F141: =IF(B141="","",OFFSET(宣告利率!$L$2,B141,0)+OFFSET(宣告利率!$K$2,B141,0)) | G141: =IF(B141="","",OFFSET(宣告利率!$J$2,B141,0)) | H141: =IF(B141="","",OFFSET(宣告利率!$G$2,B141,0)) | I141: =IF(B141="","",IF(C141<16,0,IF(C141=16,OFFSET(宣告利率!$O$2,B141-1,0),0)+OFFSET(宣告利率!$O$2,B141,0))) | J141: =IF(B141="","",IF(C141<16,0,OFFSET(宣告利率!$P$2,B141,0))) | K141: =IF(B141="","",IF(C141<16,OFFSET(宣告利率!$N$2,B141,0)+OFFSET(宣告利率!$U$2,B141,0),OFFSET(宣告利率!$Q$2,B141,0)+OFFSET(宣告利率!$U$2,B141,0))) | L141: =IF(B141="","",IF(C141<16,OFFSET(宣告利率!$N$2,B141,0),OFFSET(宣告利率!$Q$2,B141,0)+OFFSET(宣告利率!$U$2,B141,0))) | M141: =IF(B141="","",IF(OR(ZDIVOPT02=CSWD,ZDIVOPT02=DVAC),OFFSET(宣告利率!$R$2,B141,0),0)) | N141: =IF(B141="","",IF(ZDIVOPT02=CSWD,OFFSET(宣告利率!$S$2,B141,0),IF(ZDIVOPT02=DVAC,OFFSET(宣告利率!$T$2,B141,0),0))) | O141: =IF(B141="","",IF(C141<0,0,OFFSET(宣告利率!$J$2,B141,0)+MAX(OFFSET(宣告利率!$V$2,B141,0,1,3)))) | P141: =IF(B141="","",F141+L141) | Q141: =IF(B141="","",IF(C141=109,0,OFFSET(宣告利率!$AB$2,B141,0)+OFFSET(宣告利率!$AC$2,B141,0))) | R141: =IF(B141="","",P141+IF(ZDIVOPT02=CSWD,M141,0)+IF(ZDIVOPT02=DVAC,N141,0)) | S141: =IF(C141=109,0,IF(B141="","",Q141+IF(ZDIVOPT02=CSWD,M141,0)+IF(ZDIVOPT02=DVAC,N141,0))) | T141: =IF(B141="","",FYPremium+(MIN(PayYear,B141)-1)*CYPremium) | U141: =IF(B141="","",OFFSET(宣告利率!$Y$2,B141,0)) | V141: =IF(B141="","",P141+N141) | W141: =IF(B141="","",V141/D141) | X141: =IF(B141="","",IF(C141=109,0,Q141+N141)) | Y141: =IF(B141="","",IF(OR(B141<PayYear,C141=109),"-",X141/D141)) | Z141: =IF(B141="","",O141/D141) | AA141: =AND(INDIRECT("B"&ROW())>0,MOD(INDIRECT("B"&ROW()),5)=0) -> #VALUE!
B142: 【情境二】 | Q142: 單位：美元 | AA142: =AND(INDIRECT("B"&ROW())>0,MOD(INDIRECT("B"&ROW()),5)=0) -> #VALUE!
B143: =B17 -> 保單 年度 (末) | C143: =C17 -> 保險 年齡 | D143: =D17 -> 累積所繳保險費 (A) | E143: =E17 -> 基本保險金額對應之保單價值準備金 【含祝壽保險金】 | F143: =F17 -> 基本保險金額 對應之現金價值 【含祝壽保險金】 (B) | G143: =G17 -> 基本保險金額 對應之壽險保障 (身故保險金) | J143: ="假設投保後未來各保單年度宣告利率為"&TEXT(PDRate,"0.00")&"% (下表為預估假設值)" -> 假設投保後未來各保單年度宣告利率為1.75% (下表為預估假設值) | R143: =R17 -> 年度末終止契約時合計可領取之金額(含增值回饋分享金) (F) | S143: =S17 -> 次年度期初終止契約時合計可領取之金額(含增值回饋分享金) (H)=(G) | T143: =T17 -> 累積 應繳保費 | U143: =U17 -> 期末保單價值準備金(含基本保險金額、累計增加保險金額) 【含祝壽保險金】 | V143: =V17 -> (E)+(F) | W143: =W17 -> ((E)+(F))/(A) | X143: =X17 -> (G)+(E) | Y143: =Y17 -> ((G)+(E))/(A) | Z143: =Z17 -> (I)/(A) | AA143: =AND(INDIRECT("B"&ROW())>0,MOD(INDIRECT("B"&ROW()),5)=0) -> #VALUE!
...

Sheet 簡易版-試算頁
B2: =資料輸入區!B2 -> 凱基人壽美利成臻美元利率變動型終身壽險－定期給付型
K3: 單位：美元
B4: 性 別： | D4: =Sex -> 男性 | E4: 繳費期間： | F4: =IF(PayYear=1,"躉繳",PayYear&"年期") -> 躉繳 | I4: ='明細版-試算頁'!L4 -> 經費率折減後躉繳保費： | J4: ='明細版-試算頁'!O4 -> 2655727 | K4: =IF(資料輸入區!E13="月","※月繳件首期須繳交2個月保費","")
B5: 保險年齡： | D5: =Age -> 71 | E5: 繳費方式： | F5: =資料輸入區!E13&"繳" -> 躉繳 | I5: ='明細版-試算頁'!L5 -> 續期繳交保險費(經費率折減後)： | J5: ='明細版-試算頁'!O5 -> -7583744280120
B6: 本月宣告利率(假設值)： | D6: =DecareRate -> 4.35 | E6: 投保金額： | F6: =SA -> 3701867 | I6: ='明細版-試算頁'!L6 -> 高保費費率折減： | J6: ='明細版-試算頁'!O6 -> 0.07
B7: 預定利率： | D7: =PDRate -> 1.75 | E7: 原始保費： | F7: =資料輸入區!N14 -> 2855620 | I7: ='明細版-試算頁'!L7 -> 續期高保費與金融機構轉帳費率折減： | J7: ='明細版-試算頁'!O7 -> 2,655,727
C9: 各保單年度末 增值回饋分享金選擇給付方式： | E9: ='明細版-試算頁'!G9 | G9: ='明細版-試算頁'!J9 | I9: ='明細版-試算頁'!M9
E10: ='明細版-試算頁'!G10 | G10: ='明細版-試算頁'!J10
E11: ='明細版-試算頁'!G11 -> 第1保單年度起 | G11: ='明細版-試算頁'!J11 -> 以繳清保險方式增加保險金額
E12: ='明細版-試算頁'!G12 | G12: ='明細版-試算頁'!J12
B13: ='明細版-試算頁'!B13
D14: 契約生效日首日預估保單價值準備金： | E14: ='明細版-試算頁'!G14 -> 2462814 | F14: 契約生效首日預估現金價值(解約金)： | H14: ='明細版-試算頁'!M14 -> 2265614
K16: 單位：美元
C17: 2 | D17: 3 | E17: 14 | G17: =IF(ZDIVOPT02=DVAC,13,12) -> 12 | H17: 15 | J17: 16
B18: ='明細版-試算頁'!B17 -> 保單 年度 (末) | C18: =OFFSET('明細版-試算頁'!A17,0,C17) -> 保險 年齡 | D18: =OFFSET('明細版-試算頁'!A17,0,D17) -> 累積所繳保險費 (A) | E18: ='明細版-試算頁'!J17 -> 假設投保後未來各保單年度宣告利率為4.35% (下表為預估假設值)
E19: 含「基本保險金額、累計增加保險金額」 | G19: ="選擇"&IF(ZDIVOPT02=DVAC,DVAC,CSWD) -> 選擇現金給付 | H19: 含「基本保險金額、累計增加保險金額」 | L19: ="(F)="&IF(ZDIVOPT02=DVAC,"(C)","(B)")&"+(D)" -> (F)=(B)+(D) | M19: ="(G)="&IF(ZDIVOPT02=DVAC,"(C)","(B)")&"+(E)" -> (G)=(B)+(E)
E20: 壽險保障 (身故保險金) | G20: =REPLACE(OFFSET('明細版-試算頁'!A19,0,G17),LEN(OFFSET('明細版-試算頁'!A19,0,G17))-2,3,IF(ZDIVOPT02=DVAC,"(C)","(B)")) -> 增值回饋 分享金 (B) | H20: =SUBSTITUTE(OFFSET('明細版-試算頁'!A19,0,H17),"(F)=(B)+(C)","(D)") -> 年度末現金價值 【含祝壽保險金】 (D) | J20: =SUBSTITUTE(OFFSET('明細版-試算頁'!A19,0,J17),"G","E") -> 次年度期初 現金價值 (E)
B21: 1 | C21: =IF($B21="","",VLOOKUP($B21,'明細版-試算頁'!$B$17:$AD$141,C$17,FALSE)) -> 71 | D21: =IF($B21="","",VLOOKUP($B21,'明細版-試算頁'!$B$17:$AD$141,D$17,FALSE)) -> 2655727 | E21: =IF($B21="","",VLOOKUP($B21,'明細版-試算頁'!$B$17:$AD$141,E$17,FALSE)) -> 2855620 | F21: #VALUE! | G21: =IF($B21="","",VLOOKUP($B21,'明細版-試算頁'!$B$17:$AD$141,G$17,FALSE)) -> 0 | H21: =IF($B21="","",VLOOKUP($B21,'明細版-試算頁'!$B$17:$AD$141,H$17,FALSE)) -> 2370304 | I21: #VALUE! | J21: =IF($B21="","",VLOOKUP($B21,'明細版-試算頁'!$B$17:$AD$141,J$17,FALSE)) -> 2370400 | K21: #VALUE! | L21: =IF(B21="","",G21+H21) -> 2370304 | M21: =IF(J21="","",IF(J21=0,0,G21+J21)) -> 2370400
B22: =IF(B21="","",IF(C21=109,"",B21+1)) -> 2 | C22: =IF($B22="","",VLOOKUP($B22,'明細版-試算頁'!$B$17:$AD$141,C$17,FALSE)) -> 72 | D22: =IF($B22="","",VLOOKUP($B22,'明細版-試算頁'!$B$17:$AD$141,D$17,FALSE)) -> 2655727 | E22: =IF($B22="","",VLOOKUP($B22,'明細版-試算頁'!$B$17:$AD$141,E$17,FALSE)) -> 2929866 | F22: #VALUE! | G22: =IF($B22="","",VLOOKUP($B22,'明細版-試算頁'!$B$17:$AD$141,G$17,FALSE)) -> 0 | H22: =IF($B22="","",VLOOKUP($B22,'明細版-試算頁'!$B$17:$AD$141,H$17,FALSE)) -> 2473136 | I22: #VALUE! | J22: =IF($B22="","",VLOOKUP($B22,'明細版-試算頁'!$B$17:$AD$141,J$17,FALSE)) -> 2650932 | K22: #VALUE! | L22: =IF(B22="","",G22+H22) -> 2473136 | M22: =IF(J22="","",IF(J22=0,0,G22+J22)) -> 2650932
B23: =IF(B22="","",IF(C22=109,"",B22+1)) -> 3 | C23: =IF($B23="","",VLOOKUP($B23,'明細版-試算頁'!$B$17:$AD$141,C$17,FALSE)) -> 73 | D23: =IF($B23="","",VLOOKUP($B23,'明細版-試算頁'!$B$17:$AD$141,D$17,FALSE)) -> 2655727 | E23: =IF($B23="","",VLOOKUP($B23,'明細版-試算頁'!$B$17:$AD$141,E$17,FALSE)) -> 3006043 | F23: #VALUE! | G23: =IF($B23="","",VLOOKUP($B23,'明細版-試算頁'!$B$17:$AD$141,G$17,FALSE)) -> 0 | H23: =IF($B23="","",VLOOKUP($B23,'明細版-試算頁'!$B$17:$AD$141,H$17,FALSE)) -> 2760423 | I23: #VALUE! | J23: =IF($B23="","",VLOOKUP($B23,'明細版-試算頁'!$B$17:$AD$141,J$17,FALSE)) -> 2760534 | K23: #VALUE! | L23: =IF(B23="","",G23+H23) -> 2760423 | M23: =IF(J23="","",IF(J23=0,0,G23+J23)) -> 2760534
B24: =IF(B23="","",IF(C23=109,"",B23+1)) -> 4 | C24: =IF($B24="","",VLOOKUP($B24,'明細版-試算頁'!$B$17:$AD$141,C$17,FALSE)) -> 74 | D24: =IF($B24="","",VLOOKUP($B24,'明細版-試算頁'!$B$17:$AD$141,D$17,FALSE)) -> 2655727 | E24: =IF($B24="","",VLOOKUP($B24,'明細版-試算頁'!$B$17:$AD$141,E$17,FALSE)) -> 3084200 | F24: #VALUE! | G24: =IF($B24="","",VLOOKUP($B24,'明細版-試算頁'!$B$17:$AD$141,G$17,FALSE)) -> 0 | H24: =IF($B24="","",VLOOKUP($B24,'明細版-試算頁'!$B$17:$AD$141,H$17,FALSE)) -> 2874749 | I24: #VALUE! | J24: =IF($B24="","",VLOOKUP($B24,'明細版-試算頁'!$B$17:$AD$141,J$17,FALSE)) -> 2874793 | K24: #VALUE! | L24: =IF(B24="","",G24+H24) -> 2874749 | M24: =IF(J24="","",IF(J24=0,0,G24+J24)) -> 2874793
B25: =IF(B24="","",IF(C24=109,"",B24+1)) -> 5 | C25: =IF($B25="","",VLOOKUP($B25,'明細版-試算頁'!$B$17:$AD$141,C$17,FALSE)) -> 75 | D25: =IF($B25="","",VLOOKUP($B25,'明細版-試算頁'!$B$17:$AD$141,D$17,FALSE)) -> 2655727 | E25: =IF($B25="","",VLOOKUP($B25,'明細版-試算頁'!$B$17:$AD$141,E$17,FALSE)) -> 4102138 | F25: #VALUE! | G25: =IF($B25="","",VLOOKUP($B25,'明細版-試算頁'!$B$17:$AD$141,G$17,FALSE)) -> 0 | H25: =IF($B25="","",VLOOKUP($B25,'明細版-試算頁'!$B$17:$AD$141,H$17,FALSE)) -> 2966590 | I25: #VALUE! | J25: =IF($B25="","",VLOOKUP($B25,'明細版-試算頁'!$B$17:$AD$141,J$17,FALSE)) -> 2966628 | K25: #VALUE! | L25: =IF(B25="","",G25+H25) -> 2966590 | M25: =IF(J25="","",IF(J25=0,0,G25+J25)) -> 2966628
B26: =IF(B25="","",IF(C25=109,"",B25+1)) -> 6 | C26: =IF($B26="","",VLOOKUP($B26,'明細版-試算頁'!$B$17:$AD$141,C$17,FALSE)) -> 76 | D26: =IF($B26="","",VLOOKUP($B26,'明細版-試算頁'!$B$17:$AD$141,D$17,FALSE)) -> 2655727 | E26: =IF($B26="","",VLOOKUP($B26,'明細版-試算頁'!$B$17:$AD$141,E$17,FALSE)) -> 4208794 | F26: #VALUE! | G26: =IF($B26="","",VLOOKUP($B26,'明細版-試算頁'!$B$17:$AD$141,G$17,FALSE)) -> 0 | H26: =IF($B26="","",VLOOKUP($B26,'明細版-試算頁'!$B$17:$AD$141,H$17,FALSE)) -> 3058656 | I26: #VALUE! | J26: =IF($B26="","",VLOOKUP($B26,'明細版-試算頁'!$B$17:$AD$141,J$17,FALSE)) -> 3084969 | K26: #VALUE! | L26: =IF(B26="","",G26+H26) -> 3058656 | M26: =IF(J26="","",IF(J26=0,0,G26+J26)) -> 3084969
B27: =IF(B26="","",IF(C26=109,"",B26+1)) -> 7 | C27: =IF($B27="","",VLOOKUP($B27,'明細版-試算頁'!$B$17:$AD$141,C$17,FALSE)) -> 77 | D27: =IF($B27="","",VLOOKUP($B27,'明細版-試算頁'!$B$17:$AD$141,D$17,FALSE)) -> 2655727 | E27: =IF($B27="","",VLOOKUP($B27,'明細版-試算頁'!$B$17:$AD$141,E$17,FALSE)) -> 4318223 | F27: #VALUE! | G27: =IF($B27="","",VLOOKUP($B27,'明細版-試算頁'!$B$17:$AD$141,G$17,FALSE)) -> 0 | H27: =IF($B27="","",VLOOKUP($B27,'明細版-試算頁'!$B$17:$AD$141,H$17,FALSE)) -> 3176666 | I27: #VALUE! | J27: =IF($B27="","",VLOOKUP($B27,'明細版-試算頁'!$B$17:$AD$141,J$17,FALSE)) -> 3176686 | K27: #VALUE! | L27: =IF(B27="","",G27+H27) -> 3176666 | M27: =IF(J27="","",IF(J27=0,0,G27+J27)) -> 3176686
B28: =IF(B27="","",IF(C27=109,"",B27+1)) -> 8 | C28: =IF($B28="","",VLOOKUP($B28,'明細版-試算頁'!$B$17:$AD$141,C$17,FALSE)) -> 78 | D28: =IF($B28="","",VLOOKUP($B28,'明細版-試算頁'!$B$17:$AD$141,D$17,FALSE)) -> 2655727 | E28: =IF($B28="","",VLOOKUP($B28,'明細版-試算頁'!$B$17:$AD$141,E$17,FALSE)) -> 4430496 | F28: #VALUE! | G28: =IF($B28="","",VLOOKUP($B28,'明細版-試算頁'!$B$17:$AD$141,G$17,FALSE)) -> 0 | H28: =IF($B28="","",VLOOKUP($B28,'明細版-試算頁'!$B$17:$AD$141,H$17,FALSE)) -> 3266987 | I28: #VALUE! | J28: =IF($B28="","",VLOOKUP($B28,'明細版-試算頁'!$B$17:$AD$141,J$17,FALSE)) -> 3266995 | K28: #VALUE! | L28: =IF(B28="","",G28+H28) -> 3266987 | M28: =IF(J28="","",IF(J28=0,0,G28+J28)) -> 3266995
B29: =IF(B28="","",IF(C28=109,"",B28+1)) -> 9 | C29: =IF($B29="","",VLOOKUP($B29,'明細版-試算頁'!$B$17:$AD$141,C$17,FALSE)) -> 79 | D29: =IF($B29="","",VLOOKUP($B29,'明細版-試算頁'!$B$17:$AD$141,D$17,FALSE)) -> 2655727 | E29: =IF($B29="","",VLOOKUP($B29,'明細版-試算頁'!$B$17:$AD$141,E$17,FALSE)) -> 4545689 | F29: #VALUE! | G29: =IF($B29="","",VLOOKUP($B29,'明細版-試算頁'!$B$17:$AD$141,G$17,FALSE)) -> 0 | H29: =IF($B29="","",VLOOKUP($B29,'明細版-試算頁'!$B$17:$AD$141,H$17,FALSE)) -> 3355192 | I29: #VALUE! | J29: =IF($B29="","",VLOOKUP($B29,'明細版-試算頁'!$B$17:$AD$141,J$17,FALSE)) -> 3355187 | K29: #VALUE! | L29: =IF(B29="","",G29+H29) -> 3355192 | M29: =IF(J29="","",IF(J29=0,0,G29+J29)) -> 3355187
B30: =IF(B29="","",IF(C29=109,"",B29+1)) -> 10 | C30: =IF($B30="","",VLOOKUP($B30,'明細版-試算頁'!$B$17:$AD$141,C$17,FALSE)) -> 80 | D30: =IF($B30="","",VLOOKUP($B30,'明細版-試算頁'!$B$17:$AD$141,D$17,FALSE)) -> 2655727 | E30: =IF($B30="","",VLOOKUP($B30,'明細版-試算頁'!$B$17:$AD$141,E$17,FALSE)) -> 4663876 | F30: #VALUE! | G30: =IF($B30="","",VLOOKUP($B30,'明細版-試算頁'!$B$17:$AD$141,G$17,FALSE)) -> 0 | H30: =IF($B30="","",VLOOKUP($B30,'明細版-試算頁'!$B$17:$AD$141,H$17,FALSE)) -> 3440512 | I30: #VALUE! | J30: =IF($B30="","",VLOOKUP($B30,'明細版-試算頁'!$B$17:$AD$141,J$17,FALSE)) -> 3440505 | K30: #VALUE! | L30: =IF(B30="","",G30+H30) -> 3440512 | M30: =IF(J30="","",IF(J30=0,0,G30+J30)) -> 3440505
B31: =IF(B30="","",IF(C30=109,"",B30+1)) -> 11 | C31: =IF($B31="","",VLOOKUP($B31,'明細版-試算頁'!$B$17:$AD$141,C$17,FALSE)) -> 81 | D31: =IF($B31="","",VLOOKUP($B31,'明細版-試算頁'!$B$17:$AD$141,D$17,FALSE)) -> 2655727 | E31: =IF($B31="","",VLOOKUP($B31,'明細版-試算頁'!$B$17:$AD$141,E$17,FALSE)) -> 4689434 | F31: #VALUE! | G31: =IF($B31="","",VLOOKUP($B31,'明細版-試算頁'!$B$17:$AD$141,G$17,FALSE)) -> 0 | H31: =IF($B31="","",VLOOKUP($B31,'明細版-試算頁'!$B$17:$AD$141,H$17,FALSE)) -> 3527020 | I31: #VALUE! | J31: =IF($B31="","",VLOOKUP($B31,'明細版-試算頁'!$B$17:$AD$141,J$17,FALSE)) -> 3527008 | K31: #VALUE! | L31: =IF(B31="","",G31+H31) -> 3527020 | M31: =IF(J31="","",IF(J31=0,0,G31+J31)) -> 3527008
B32: =IF(B31="","",IF(C31=109,"",B31+1)) -> 12 | C32: =IF($B32="","",VLOOKUP($B32,'明細版-試算頁'!$B$17:$AD$141,C$17,FALSE)) -> 82 | D32: =IF($B32="","",VLOOKUP($B32,'明細版-試算頁'!$B$17:$AD$141,D$17,FALSE)) -> 2655727 | E32: =IF($B32="","",VLOOKUP($B32,'明細版-試算頁'!$B$17:$AD$141,E$17,FALSE)) -> 4715132 | F32: #VALUE! | G32: =IF($B32="","",VLOOKUP($B32,'明細版-試算頁'!$B$17:$AD$141,G$17,FALSE)) -> 0 | H32: =IF($B32="","",VLOOKUP($B32,'明細版-試算頁'!$B$17:$AD$141,H$17,FALSE)) -> 3614191 | I32: #VALUE! | J32: =IF($B32="","",VLOOKUP($B32,'明細版-試算頁'!$B$17:$AD$141,J$17,FALSE)) -> 3614175 | K32: #VALUE! | L32: =IF(B32="","",G32+H32) -> 3614191 | M32: =IF(J32="","",IF(J32=0,0,G32+J32)) -> 3614175
B33: =IF(B32="","",IF(C32=109,"",B32+1)) -> 13 | C33: =IF($B33="","",VLOOKUP($B33,'明細版-試算頁'!$B$17:$AD$141,C$17,FALSE)) -> 83 | D33: =IF($B33="","",VLOOKUP($B33,'明細版-試算頁'!$B$17:$AD$141,D$17,FALSE)) -> 2655727 | E33: =IF($B33="","",VLOOKUP($B33,'明細版-試算頁'!$B$17:$AD$141,E$17,FALSE)) -> 4741011 | F33: #VALUE! | G33: =IF($B33="","",VLOOKUP($B33,'明細版-試算頁'!$B$17:$AD$141,G$17,FALSE)) -> 0 | H33: =IF($B33="","",VLOOKUP($B33,'明細版-試算頁'!$B$17:$AD$141,H$17,FALSE)) -> 3702475 | I33: #VALUE! | J33: =IF($B33="","",VLOOKUP($B33,'明細版-試算頁'!$B$17:$AD$141,J$17,FALSE)) -> 3702457 | K33: #VALUE! | L33: =IF(B33="","",G33+H33) -> 3702475 | M33: =IF(J33="","",IF(J33=0,0,G33+J33)) -> 3702457
... B35: =IF(B34="","",IF(C34=109,"",B34+1)) -> 15 | C35: =IF($B35="","",VLOOKUP($B35,'明細版-試算頁'!$B$17:$AD$141,C$17,FALSE)) -> 85 | D35: =IF($B35="","",VLOOKUP($B35,'明細版-試算頁'!$B$17:$AD$141,D$17,FALSE)) -> 2655727 | E35: =IF($B35="","",VLOOKUP($B35,'明細版-試算頁'!$B$17:$AD$141,E$17,FALSE)) -> 4793495 | F35: #VALUE! | G35: =IF($B35="","",VLOOKUP($B35,'明細版-試算頁'!$B$17:$AD$141,G$17,FALSE)) -> 0 | H35: =IF($B35="","",VLOOKUP($B35,'明細版-試算頁'!$B$17:$AD$141,H$17,FALSE)) -> 3883905 | I35: #VALUE! | J35: =IF($B35="","",VLOOKUP($B35,'明細版-試算頁'!$B$17:$AD$141,J$17,FALSE)) -> 3883886 | K35: #VALUE! | L35: =IF(B35="","",G35+H35) -> 3883905 | M35: =IF(J35="","",IF(J35=0,0,G35+J35)) -> 3883886
B36: =$B$18 -> 保單 年度 (末) | C36: =$C$18 -> 保險 年齡 | D36: =$D$18 -> 累積所繳保險費 (A) | E36: =$E$18 -> 假設投保後未來各保單年度宣告利率為4.35% (下表為預估假設值)
E37: =$E$19 -> 含「基本保險金額、累計增加保險金額」 | G37: =$G$19 -> 選擇現金給付 | H37: =$H$19 -> 含「基本保險金額、累計增加保險金額」 | L37: =$L$19 -> (F)=(B)+(D) | M37: =$M$19 -> (G)=(B)+(E)
E38: =$E$20 -> 壽險保障 (身故保險金) | G38: =$G$20 -> 增值回饋 分享金 (B) | H38: =$H$20 -> 年度末現金價值 【含祝壽保險金】 (D) | J38: =$J$20 -> 次年度期初 現金價值 (E)
B39: =IF(B35="","",IF(C35=109,"",B35+1)) -> 16 | C39: =IF($B39="","",VLOOKUP($B39,'明細版-試算頁'!$B$17:$AD$141,C$17,FALSE)) -> 86 | D39: =IF($B39="","",VLOOKUP($B39,'明細版-試算頁'!$B$17:$AD$141,D$17,FALSE)) -> 2655727 | E39: =IF($B39="","",VLOOKUP($B39,'明細版-試算頁'!$B$17:$AD$141,E$17,FALSE)) -> 4819655 | F39: #VALUE! | G39: =IF($B39="","",VLOOKUP($B39,'明細版-試算頁'!$B$17:$AD$141,G$17,FALSE)) -> 0 | H39: =IF($B39="","",VLOOKUP($B39,'明細版-試算頁'!$B$17:$AD$141,H$17,FALSE)) -> 3977630 | I39: #VALUE! | J39: =IF($B39="","",VLOOKUP($B39,'明細版-試算頁'!$B$17:$AD$141,J$17,FALSE)) -> 3977610 | K39: #VALUE! | L39: =IF(B39="","",G39+H39) -> 3977630 | M39: =IF(J39="","",IF(J39=0,0,G39+J39)) -> 3977610
B40: =IF(B39="","",IF(C39=109,"",B39+1)) -> 17 | C40: =IF($B40="","",VLOOKUP($B40,'明細版-試算頁'!$B$17:$AD$141,C$17,FALSE)) -> 87 | D40: =IF($B40="","",VLOOKUP($B40,'明細版-試算頁'!$B$17:$AD$141,D$17,FALSE)) -> 2655727 | E40: =IF($B40="","",VLOOKUP($B40,'明細版-試算頁'!$B$17:$AD$141,E$17,FALSE)) -> 4846167 | F40: #VALUE! | G40: =IF($B40="","",VLOOKUP($B40,'明細版-試算頁'!$B$17:$AD$141,G$17,FALSE)) -> 0 | H40: =IF($B40="","",VLOOKUP($B40,'明細版-試算頁'!$B$17:$AD$141,H$17,FALSE)) -> 4073604 | I40: #VALUE! | J40: =IF($B40="","",VLOOKUP($B40,'明細版-試算頁'!$B$17:$AD$141,J$17,FALSE)) -> 4073589 | K40: #VALUE! | L40: =IF(B40="","",G40+H40) -> 4073604 | M40: =IF(J40="","",IF(J40=0,0,G40+J40)) -> 4073589
B41: =IF(B40="","",IF(C40=109,"",B40+1)) -> 18 | C41: =IF($B41="","",VLOOKUP($B41,'明細版-試算頁'!$B$17:$AD$141,C$17,FALSE)) -> 88 | D41: =IF($B41="","",VLOOKUP($B41,'明細版-試算頁'!$B$17:$AD$141,D$17,FALSE)) -> 2655727 | E41: =IF($B41="","",VLOOKUP($B41,'明細版-試算頁'!$B$17:$AD$141,E$17,FALSE)) -> 4872518 | F41: #VALUE! | G41: =IF($B41="","",VLOOKUP($B41,'明細版-試算頁'!$B$17:$AD$141,G$17,FALSE)) -> 0 | H41: =IF($B41="","",VLOOKUP($B41,'明細版-試算頁'!$B$17:$AD$141,H$17,FALSE)) -> 4173642 | I41: #VALUE! | J41: =IF($B41="","",VLOOKUP($B41,'明細版-試算頁'!$B$17:$AD$141,J$17,FALSE)) -> 4173633 | K41: #VALUE! | L41: =IF(B41="","",G41+H41) -> 4173642 | M41: =IF(J41="","",IF(J41=0,0,G41+J41)) -> 4173633
B42: =IF(B41="","",IF(C41=109,"",B41+1)) -> 19 | C42: =IF($B42="","",VLOOKUP($B42,'明細版-試算頁'!$B$17:$AD$141,C$17,FALSE)) -> 89 | D42: =IF($B42="","",VLOOKUP($B42,'明細版-試算頁'!$B$17:$AD$141,D$17,FALSE)) -> 2655727 | E42: =IF($B42="","",VLOOKUP($B42,'明細版-試算頁'!$B$17:$AD$141,E$17,FALSE)) -> 4899315 | F42: #VALUE! | G42: =IF($B42="","",VLOOKUP($B42,'明細版-試算頁'!$B$17:$AD$141,G$17,FALSE)) -> 0 | H42: =IF($B42="","",VLOOKUP($B42,'明細版-試算頁'!$B$17:$AD$141,H$17,FALSE)) -> 4278540 | I42: #VALUE! | J42: =IF($B42="","",VLOOKUP($B42,'明細版-試算頁'!$B$17:$AD$141,J$17,FALSE)) -> 4278540 | K42: #VALUE! | L42: =IF(B42="","",G42+H42) -> 4278540 | M42: =IF(J42="","",IF(J42=0,0,G42+J42)) -> 4278540
B43: =IF(B42="","",IF(C42=109,"",B42+1)) -> 20 | C43: =IF($B43="","",VLOOKUP($B43,'明細版-試算頁'!$B$17:$AD$141,C$17,FALSE)) -> 90 | D43: =IF($B43="","",VLOOKUP($B43,'明細版-試算頁'!$B$17:$AD$141,D$17,FALSE)) -> 2655727 | E43: =IF($B43="","",VLOOKUP($B43,'明細版-試算頁'!$B$17:$AD$141,E$17,FALSE)) -> 4926019 | F43: #VALUE! | G43: =IF($B43="","",VLOOKUP($B43,'明細版-試算頁'!$B$17:$AD$141,G$17,FALSE)) -> 0 | H43: =IF($B43="","",VLOOKUP($B43,'明細版-試算頁'!$B$17:$AD$141,H$17,FALSE)) -> 4389782 | I43: #VALUE! | J43: =IF($B43="","",VLOOKUP($B43,'明細版-試算頁'!$B$17:$AD$141,J$17,FALSE)) -> 4389795 | K43: #VALUE! | L43: =IF(B43="","",G43+H43) -> 4389782 | M43: =IF(J43="","",IF(J43=0,0,G43+J43)) -> 4389795
B44: =IF(B43="","",IF(C43=109,"",B43+1)) -> 21 | C44: =IF($B44="","",VLOOKUP($B44,'明細版-試算頁'!$B$17:$AD$141,C$17,FALSE)) -> 91 | D44: =IF($B44="","",VLOOKUP($B44,'明細版-試算頁'!$B$17:$AD$141,D$17,FALSE)) -> 2655727 | E44: =IF($B44="","",VLOOKUP($B44,'明細版-試算頁'!$B$17:$AD$141,E$17,FALSE)) -> 4953272 | F44: #VALUE! | G44: =IF($B44="","",VLOOKUP($B44,'明細版-試算頁'!$B$17:$AD$141,G$17,FALSE)) -> 0 | H44: =IF($B44="","",VLOOKUP($B44,'明細版-試算頁'!$B$17:$AD$141,H$17,FALSE)) -> 4508994 | I44: #VALUE! | J44: =IF($B44="","",VLOOKUP($B44,'明細版-試算頁'!$B$17:$AD$141,J$17,FALSE)) -> 4509032 | K44: #VALUE! | L44: =IF(B44="","",G44+H44) -> 4508994 | M44: =IF(J44="","",IF(J44=0,0,G44+J44)) -> 4509032
B45: =IF(B44="","",IF(C44=109,"",B44+1)) -> 22 | C45: =IF($B45="","",VLOOKUP($B45,'明細版-試算頁'!$B$17:$AD$141,C$17,FALSE)) -> 92 | D45: =IF($B45="","",VLOOKUP($B45,'明細版-試算頁'!$B$17:$AD$141,D$17,FALSE)) -> 2655727 | E45: =IF($B45="","",VLOOKUP($B45,'明細版-試算頁'!$B$17:$AD$141,E$17,FALSE)) -> 4980518 | F45: #VALUE! | G45: =IF($B45="","",VLOOKUP($B45,'明細版-試算頁'!$B$17:$AD$141,G$17,FALSE)) -> 0 | H45: =IF($B45="","",VLOOKUP($B45,'明細版-試算頁'!$B$17:$AD$141,H$17,FALSE)) -> 4640553 | I45: #VALUE! | J45: =IF($B45="","",VLOOKUP($B45,'明細版-試算頁'!$B$17:$AD$141,J$17,FALSE)) -> 4640620 | K45: #VALUE! | L45: =IF(B45="","",G45+H45) -> 4640553 | M45: =IF(J45="","",IF(J45=0,0,G45+J45)) -> 4640620
B46: =IF(B45="","",IF(C45=109,"",B45+1)) -> 23 | C46: =IF($B46="","",VLOOKUP($B46,'明細版-試算頁'!$B$17:$AD$141,C$17,FALSE)) -> 93 | D46: =IF($B46="","",VLOOKUP($B46,'明細版-試算頁'!$B$17:$AD$141,D$17,FALSE)) -> 2655727 | E46: =IF($B46="","",VLOOKUP($B46,'明細版-試算頁'!$B$17:$AD$141,E$17,FALSE)) -> 5022761 | F46: #VALUE! | G46: =IF($B46="","",VLOOKUP($B46,'明細版-試算頁'!$B$17:$AD$141,G$17,FALSE)) -> 0 | H46: =IF($B46="","",VLOOKUP($B46,'明細版-試算頁'!$B$17:$AD$141,H$17,FALSE)) -> 4786593 | I46: #VALUE! | J46: =IF($B46="","",VLOOKUP($B46,'明細版-試算頁'!$B$17:$AD$141,J$17,FALSE)) -> 4786658 | K46: #VALUE! | L46: =IF(B46="","",G46+H46) -> 4786593 | M46: =IF(J46="","",IF(J46=0,0,G46+J46)) -> 4786658
B47: =IF(B46="","",IF(C46=109,"",B46+1)) -> 24 | C47: =IF($B47="","",VLOOKUP($B47,'明細版-試算頁'!$B$17:$AD$141,C$17,FALSE)) -> 94 | D47: =IF($B47="","",VLOOKUP($B47,'明細版-試算頁'!$B$17:$AD$141,D$17,FALSE)) -> 2655727 | E47: =IF($B47="","",VLOOKUP($B47,'明細版-試算頁'!$B$17:$AD$141,E$17,FALSE)) -> 5153353 | F47: #VALUE! | G47: =IF($B47="","",VLOOKUP($B47,'明細版-試算頁'!$B$17:$AD$141,G$17,FALSE)) -> 0 | H47: =IF($B47="","",VLOOKUP($B47,'明細版-試算頁'!$B$17:$AD$141,H$17,FALSE)) -> 4935719 | I47: #VALUE! | J47: =IF($B47="","",VLOOKUP($B47,'明細版-試算頁'!$B$17:$AD$141,J$17,FALSE)) -> 4935783 | K47: #VALUE! | L47: =IF(B47="","",G47+H47) -> 4935719 | M47: =IF(J47="","",IF(J47=0,0,G47+J47)) -> 4935783
B48: =IF(B47="","",IF(C47=109,"",B47+1)) -> 25 | C48: =IF($B48="","",VLOOKUP($B48,'明細版-試算頁'!$B$17:$AD$141,C$17,FALSE)) -> 95 | D48: =IF($B48="","",VLOOKUP($B48,'明細版-試算頁'!$B$17:$AD$141,D$17,FALSE)) -> 2655727 | E48: =IF($B48="","",VLOOKUP($B48,'明細版-試算頁'!$B$17:$AD$141,E$17,FALSE)) -> 5287340 | F48: #VALUE! | G48: =IF($B48="","",VLOOKUP($B48,'明細版-試算頁'!$B$17:$AD$141,G$17,FALSE)) -> 0 | H48: =IF($B48="","",VLOOKUP($B48,'明細版-試算頁'!$B$17:$AD$141,H$17,FALSE)) -> 5087959 | I48: #VALUE! | J48: =IF($B48="","",VLOOKUP($B48,'明細版-試算頁'!$B$17:$AD$141,J$17,FALSE)) -> 5088022 | K48: #VALUE! | L48: =IF(B48="","",G48+H48) -> 5087959 | M48: =IF(J48="","",IF(J48=0,0,G48+J48)) -> 5088022
B49: =IF(B48="","",IF(C48=109,"",B48+1)) -> 26 | C49: =IF($B49="","",VLOOKUP($B49,'明細版-試算頁'!$B$17:$AD$141,C$17,FALSE)) -> 96 | D49: =IF($B49="","",VLOOKUP($B49,'明細版-試算頁'!$B$17:$AD$141,D$17,FALSE)) -> 2655727 | E49: =IF($B49="","",VLOOKUP($B49,'明細版-試算頁'!$B$17:$AD$141,E$17,FALSE)) -> 5424812 | F49: #VALUE! | G49: =IF($B49="","",VLOOKUP($B49,'明細版-試算頁'!$B$17:$AD$141,G$17,FALSE)) -> 0 | H49: =IF($B49="","",VLOOKUP($B49,'明細版-試算頁'!$B$17:$AD$141,H$17,FALSE)) -> 5244056 | I49: #VALUE! | J49: =IF($B49="","",VLOOKUP($B49,'明細版-試算頁'!$B$17:$AD$141,J$17,FALSE)) -> 5244119 | K49: #VALUE! | L49: =IF(B49="","",G49+H49) -> 5244056 | M49: =IF(J49="","",IF(J49=0,0,G49+J49)) -> 5244119
B50: =IF(B49="","",IF(C49=109,"",B49+1)) -> 27 | C50: =IF($B50="","",VLOOKUP($B50,'明細版-試算頁'!$B$17:$AD$141,C$17,FALSE)) -> 97 | D50: =IF($B50="","",VLOOKUP($B50,'明細版-試算頁'!$B$17:$AD$141,D$17,FALSE)) -> 2655727 | E50: =IF($B50="","",VLOOKUP($B50,'明細版-試算頁'!$B$17:$AD$141,E$17,FALSE)) -> 5565857 | F50: #VALUE! | G50: =IF($B50="","",VLOOKUP($B50,'明細版-試算頁'!$B$17:$AD$141,G$17,FALSE)) -> 0 | H50: =IF($B50="","",VLOOKUP($B50,'明細版-試算頁'!$B$17:$AD$141,H$17,FALSE)) -> 5404091 | I50: #VALUE! | J50: =IF($B50="","",VLOOKUP($B50,'明細版-試算頁'!$B$17:$AD$141,J$17,FALSE)) -> 5404149 | K50: #VALUE! | L50: =IF(B50="","",G50+H50) -> 5404091 | M50: =IF(J50="","",IF(J50=0,0,G50+J50)) -> 5404149
B51: =IF(B50="","",IF(C50=109,"",B50+1)) -> 28 | C51: =IF($B51="","",VLOOKUP($B51,'明細版-試算頁'!$B$17:$AD$141,C$17,FALSE)) -> 98 | D51: =IF($B51="","",VLOOKUP($B51,'明細版-試算頁'!$B$17:$AD$141,D$17,FALSE)) -> 2655727 | E51: =IF($B51="","",VLOOKUP($B51,'明細版-試算頁'!$B$17:$AD$141,E$17,FALSE)) -> 5710569 | F51: #VALUE! | G51: =IF($B51="","",VLOOKUP($B51,'明細版-試算頁'!$B$17:$AD$141,G$17,FALSE)) -> 0 | H51: =IF($B51="","",VLOOKUP($B51,'明細版-試算頁'!$B$17:$AD$141,H$17,FALSE)) -> 5566624 | I51: #VALUE! | J51: =IF($B51="","",VLOOKUP($B51,'明細版-試算頁'!$B$17:$AD$141,J$17,FALSE)) -> 5566682 | K51: #VALUE! | L51: =IF(B51="","",G51+H51) -> 5566624 | M51: =IF(J51="","",IF(J51=0,0,G51+J51)) -> 5566682
... B63: =IF(B62="","",IF(C62=109,"",B62+1)) | C63: =IF($B63="","",VLOOKUP($B63,'明細版-試算頁'!$B$17:$AD$141,C$17,FALSE)) | D63: =IF($B63="","",VLOOKUP($B63,'明細版-試算頁'!$B$17:$AD$141,D$17,FALSE)) | E63: =IF($B63="","",VLOOKUP($B63,'明細版-試算頁'!$B$17:$AD$141,E$17,FALSE)) | F63: #VALUE! | G63: =IF($B63="","",VLOOKUP($B63,'明細版-試算頁'!$B$17:$AD$141,G$17,FALSE)) | H63: =IF($B63="","",VLOOKUP($B63,'明細版-試算頁'!$B$17:$AD$141,H$17,FALSE)) | I63: #VALUE! | J63: =IF($B63="","",VLOOKUP($B63,'明細版-試算頁'!$B$17:$AD$141,J$17,FALSE)) | K63: #VALUE! | L63: =IF(B63="","",G63+H63) | M63: =IF(J63="","",IF(J63=0,0,G63+J63))
B64: =$B$18 -> 保單 年度 (末) | C64: =$C$18 -> 保險 年齡 | D64: =$D$18 -> 累積所繳保險費 (A) | E64: =$E$18 -> 假設投保後未來各保單年度宣告利率為4.35% (下表為預估假設值)
E65: =$E$19 -> 含「基本保險金額、累計增加保險金額」 | G65: =$G$19 -> 選擇現金給付 | H65: =$H$19 -> 含「基本保險金額、累計增加保險金額」 | L65: =$L$19 -> (F)=(B)+(D) | M65: =$M$19 -> (G)=(B)+(E)
E66: =$E$20 -> 壽險保障 (身故保險金) | G66: =$G$20 -> 增值回饋 分享金 (B) | H66: =$H$20 -> 年度末現金價值 【含祝壽保險金】 (D) | J66: =$J$20 -> 次年度期初 現金價值 (E)
B67: =IF(B63="","",IF(C63=109,"",B63+1)) | C67: =IF($B67="","",VLOOKUP($B67,'明細版-試算頁'!$B$17:$AD$141,C$17,FALSE)) | D67: =IF($B67="","",VLOOKUP($B67,'明細版-試算頁'!$B$17:$AD$141,D$17,FALSE)) | E67: =IF($B67="","",VLOOKUP($B67,'明細版-試算頁'!$B$17:$AD$141,E$17,FALSE)) | F67: #VALUE! | G67: =IF($B67="","",VLOOKUP($B67,'明細版-試算頁'!$B$17:$AD$141,G$17,FALSE)) | H67: =IF($B67="","",VLOOKUP($B67,'明細版-試算頁'!$B$17:$AD$141,H$17,FALSE)) | I67: #VALUE! | J67: =IF($B67="","",VLOOKUP($B67,'明細版-試算頁'!$B$17:$AD$141,J$17,FALSE)) | K67: #VALUE! | L67: =IF(B67="","",G67+H67) | M67: =IF(J67="","",IF(J67=0,0,G67+J67))
B68: =IF(B67="","",IF(C67=109,"",B67+1)) | C68: =IF($B68="","",VLOOKUP($B68,'明細版-試算頁'!$B$17:$AD$141,C$17,FALSE)) | D68: =IF($B68="","",VLOOKUP($B68,'明細版-試算頁'!$B$17:$AD$141,D$17,FALSE)) | E68: =IF($B68="","",VLOOKUP($B68,'明細版-試算頁'!$B$17:$AD$141,E$17,FALSE)) | F68: #VALUE! | G68: =IF($B68="","",VLOOKUP($B68,'明細版-試算頁'!$B$17:$AD$141,G$17,FALSE)) | H68: =IF($B68="","",VLOOKUP($B68,'明細版-試算頁'!$B$17:$AD$141,H$17,FALSE)) | I68: #VALUE! | J68: =IF($B68="","",VLOOKUP($B68,'明細版-試算頁'!$B$17:$AD$141,J$17,FALSE)) | K68: #VALUE! | L68: =IF(B68="","",G68+H68) | M68: =IF(J68="","",IF(J68=0,0,G68+J68))
B69: =IF(B68="","",IF(C68=109,"",B68+1)) | C69: =IF($B69="","",VLOOKUP($B69,'明細版-試算頁'!$B$17:$AD$141,C$17,FALSE)) | D69: =IF($B69="","",VLOOKUP($B69,'明細版-試算頁'!$B$17:$AD$141,D$17,FALSE)) | E69: =IF($B69="","",VLOOKUP($B69,'明細版-試算頁'!$B$17:$AD$141,E$17,FALSE)) | F69: #VALUE! | G69: =IF($B69="","",VLOOKUP($B69,'明細版-試算頁'!$B$17:$AD$141,G$17,FALSE)) | H69: =IF($B69="","",VLOOKUP($B69,'明細版-試算頁'!$B$17:$AD$141,H$17,FALSE)) | I69: #VALUE! | J69: =IF($B69="","",VLOOKUP($B69,'明細版-試算頁'!$B$17:$AD$141,J$17,FALSE)) | K69: #VALUE! | L69: =IF(B69="","",G69+H69) | M69: =IF(J69="","",IF(J69=0,0,G69+J69))
